Workbook

Sheet Итого Месяцев
A1: СВОДКА ПО МЕСЯЦАМ — СУММЫ (сум)
A2: Категория | B2: 2025г.Ноябрь | C2: 2025г.Декабрь | D2: 2026г.Февраль | E2: 2026г.Март | F2: 2026г.Апрель | G2: 2026г.Май | H2: 2026г.Июнь | I2: 2026г.Июль | J2: Август | K2: Сентябрь | L2: Октябрь | M2: Ноябрь | N2: Декабрь
A3: Оплата рабочих | B3: =SUMIFS('Оплата рабочих'!$F$2:$F$106,'Оплата рабочих'!$A$2:$A$106,">=01.11.2025",'Оплата рабочих'!$A$2:$A$106,"<=30.11.2025") -> 91695000 | C3: =SUMIFS('Оплата рабочих'!$F$4:$F$106,'Оплата рабочих'!$A$4:$A$106,">=01.12.2025",'Оплата рабочих'!$A$4:$A$106,"<=31.12.2025") -> 0 | D3: =SUMIFS('Оплата рабочих'!$F$4:$F$106,'Оплата рабочих'!$A$4:$A$106,">=01.02.2026",'Оплата рабочих'!$A$4:$A$106,"<=28.02.2026") -> 407530000 | E3: =SUMIFS('Оплата рабочих'!$F$4:$F$106,'Оплата рабочих'!$A$4:$A$106,">=01.03.2026",'Оплата рабочих'!$A$4:$A$106,"<=31.03.2026") -> 459180000 | F3: =SUMIFS('Оплата рабочих'!$F$4:$F$106,'Оплата рабочих'!$A$4:$A$106,">=01.04.2026",'Оплата рабочих'!$A$4:$A$106,"<=30.04.2026") -> 0 | G3: =SUMIFS('Оплата рабочих'!$F$4:$F$106,'Оплата рабочих'!$A$4:$A$106,">=01.05.2026",'Оплата рабочих'!$A$4:$A$106,"<=31.05.2026") -> 703280000 | H3: =SUMIFS('Оплата рабочих'!$F$4:$F$106,'Оплата рабочих'!$A$4:$A$106,">=01.06.2026",'Оплата рабочих'!$A$4:$A$106,"<=30.06.2026") -> 937110000
A4: Строй Хоз.Товар | B4: =SUMIFS(Снабжения!$H$3:$H$1022,Снабжения!$A$3:$A$1022,">=01.11.2025",Снабжения!$A$3:$A$1022,"<=30.11.2025") -> 34494036 | C4: =SUMIFS(Снабжения!$H$3:$H$1022,Снабжения!$A$3:$A$1022,">=01.12.2025",Снабжения!$A$3:$A$1022,"<=31.12.2025") -> 0 | D4: =SUMIFS(Снабжения!$H$3:$H$1022,Снабжения!$A$3:$A$1022,">=01.02.2026",Снабжения!$A$3:$A$1022,"<=28.02.2026") -> 83209644 | E4: =SUMIFS(Снабжения!$H$3:$H$1022,Снабжения!$A$3:$A$1022,">=01.03.2026",Снабжения!$A$3:$A$1022,"<=31.03.2026") -> 48394067 | F4: =SUMIFS(Снабжения!$H$3:$H$1022,Снабжения!$A$3:$A$1022,">=01.04.2026",Снабжения!$A$3:$A$1022,"<=30.04.2026") -> 47268860 | G4: =SUMIFS(Снабжения!$H$3:$H$1022,Снабжения!$A$3:$A$1022,">=01.05.2026",Снабжения!$A$3:$A$1022,"<=31.05.2026") -> 46954138 | H4: =SUMIFS(Снабжения!$H$3:$H$1022,Снабжения!$A$3:$A$1022,">=01.06.2026",Снабжения!$A$3:$A$1022,"<=30.06.2026") -> 0
A5: Арматура | B5: =SUMIFS('Арматура приход'!$AB$2:$AB$192,'Арматура приход'!$B$2:$B$192,">=01.11.2025",'Арматура приход'!$B$2:$B$192,"<=30.11.2025") -> 8.4335567e+08 | C5: =SUMIFS('Арматура приход'!$AB$2:$AB$192,'Арматура приход'!$B$2:$B$192,">=01.12.2025",'Арматура приход'!$B$2:$B$192,"<=31.12.2025") -> 0 | D5: =SUMIFS('Арматура приход'!$AB$2:$AB$192,'Арматура приход'!$B$2:$B$192,">=01.02.2026",'Арматура приход'!$B$2:$B$192,"<=28.02.2026") -> 1344752928 | E5: =SUMIFS('Арматура приход'!$AB$2:$AB$192,'Арматура приход'!$B$2:$B$192,">=01.03.2026",'Арматура приход'!$B$2:$B$192,"<=31.03.2026") -> 571152608 | F5: =SUMIFS('Арматура приход'!$AB$2:$AB$192,'Арматура приход'!$B$2:$B$192,">=01.04.2026",'Арматура приход'!$B$2:$B$192,"<=30.04.2026") -> 1175574400 | G5: =SUMIFS('Арматура приход'!$AB$2:$AB$300,'Арматура приход'!$B$2:$B$300,">=01.05.2026",'Арматура приход'!$B$2:$B$300,"<=31.05.2026") -> 1343005248 | H5: =SUMIFS('Арматура приход'!$AB$2:$AB$300,'Арматура приход'!$B$2:$B$300,">=01.06.2026",'Арматура приход'!$B$2:$B$300,"<=30.06.2026") -> 0
A6: Бетон | B6: =SUMIFS(Бетон!$F:$F,Бетон!$A:$A,">=01.11.2025",Бетон!$A:$A,"<=30.11.2025") -> 95090000 | C6: =SUMIFS(Бетон!$F:$F,Бетон!$A:$A,">=01.12.2025",Бетон!$A:$A,"<=31.12.2025") -> 0 | D6: =SUMIFS(Бетон!$F:$F,Бетон!$A:$A,">=01.02.2026",Бетон!$A:$A,"<=28.02.2026") -> 1837510000 | E6: =SUMIFS(Бетон!$F:$F,Бетон!$A:$A,">=01.03.2026",Бетон!$A:$A,"<=31.03.2026") -> 618770000 | F6: =SUMIFS(Бетон!$F:$F,Бетон!$A:$A,">=01.04.2026",Бетон!$A:$A,"<=30.04.2026") -> 752500000 | G6: =SUMIFS(Бетон!$F:$F,Бетон!$A:$A,">=01.05.2026",Бетон!$A:$A,"<=31.05.2026") -> 811300000 | H6: =SUMIFS(Бетон!$F:$F,Бетон!$A:$A,">=01.06.2026",Бетон!$A:$A,"<=30.06.2026") -> 151200000
A7: Опалубка | B7: =SUMIFS(Строй.Мат!$M$2:$M$1010,Строй.Мат!$A$2:$A$1010,">=01.11.2025",Строй.Мат!$A$2:$A$1010,"<=30.11.2025") -> 7100000 | C7: =SUMIFS(Строй.Мат!$M$2:$M$1010,Строй.Мат!$A$2:$A$1010,">=01.12.2025",Строй.Мат!$A$2:$A$1010,"<=31.12.2025") -> 0 | D7: =SUMIFS(Строй.Мат!$M$2:$M$1010,Строй.Мат!$A$2:$A$1010,">=01.02.2026",Строй.Мат!$A$2:$A$1010,"<=28.02.2026") -> 0 | E7: =SUMIFS(Строй.Мат!$M$2:$M$1010,Строй.Мат!$A$2:$A$1010,">=01.03.2026",Строй.Мат!$A$2:$A$1010,"<=31.03.2026") -> 676731600 | F7: =SUMIFS(Строй.Мат!$M$2:$M$1010,Строй.Мат!$A$2:$A$1010,">=01.04.2026",Строй.Мат!$A$2:$A$1010,"<=30.04.2026") -> 1419436000 | G7: =SUMIFS(Строй.Мат!$M$2:$M$1010,Строй.Мат!$A$2:$A$1010,">=01.05.2026",Строй.Мат!$A$2:$A$1010,"<=31.05.2026") -> 8300000 | H7: =SUMIFS(Строй.Мат!$M$2:$M$1010,Строй.Мат!$A$2:$A$1010,">=01.06.2026",Строй.Мат!$A$2:$A$1010,"<=30.06.2026") -> 28500000
A8: Учет Расходов | B8: =SUMIFS(Расходы!$J$2:$J$1000,Расходы!$A$2:$A$1000,">=01.11.2025",Расходы!$A$2:$A$1000,"<=30.11.2025") -> 0 | C8: =SUMIFS(Расходы!$J$2:$J$1000,Расходы!$A$2:$A$1000,">=01.12.2025",Расходы!$A$2:$A$1000,"<=31.12.2025") -> 0 | D8: =SUMIFS(Расходы!$J$2:$J$1000,Расходы!$A$2:$A$1000,">=01.02.2026",Расходы!$A$2:$A$1000,"<=28.02.2026") -> 86333494 | E8: =SUMIFS(Расходы!$J$2:$J$1000,Расходы!$A$2:$A$1000,">=01.03.2026",Расходы!$A$2:$A$1000,"<=31.03.2026") -> 8778300 | F8: =SUMIFS(Расходы!$J$2:$J$1000,Расходы!$A$2:$A$1000,">=01.04.2026",Расходы!$A$2:$A$1000,"<=30.04.2026") -> 6895500 | G8: =SUMIFS(Расходы!$J$2:$J$1000,Расходы!$A$2:$A$1000,">=01.05.2026",Расходы!$A$2:$A$1000,"<=31.05.2026") -> 0 | H8: =SUMIFS(Расходы!$J$2:$J$1000,Расходы!$A$2:$A$1000,">=01.06.2026",Расходы!$A$2:$A$1000,"<=30.06.2026") -> 12000000
A9: Арматура тоннаж | B9: =B18/640 -> 110.444 | C9: =C18/640 -> 0 | D9: =D18/640 -> 173.425 | E9: =E18/640 -> 73.825 | F9: =F18/640 -> 151.96 | G9: =G18/640 -> 274.9 | H9: =H18/640 -> 0
A10: Бозорлик | B10: =SUMIFS(Бозорлик!$F$2:$F$1002,Бозорлик!$A$2:$A$1002,">=01.11.2025",Бозорлик!$A$2:$A$1002,"<=30.11.2025") -> 850000 | C10: =SUMIFS(Бозорлик!$F$2:$F$1002,Бозорлик!$A$2:$A$1002,">=01.12.2025",Бозорлик!$A$2:$A$1002,"<=31.12.2025") -> 0 | D10: =SUMIFS(Бозорлик!$F$2:$F$1002,Бозорлик!$A$2:$A$1002,">=01.02.2026",Бозорлик!$A$2:$A$1002,"<=28.02.2026") -> 17507440 | E10: =SUMIFS(Бозорлик!$F$2:$F$1002,Бозорлик!$A$2:$A$1002,">=01.03.2026",Бозорлик!$A$2:$A$1002,"<=31.03.2026") -> 24949046 | F10: =SUMIFS(Бозорлик!$F$2:$F$1002,Бозорлик!$A$2:$A$1002,">=01.04.2026",Бозорлик!$A$2:$A$1002,"<=30.04.2026") -> 29292191 | G10: =SUMIFS(Бозорлик!$F$2:$F$1002,Бозорлик!$A$2:$A$1002,">=01.05.2026",Бозорлик!$A$2:$A$1002,"<=31.05.2026") -> 40428150 | H10: =SUMIFS(Бозорлик!$F$2:$F$1002,Бозорлик!$A$2:$A$1002,">=01.06.2026",Бозорлик!$A$2:$A$1002,"<=30.06.2026") -> 3285000
A11: Спец.Техника | B11: =SUMIFS(Спец.Техника!$F$2:$F$1018,Спец.Техника!$A$2:$A$1018,">=01.11.2025",Спец.Техника!$A$2:$A$1018,"<=30.11.2025") -> 0 | C11: =SUMIFS(Спец.Техника!$F$2:$F$1018,Спец.Техника!$A$2:$A$1018,">=01.12.2025",Спец.Техника!$A$2:$A$1018,"<=31.12.2025") -> 0 | D11: =SUMIFS(Спец.Техника!$F$2:$F$1018,Спец.Техника!$A$2:$A$1018,">=01.02.2026",Спец.Техника!$A$2:$A$1018,"<=28.02.2026") -> 48390000 | E11: =SUMIFS(Спец.Техника!$F$2:$F$1018,Спец.Техника!$A$2:$A$1018,">=01.03.2026",Спец.Техника!$A$2:$A$1018,"<=31.03.2026") -> 3500000 | F11: =SUMIFS(Спец.Техника!$F$2:$F$1018,Спец.Техника!$A$2:$A$1018,">=01.04.2026",Спец.Техника!$A$2:$A$1018,"<=30.04.2026") -> 2000000 | G11: =SUMIFS(Спец.Техника!$F$2:$F$1018,Спец.Техника!$A$2:$A$1018,">=01.05.2026",Спец.Техника!$A$2:$A$1018,"<=31.05.2026") -> 0 | H11: =SUMIFS(Спец.Техника!$F$2:$F$1018,Спец.Техника!$A$2:$A$1018,">=01.05.2026",Спец.Техника!$A$2:$A$1018,"<=31.05.2026") -> 0
A12: Итого | B12: =SUM(B3:B8,B10,B11) -> 1.0725847e+09 | C12: =SUM(C3:C8,C10,C11) -> 0 | D12: =SUM(D3:D8,D10,D11) -> 3825233506 | E12: =SUM(E3:E8,E10,E11) -> 2.4114556e+09 | F12: =SUM(F3:F8,F10,F11) -> 3.432967e+09 | G12: =SUM(G3:G8,G10,G11) -> 2.9532675e+09 | H12: =SUM(H3:H8) -> 1128810000 | I12: =SUM(I3:I8) -> 0 | J12: =SUM(J3:J8) -> 0 | K12: =SUM(K3:K8) -> 0 | L12: =SUM(L3:L8) -> 0 | M12: =SUM(M3:M8) -> 0 | N12: =SUM(N3:N8) -> 0
A14: СВОДКА ПО МЕСЯЦАМ — ТОННАЖИ И ОБЪЁМЫ
A15: Категория | B15: 2025г.Ноябрь | C15: 2025г.Декабрь | D15: 2026г.Февраль | E15: 2026г.Март | F15: 2026г.Апрель | G15: 2026г.Май | H15: 2026г.Июнь | I15: 2026г.Июль | J15: Август | K15: Сентябрь | L15: Октябрь | M15: Ноябрь | N15: Декабрь
A16: Оплата рабочих | B16: =SUMIFS('Оплата рабочих'!$G$2:$G$115,'Оплата рабочих'!$A$2:$A$115,">=01.11.2025",'Оплата рабочих'!$A$2:$A$115,"<=30.11.2025") -> 7641.25 | C16: =SUMIFS('Оплата рабочих'!$G$2:$G$115,'Оплата рабочих'!$A$2:$A$115,">=01.12.2025",'Оплата рабочих'!$A$2:$A$115,"<=31.12.2025") -> 0 | D16: =SUMIFS('Оплата рабочих'!$G$2:$G$115,'Оплата рабочих'!$A$2:$A$115,">=01.02.2026",'Оплата рабочих'!$A$2:$A$115,"<=28.02.2026") -> 33705.8 | E16: =SUMIFS('Оплата рабочих'!$G$2:$G$115,'Оплата рабочих'!$A$2:$A$115,">=01.03.2026",'Оплата рабочих'!$A$2:$A$115,"<=31.03.2026") -> 37854.905 | F16: =SUMIFS('Оплата рабочих'!$G$2:$G$115,'Оплата рабочих'!$A$2:$A$115,">=01.04.2026",'Оплата рабочих'!$A$2:$A$115,"<=30.04.2026") -> 0 | G16: =SUMIFS('Оплата рабочих'!$G$2:$G$115,'Оплата рабочих'!$A$2:$A$115,">=01.05.2026",'Оплата рабочих'!$A$2:$A$115,"<=31.05.2026") -> 58331.185 | H16: =SUMIFS('Оплата рабочих'!$G$2:$G$115,'Оплата рабочих'!$A$2:$A$115,">=01.06.2026",'Оплата рабочих'!$A$2:$A$115,"<=30.06.2026") -> #DIV/0!
A17: Строй Хоз.Товар | B17: {=SUMPRODUCT((Снабжения!$A$3:$A$1031>=DATE(2025,11,1))*(Снабжения!$A$3:$A$1031<=DATE(2025,11,30))*IFERROR(Снабжения!$P$3:$P$1031*1,0))} -> 2871.8605 | C17: {=SUMPRODUCT((Снабжения!$A$3:$A$1031>=DATE(2025,12,1))*(Снабжения!$A$3:$A$1031<=DATE(2025,12,31))*IFERROR(Снабжения!$P$3:$P$1031*1,0))} -> 0 | D17: {=SUMPRODUCT((Снабжения!$A$3:$A$1031>=DATE(2026,2,1))*(Снабжения!$A$3:$A$1031<=DATE(2026,2,28))*IFERROR(Снабжения!$P$3:$P$1031*1,0))} -> 6859.6783 | E17: {=SUMPRODUCT((Снабжения!$A$3:$A$1031>=DATE(2026,3,1))*(Снабжения!$A$3:$A$1031<=DATE(2026,3,31))*IFERROR(Снабжения!$P$3:$P$1031*1,0))} -> 4004.5189 | F17: {=SUMPRODUCT((Снабжения!$A$3:$A$1031>=DATE(2026,4,1))*(Снабжения!$A$3:$A$1031<=DATE(2026,4,30))*IFERROR(Снабжения!$P$3:$P$1031*1,0))} -> 3913.6016 | G17: {=SUMPRODUCT((Снабжения!$A$3:$A$1031>=DATE(2026,5,1))*(Снабжения!$A$3:$A$1031<=DATE(2026,5,31))*IFERROR(Снабжения!$P$3:$P$1031*1,0))} -> 2737.9202 | H17: =SUMIFS(Снабжения!$P$3:$P$1022,Снабжения!$A$3:$A$1022,">=01.06.2026",Снабжения!$A$3:$A$1022,"<=30.06.2026") -> #DIV/0!
A18: Арматура | B18: =SUMIFS('Арматура приход'!$AD$2:$AD$192,'Арматура приход'!$B$2:$B$192,">=01.11.2025",'Арматура приход'!$B$2:$B$192,"<=30.11.2025") -> 70684.16 | C18: =SUMIFS('Арматура приход'!$X$2:$X$192,'Арматура приход'!$B$2:$B$192,">=01.12.2025",'Арматура приход'!$B$2:$B$192,"<=31.12.2025") -> 0 | D18: =SUMIFS('Арматура приход'!$AD$2:$AD$192,'Арматура приход'!$B$2:$B$192,">=01.02.2026",'Арматура приход'!$B$2:$B$192,"<=28.02.2026") -> 110992 | E18: =SUMIFS('Арматура приход'!$AD$2:$AD$192,'Арматура приход'!$B$2:$B$192,">=01.03.2026",'Арматура приход'!$B$2:$B$192,"<=31.03.2026") -> 47248 | F18: =SUMIFS('Арматура приход'!$AD$2:$AD$300,'Арматура приход'!$B$2:$B$300,">=01.04.2026",'Арматура приход'!$B$2:$B$300,"<=30.04.2026") -> 97254.4 | G18: =SUMIFS('Арматура приход'!$AD$2:$AD$300,'Арматура приход'!$B$2:$B$300,">=01.05.2026",'Арматура приход'!$B$2:$B$300,"<=31.05.2026") -> 175936 | H18: =SUMIFS('Арматура приход'!$AD$2:$AD$300,'Арматура приход'!$B$2:$B$300,">=01.06.2026",'Арматура приход'!$B$2:$B$300,"<=30.06.2026") -> 0
A19: Бетон | B19: =SUMIFS(Бетон!$G:$G,Бетон!$A:$A,">=01.11.2025",Бетон!$A:$A,"<=30.11.2025") -> 8067.6651 | C19: =SUMIFS(Бетон!$G:$G,Бетон!$A:$A,">=01.12.2025",Бетон!$A:$A,"<=31.12.2025") -> 0 | D19: =SUMIFS(Бетон!$G:$G,Бетон!$A:$A,">=01.02.2026",Бетон!$A:$A,"<=28.02.2026") -> 152166.81 | E19: =SUMIFS(Бетон!$G:$G,Бетон!$A:$A,">=01.03.2026",Бетон!$A:$A,"<=31.03.2026") -> 51029.593 | F19: =SUMIFS(Бетон!$G:$G,Бетон!$A:$A,">=01.04.2026",Бетон!$A:$A,"<=30.04.2026") -> 62402.971 | G19: {=SUMPRODUCT((Бетон!$A$2:$A$1086>=DATE(2026,5,1))*(Бетон!$A$2:$A$1086<=DATE(2026,5,31))*IFERROR(Бетон!$G$2:$G$1086*1,0))} -> 53347.41 | H19: =SUMIFS(Бетон!$G:$G,Бетон!$A:$A,">=01.06.2026",Бетон!$A:$A,"<=30.06.2026") -> #DIV/0!
A20: Опалубка | B20: =SUMIFS(Строй.Мат!$P$2:$P$1010,Строй.Мат!$A$2:$A$1010,">=01.11.2025",Строй.Мат!$A$2:$A$1010,"<=30.11.2025") -> 3175.0841 | C20: =SUMIFS(Строй.Мат!$P$2:$P$1010,Строй.Мат!$A$2:$A$1010,">=01.12.2025",Строй.Мат!$A$2:$A$1010,"<=31.12.2025") -> 0 | D20: =SUMIFS(Строй.Мат!$P$2:$P$1010,Строй.Мат!$A$2:$A$1010,">=01.02.2026",Строй.Мат!$A$2:$A$1010,"<=28.02.2026") -> 631.14754 | E20: =SUMIFS(Строй.Мат!$P$2:$P$1010,Строй.Мат!$A$2:$A$1010,">=01.03.2026",Строй.Мат!$A$2:$A$1010,"<=31.03.2026") -> 56295.481 | F20: =SUMIFS(Строй.Мат!$P$2:$P$1010,Строй.Мат!$A$2:$A$1010,">=01.04.2026",Строй.Мат!$A$2:$A$1010,"<=30.04.2026") -> 120399.7 | G20: =SUMIFS(Строй.Мат!$P$2:$P$1010,Строй.Мат!$A$2:$A$1010,">=01.05.2026",Строй.Мат!$A$2:$A$1010,"<=31.05.2026") -> #DIV/0! | H20: =SUMIFS(Строй.Мат!$P$2:$P$1010,Строй.Мат!$A$2:$A$1010,">=01.06.2026",Строй.Мат!$A$2:$A$1010,"<=30.06.2026") -> #DIV/0!
A21: Учет Расходов | B21: {=SUMPRODUCT((Расходы!$A$2:$A$1000>=DATE(2025,11,1))*(Расходы!$A$2:$A$1000<=DATE(2025,11,30))*IFERROR(Расходы!$N$2:$N$1000*1,0))} -> 0 | C21: {=SUMPRODUCT((Расходы!$A$2:$A$1000>=DATE(2025,12,1))*(Расходы!$A$2:$A$1000<=DATE(2025,12,31))*IFERROR(Расходы!$N$2:$N$1000*1,0))} -> 0 | D21: {=SUMPRODUCT((Расходы!$A$2:$A$1000>=DATE(2026,2,1))*(Расходы!$A$2:$A$1000<=DATE(2026,2,28))*IFERROR(Расходы!$N$2:$N$1000*1,0))} -> 7140.7653 | E21: {=SUMPRODUCT((Расходы!$A$2:$A$1000>=DATE(2026,3,1))*(Расходы!$A$2:$A$1000<=DATE(2026,3,31))*IFERROR(Расходы!$N$2:$N$1000*1,0))} -> 728.08768 | F21: {=SUMPRODUCT((Расходы!$A$2:$A$1000>=DATE(2026,4,1))*(Расходы!$A$2:$A$1000<=DATE(2026,4,30))*IFERROR(Расходы!$N$2:$N$1000*1,0))} -> 571.28733 | G21: {=SUMPRODUCT((Расходы!$A$2:$A$1000>=DATE(2026,5,1))*(Расходы!$A$2:$A$1000<=DATE(2026,5,31))*IFERROR(Расходы!$N$2:$N$1000*1,0))} -> 0 | H21: =SUMIFS(Расходы!$N$2:$N$1000,Расходы!$A$2:$A$1000,">=01.06.2026",Расходы!$A$2:$A$1000,"<=30.06.2026") -> #DIV/0!
A22: Арматура тоннаж | B22: =B18/640 -> 110.444 | C22: =C18/640 -> 0 | D22: =D18/640 -> 173.425 | E22: =E18/640 -> 73.825 | F22: =F18/640 -> 151.96 | G22: =G18/640 -> 274.9 | H22: =H18/640 -> 0
A23: Бозорлик | B23: =SUMIFS(Бозорлик!$G$2:$G$1014,Бозорлик!$A$2:$A$1014,">=01.11.2025",Бозорлик!$A$2:$A$1014,"<=30.11.2025") -> 73.275862 | C23: =SUMIFS(Бозорлик!$G$2:$G$1014,Бозорлик!$A$2:$A$1014,">=01.12.2025",Бозорлик!$A$2:$A$1014,"<=31.12.2025") -> 0 | D23: =SUMIFS(Бозорлик!$G$2:$G$1014,Бозорлик!$A$2:$A$1014,">=01.02.2026",Бозорлик!$A$2:$A$1014,"<=28.02.2026") -> 1442.9119 | E23: =SUMIFS(Бозорлик!$G$2:$G$1014,Бозорлик!$A$2:$A$1014,">=01.03.2026",Бозорлик!$A$2:$A$1014,"<=31.03.2026") -> 2062.8628 | F23: =SUMIFS(Бозорлик!$G$2:$G$1014,Бозорлик!$A$2:$A$1014,">=01.04.2026",Бозорлик!$A$2:$A$1014,"<=30.04.2026") -> 2414.8633 | G23: {=SUMPRODUCT((Бозорлик!$A$2:$A$1014>=DATE(2026,5,1))*(Бозорлик!$A$2:$A$1014<=DATE(2026,5,31))*IFERROR(Бозорлик!$G$2:$G$1014*1,0))} -> 2439.3399 | H23: =SUMIFS(Бозорлик!$G$2:$G$1014,Бозорлик!$A$2:$A$1014,">=01.06.2026",Бозорлик!$A$2:$A$1014,"<=30.06.2026") -> #DIV/0!
A24: Спец.Техника | B24: =SUMIFS(Спец.Техника!$G$2:$G$1030,Спец.Техника!$A$2:$A$1030,">=01.11.2025",Спец.Техника!$A$2:$A$1030,"<=30.11.2025") -> 0 | C24: =SUMIFS(Спец.Техника!$G$2:$G$1030,Спец.Техника!$A$2:$A$1030,">=01.12.2025",Спец.Техника!$A$2:$A$1030,"<=31.12.2025") -> 0 | D24: =SUMIFS(Спец.Техника!$G$2:$G$1030,Спец.Техника!$A$2:$A$1030,">=01.02.2026",Спец.Техника!$A$2:$A$1030,"<=28.02.2026") -> 3964.9068 | E24: =SUMIFS(Спец.Техника!$G$2:$G$1030,Спец.Техника!$A$2:$A$1030,">=01.03.2026",Спец.Техника!$A$2:$A$1030,"<=31.03.2026") -> 289.21529 | F24: =SUMIFS(Спец.Техника!$G$2:$G$1030,Спец.Техника!$A$2:$A$1030,">=01.04.2026",Спец.Техника!$A$2:$A$1030,"<=30.04.2026") -> 164.60905 | G24: =SUMIFS(Спец.Техника!$G$2:$G$1030,Спец.Техника!$A$2:$A$1030,">=01.05.2026",Спец.Техника!$A$2:$A$1030,"<=31.05.2026") -> 0 | H24: =SUMIFS(Спец.Техника!$G$2:$G$1030,Спец.Техника!$A$2:$A$1030,">=01.06.2026",Спец.Техника!$A$2:$A$1030,"<=30.06.2026") -> 0
A25: Итого | B25: =SUM(B16:B21,B23:B24) -> 92513.296 | C25: =SUM(C16:C21,C23:C24) -> 0 | D25: =SUM(D16:D21,D23:D24) -> 316904.02 | E25: =SUM(E16:E21,E23:E24) -> 199512.66 | F25: =SUM(F16:F21,F23:F24) -> 287121.43 | G25: =SUM(G16:G21,G23:G24) -> #DIV/0! | H25: =SUM(H16:H21) -> #DIV/0! | I25: =SUM(I16:I21) -> 0 | J25: =SUM(J16:J21) -> 0 | K25: =SUM(K16:K21) -> 0 | L25: =SUM(L16:L21) -> 0 | M25: =SUM(M16:M21) -> 0 | N25: =SUM(N16:N21) -> 0

Sheet Курс валют
A1: Дата | B1: Валюта | C1: Количество | D1: Курс (сум)
A2: 45962 | B2: USD | C2: 1 | D2: 12100
A3: 45963 | B3: USD | C3: 1 | D3: 11970
A4: 45964 | B4: USD | C4: 1 | D4: 11970
A5: 45968 | B5: USD | C5: 1 | D5: 12020
A6: 45973 | B6: USD | C6: 1 | D6: 12000
A7: 45978 | B7: USD | C7: 1 | D7: 11800
A8: 45986 | B8: USD | C8: 1 | D8: 11600
A9: 45990 | B9: USD | C9: 1 | D9: 11600
A10: 46054 | B10: USD | C10: 1 | D10: 12200
A11: 46055 | B11: USD | C11: 1 | D11: 12200
A12: 46056 | B12: USD | C12: 1 | D12: 12200
A13: 46057 | B13: USD | C13: 1 | D13: 12200
... A119: 46163 | B119: USD | C119: 1 | D119: 12130
A120: 46164 | B120: USD | C120: 1
A121: 46165 | B121: USD | C121: 1
A122: 46166 | B122: USD | C122: 1
A123: 46167 | B123: USD | C123: 1
A124: 46168 | B124: USD | C124: 1
A125: 46169 | B125: USD | C125: 1
A126: 46170 | B126: USD | C126: 1
A127: 46171 | B127: USD | C127: 1
A128: 46172 | B128: USD | C128: 1
A129: 46173 | B129: USD | C129: 1
A130: 46174 | B130: USD | C130: 1
A131: 46175 | B131: USD | C131: 1
... A147: 46191 | B147: USD | C147: 1

Sheet Оплата рабочих
A1: Дата | B1: № | C1: Наименование товара | D1: Ед.изм | E1: Кол-во | F1: Сумма | G1: В долларе | H1: Заказчик
A2: 45973 | B2: 1 | C2: Услуга рабочих изоляций | D2: м2 | E2: 1 | F2: 91695000 | G2: =IF(A2<>"", F2 / VLOOKUP(A2, 'Курс валют'!$A:$D, 4, 0), "") -> 7641.25 | H2: Мева Шарбат Илмий Экспериментал Виночилик
A3: 12.11.2025 Итог | F3: =SUBTOTAL(9,F2:F2) -> 91695000 | G3: =IF(A3<>"", F3 / VLOOKUP(A3, 'Курс валют'!$A:$D, 4, 0), "") -> #N/A
A4: 46054 | B4: 1 | C4: Технадзор | D4: зарплата | E4: 1 | F4: 6000000 | G4: =IF(A4<>"", F4 / VLOOKUP(A4, 'Курс валют'!$A:$D, 4, 0), "") -> 491.80328 | H4: Мева Шарбат Илмий Экспериментал Виночилик
A5: 46054 | B5: 2 | C5: Геодезист | D5: зарплата | E5: 1 | F5: 7000000 | G5: =IF(A5<>"", F5 / VLOOKUP(A5, 'Курс валют'!$A:$D, 4, 0), "") -> 573.77049 | H5: Мева Шарбат Илмий Экспериментал Виночилик
A6: 46054 | B6: 3 | C6: Прораб | D6: зарплата | E6: 1 | F6: 10000000 | G6: =IF(A6<>"", F6 / VLOOKUP(A6, 'Курс валют'!$A:$D, 4, 0), "") -> 819.67213 | H6: Мева Шарбат Илмий Экспериментал Виночилик
A7: 46054 | B7: 4 | C7: ТБ и ОТ | D7: зарплата | E7: 1 | F7: 4000000 | G7: =IF(A7<>"", F7 / VLOOKUP(A7, 'Курс валют'!$A:$D, 4, 0), "") -> 327.86885 | H7: Мева Шарбат Илмий Экспериментал Виночилик
A8: 46054 | B8: 5 | C8: Крановщик | D8: зарплата | E8: 1 | F8: 10000000 | G8: =IF(A8<>"", F8 / VLOOKUP(A8, 'Курс валют'!$A:$D, 4, 0), "") -> 819.67213 | H8: Мева Шарбат Илмий Экспериментал Виночилик
A9: 01.02.2026 Итог | F9: =SUBTOTAL(9,F4:F8) -> 37000000 | G9: =IF(A9<>"", F9 / VLOOKUP(A9, 'Курс валют'!$A:$D, 4, 0), "") -> #N/A
A10: 46081 | B10: 1 | C10: Бетон | D10: м2 | E10: 2414 | F10: =145000*E10 -> 350030000 | G10: =IF(A10<>"", F10 / VLOOKUP(A10, 'Курс валют'!$A:$D, 4, 0), "") -> 28975.993 | H10: Мева Шарбат Илмий Экспериментал Виночилик
A11: 46081 | B11: 2 | C11: Вертолет | D11: м2 | E11: 2050 | F11: =10000*E11 -> 20500000 | G11: =IF(A11<>"", F11 / VLOOKUP(A11, 'Курс валют'!$A:$D, 4, 0), "") -> 1697.0199 | H11: Мева Шарбат Илмий Экспериментал Виночилик
A12: 28.02.2026 Итог | F12: =SUBTOTAL(9,F10:F11) -> 370530000 | G12: =IF(A12<>"", F12 / VLOOKUP(A12, 'Курс валют'!$A:$D, 4, 0), "") -> #N/A
A13: 46112 | B13: 1 | C13: Бетон | D13: м2 | E13: 3530 | F13: =E13*115000 -> 405950000 | G13: =IF(A13<>"", F13 / VLOOKUP(A13, 'Курс валют'!$A:$D, 4, 0), "") -> 33466.612 | H13: Мева Шарбат Илмий Экспериментал Виночилик
A14: 46112 | B14: 2 | C14: Вертолет | D14: м2 | E14: 923 | F14: =10000*E14 -> 9230000 | G14: =IF(A14<>"", F14 / VLOOKUP(A14, 'Курс валют'!$A:$D, 4, 0), "") -> 760.92333 | H14: Мева Шарбат Илмий Экспериментал Виночилик
A15: 46112 | B15: 3 | C15: Технадзор | D15: зарплата | E15: 1 | F15: 6000000 | G15: =IF(A15<>"", F15 / VLOOKUP(A15, 'Курс валют'!$A:$D, 4, 0), "") -> 494.64138 | H15: Мева Шарбат Илмий Экспериментал Виночилик
A16: 46112 | B16: 4 | C16: Геодезист | D16: зарплата | E16: 1 | F16: 7000000 | G16: =IF(A16<>"", F16 / VLOOKUP(A16, 'Курс валют'!$A:$D, 4, 0), "") -> 577.08162 | H16: Мева Шарбат Илмий Экспериментал Виночилик
A17: 46112 | B17: 5 | C17: Прораб | D17: зарплата | E17: 1 | F17: 10000000 | G17: =IF(A17<>"", F17 / VLOOKUP(A17, 'Курс валют'!$A:$D, 4, 0), "") -> 824.40231 | H17: Мева Шарбат Илмий Экспериментал Виночилик
A18: 46112 | B18: 6 | C18: ТБ и ОТ | D18: зарплата | E18: 1 | F18: 4000000 | G18: =IF(A18<>"", F18 / VLOOKUP(A18, 'Курс валют'!$A:$D, 4, 0), "") -> 329.76092 | H18: Мева Шарбат Илмий Экспериментал Виночилик
A19: 46112 | B19: 7 | C19: Крановщик | D19: зарплата | E19: 1 | F19: 12000000 | G19: =IF(A19<>"", F19 / VLOOKUP(A19, 'Курс валют'!$A:$D, 4, 0), "") -> 989.28277 | H19: Мева Шарбат Илмий Экспериментал Виночилик
A20: 46112 | B20: 8 | C20: Повар | D20: зарплата | E20: 1 | F20: 5000000 | G20: =IF(A20<>"", F20 / VLOOKUP(A20, 'Курс валют'!$A:$D, 4, 0), "") -> 412.20115 | H20: Мева Шарбат Илмий Экспериментал Виночилик
A21: 31.03.2026 Итог | F21: =SUBTOTAL(9,F13:F20) -> 459180000 | G21: =IF(A21<>"", F21 / VLOOKUP(A21, 'Курс валют'!$A:$D, 4, 0), "") -> #N/A
A22: Общий итог | F22: =SUBTOTAL(9,F2:F20) -> 958405000 | G22: =IF(A22<>"", F22 / VLOOKUP(A22, 'Курс валют'!$A:$D, 4, 0), "") -> #N/A
A23: 46143 | B23: 1 | C23: Бетон | D23: м2 | F23: 400000000 | G23: =IF(A23<>"", F23 / VLOOKUP(A23, 'Курс валют'!$A:$D, 4, 0), "") -> 33057.851 | H23: Мева Шарбат Илмий Экспериментал Виночилик
A24: 46146 | B24: 2 | C24: Бетон | D24: м2 | F24: 170000000 | G24: =IF(A24<>"", F24 / VLOOKUP(A24, 'Курс валют'!$A:$D, 4, 0), "") -> 14166.667 | H24: Мева Шарбат Илмий Экспериментал Виночилик
A25: 46147 | B25: 3 | C25: Бетон | D25: м2 | F25: 133280000 | G25: =IF(A25<>"", F25 / VLOOKUP(A25, 'Курс валют'!$A:$D, 4, 0), "") -> 11106.667 | H25: Мева Шарбат Илмий Экспериментал Виночилик
A26: 46174 | B26: 1 | C26: Бетон | D26: м2 | F26: 450000000 | G26: =IF(A26<>"", F26 / VLOOKUP(A26, 'Курс валют'!$A:$D, 4, 0), "") -> #DIV/0! | H26: Мева Шарбат Илмий Экспериментал Виночилик
A27: 46176 | B27: 1 | C27: Бетон | D27: м2 | F27: 350000000 | G27: =IF(A27<>"", F27 / VLOOKUP(A27, '[1]Курс валют'!$A:$D, 4, 0), "") -> #DIV/0! | H27: Мева Шарбат Илмий Экспериментал Виночилик
A28: 46176 | B28: 2 | C28: Изоляция | D28: м2 | F28: 3360000 | G28: =IF(A28<>"", F28 / VLOOKUP(A28, '[1]Курс валют'!$A:$D, 4, 0), "") -> #DIV/0! | H28: Мева Шарбат Илмий Экспериментал Виночилик
A29: 46178 | B29: 1 | C29: Бетон | D29: м2 | F29: 133750000 | G29: =IF(A29<>"", F29 / VLOOKUP(A29, '[1]Курс валют'!$A:$D, 4, 0), "") -> #DIV/0! | H29: Мева Шарбат Илмий Экспериментал Виночилик
G30: =IF(A30<>"", F30 / VLOOKUP(A30, '[1]Курс валют'!$A:$D, 4, 0), "")

Sheet Бозорлик
A1: Дата | B1: Наименование | C1: Ед.изм | D1: Кол-во | E1: Сумма за ед.изм | F1: Общая | G1: В долларе | H1: Столбец1
A2: 45986 | B2: Сабзи | C2: кг | D2: 60 | E2: 7000 | F2: =[1]Бозорлик!$D2*[1]Бозорлик!$E2 -> 420000 | G2: =IF(A2<>"", F2/ VLOOKUP(A2, 'Курс валют'!$A:$D, 4, 0), "") -> 36.206897
A3: 45986 | B3: Пиёз | C3: кг | D3: 35 | E3: 4000 | F3: =[1]Бозорлик!$D3*[1]Бозорлик!$E3 -> 140000 | G3: =IF(A3<>"", F3/ VLOOKUP(A3, 'Курс валют'!$A:$D, 4, 0), "") -> 12.068966
A4: 45986 | B4: Ёг | C4: литр | D4: 10 | E4: 21000 | F4: =[1]Бозорлик!$D4*[1]Бозорлик!$E4 -> 210000 | G4: =IF(A4<>"", F4/ VLOOKUP(A4, 'Курс валют'!$A:$D, 4, 0), "") -> 18.103448
A5: 45986 | B5: Туруп | C5: кг | D5: 10 | E5: 7000 | F5: =[1]Бозорлик!$D5*[1]Бозорлик!$E5 -> 70000 | G5: =IF(A5<>"", F5/ VLOOKUP(A5, 'Курс валют'!$A:$D, 4, 0), "") -> 6.0344828
A6: 45986 | B6: Арава | C6: услуга | D6: 1 | E6: 10000 | F6: =[1]Бозорлик!$D6*[1]Бозорлик!$E6 -> 10000 | G6: =IF(A6<>"", F6/ VLOOKUP(A6, 'Курс валют'!$A:$D, 4, 0), "") -> 0.86206897
A7: 25.11.2025 Итог | F7: =SUBTOTAL(9,F2:F6) -> 850000 | G7: =IF(A7<>"", F7/ VLOOKUP(A7, 'Курс валют'!$A:$D, 4, 0), "") -> #N/A
A8: 46060 | B8: Пахта ёг | C8: литр | D8: 10 | E8: 20000 | F8: =[1]Бозорлик!$D8*[1]Бозорлик!$E8 -> 200000 | G8: =IF(A8<>"", F8/ VLOOKUP(A8, 'Курс валют'!$A:$D, 4, 0), "") -> 16.393443
A9: 46060 | B9: Томат | C9: шт | D9: 3 | E9: 30000 | F9: =[1]Бозорлик!$D9*[1]Бозорлик!$E9 -> 90000 | G9: =IF(A9<>"", F9/ VLOOKUP(A9, 'Курс валют'!$A:$D, 4, 0), "") -> 7.3770492
A10: 46060 | B10: Макарон | C10: кг | D10: 24 | E10: 10000 | F10: =[1]Бозорлик!$D10*[1]Бозорлик!$E10 -> 240000 | G10: =IF(A10<>"", F10/ VLOOKUP(A10, 'Курс валют'!$A:$D, 4, 0), "") -> 19.672131
A11: 46060 | B11: Картошка | C11: кг | D11: 44 | E11: 7500 | F11: =[1]Бозорлик!$D11*[1]Бозорлик!$E11 -> 330000 | G11: =IF(A11<>"", F11/ VLOOKUP(A11, 'Курс валют'!$A:$D, 4, 0), "") -> 27.04918
A12: 46060 | B12: Сабзи | C12: кг | D12: 61 | E12: 5900 | F12: =[1]Бозорлик!$D12*[1]Бозорлик!$E12 -> 359900 | G12: =IF(A12<>"", F12/ VLOOKUP(A12, 'Курс валют'!$A:$D, 4, 0), "") -> 29.5
A13: 46060 | B13: Туз | C13: блок | D13: 1 | E13: 100000 | F13: =[1]Бозорлик!$D13*[1]Бозорлик!$E13 -> 100000 | G13: =IF(A13<>"", F13/ VLOOKUP(A13, 'Курс валют'!$A:$D, 4, 0), "") -> 8.1967213
A14: 46060 | B14: Тухум | C14: решетка | D14: 6 | E14: 45000 | F14: =[1]Бозорлик!$D14*[1]Бозорлик!$E14 -> 270000 | G14: =IF(A14<>"", F14/ VLOOKUP(A14, 'Курс валют'!$A:$D, 4, 0), "") -> 22.131148
A15: 46060 | B15: Сарёг | C15: кг | D15: 2 | E15: 45000 | F15: =[1]Бозорлик!$D15*[1]Бозорлик!$E15 -> 90000 | G15: =IF(A15<>"", F15/ VLOOKUP(A15, 'Курс валют'!$A:$D, 4, 0), "") -> 7.3770492
A16: 46060 | B16: Чеснок | C16: кг | D16: 2 | E16: 30000 | F16: =[1]Бозорлик!$D16*[1]Бозорлик!$E16 -> 60000 | G16: =IF(A16<>"", F16/ VLOOKUP(A16, 'Курс валют'!$A:$D, 4, 0), "") -> 4.9180328
A17: 46060 | B17: Канд | C17: кг | D17: 10 | E17: 15000 | F17: =[1]Бозорлик!$D17*[1]Бозорлик!$E17 -> 150000 | G17: =IF(A17<>"", F17/ VLOOKUP(A17, 'Курс валют'!$A:$D, 4, 0), "") -> 12.295082
A18: 46060 | B18: Филе | C18: кг | D18: 10 | E18: 46000 | F18: =[1]Бозорлик!$D18*[1]Бозорлик!$E18 -> 460000 | G18: =IF(A18<>"", F18/ VLOOKUP(A18, 'Курс валют'!$A:$D, 4, 0), "") -> 37.704918
A19: 07.02.2026 Итог | F19: =SUBTOTAL(9,F8:F18) -> 2349900 | G19: =IF(A19<>"", F19/ VLOOKUP(A19, 'Курс валют'!$A:$D, 4, 0), "") -> #N/A
A20: 46063 | B20: Пахта ёг | C20: литр | D20: 10 | E20: 20000 | F20: =[1]Бозорлик!$D20*[1]Бозорлик!$E20 -> 200000 | G20: =IF(A20<>"", F20/ VLOOKUP(A20, 'Курс валют'!$A:$D, 4, 0), "") -> 16.393443
A21: 46063 | B21: Писта ёг | C21: литр | D21: 10 | E21: 20000 | F21: =[1]Бозорлик!$D21*[1]Бозорлик!$E21 -> 200000 | G21: =IF(A21<>"", F21/ VLOOKUP(A21, 'Курс валют'!$A:$D, 4, 0), "") -> 16.393443
A22: 46063 | B22: Гушт | C22: кг | D22: 20 | E22: 80000 | F22: =[1]Бозорлик!$D22*[1]Бозорлик!$E22 -> 1600000 | G22: =IF(A22<>"", F22/ VLOOKUP(A22, 'Курс валют'!$A:$D, 4, 0), "") -> 131.14754
A23: 46063 | B23: Тухум | C23: решетка | D23: 10 | E23: 45000 | F23: =[1]Бозорлик!$D23*[1]Бозорлик!$E23 -> 450000 | G23: =IF(A23<>"", F23/ VLOOKUP(A23, 'Курс валют'!$A:$D, 4, 0), "") -> 36.885246
A24: 46063 | B24: Сарёг | C24: кг | D24: 5 | E24: 45000 | F24: =[1]Бозорлик!$D24*[1]Бозорлик!$E24 -> 225000 | G24: =IF(A24<>"", F24/ VLOOKUP(A24, 'Курс валют'!$A:$D, 4, 0), "") -> 18.442623
A25: 46063 | B25: Пиёз | C25: кг | D25: 37 | E25: 3500 | F25: =[1]Бозорлик!$D25*[1]Бозорлик!$E25 -> 129500 | G25: =IF(A25<>"", F25/ VLOOKUP(A25, 'Курс валют'!$A:$D, 4, 0), "") -> 10.614754
A26: 46063 | B26: Сабзи | C26: кг | D26: 129 | E26: 6000 | F26: =[1]Бозорлик!$D26*[1]Бозорлик!$E26 -> 774000 | G26: =IF(A26<>"", F26/ VLOOKUP(A26, 'Курс валют'!$A:$D, 4, 0), "") -> 63.442623
A27: 46063 | B27: Туруп | C27: кг | D27: 44 | E27: 6000 | F27: =[1]Бозорлик!$D27*[1]Бозорлик!$E27 -> 264000 | G27: =IF(A27<>"", F27/ VLOOKUP(A27, 'Курс валют'!$A:$D, 4, 0), "") -> 21.639344
A28: 46063 | B28: Пичок | C28: шт | D28: 5 | E28: 10000 | F28: =[1]Бозорлик!$D28*[1]Бозорлик!$E28 -> 50000 | G28: =IF(A28<>"", F28/ VLOOKUP(A28, 'Курс валют'!$A:$D, 4, 0), "") -> 4.0983607
A29: 46063 | B29: Боз | C29: метр | D29: 5 | E29: 14000 | F29: =[1]Бозорлик!$D29*[1]Бозорлик!$E29 -> 70000 | G29: =IF(A29<>"", F29/ VLOOKUP(A29, 'Курс валют'!$A:$D, 4, 0), "") -> 5.7377049
A30: 10.02.2026 Итог | F30: =SUBTOTAL(9,F20:F29) -> 3962500 | G30: =IF(A30<>"", F30/ VLOOKUP(A30, 'Курс валют'!$A:$D, 4, 0), "") -> #N/A
A31: 46067 | B31: Гуруч | C31: кг | D31: 160 | E31: 14000 | F31: =[1]Бозорлик!$D31*[1]Бозорлик!$E31 -> 2240000 | G31: =IF(A31<>"", F31/ VLOOKUP(A31, 'Курс валют'!$A:$D, 4, 0), "") -> 183.90805
A32: 14.02.2026 Итог | F32: =SUBTOTAL(9,F31:F31) -> 2240000 | G32: =IF(A32<>"", F32/ VLOOKUP(A32, 'Курс валют'!$A:$D, 4, 0), "") -> #N/A
A33: 46070 | B33: Гушт | C33: кг | D33: 5 | E33: 90000 | F33: =[1]Бозорлик!$D33*[1]Бозорлик!$E33 -> 450000 | G33: =IF(A33<>"", F33/ VLOOKUP(A33, 'Курс валют'!$A:$D, 4, 0), "") -> 37.037037
A34: 46070 | B34: Кук чой | C34: кг | D34: 2 | E34: 70000 | F34: =[1]Бозорлик!$D34*[1]Бозорлик!$E34 -> 140000 | G34: =IF(A34<>"", F34/ VLOOKUP(A34, 'Курс валют'!$A:$D, 4, 0), "") -> 11.522634
A35: 46070 | B35: Сарёг | C35: кг | D35: 7 | E35: 50000 | F35: =[1]Бозорлик!$D35*[1]Бозорлик!$E35 -> 350000 | G35: =IF(A35<>"", F35/ VLOOKUP(A35, 'Курс валют'!$A:$D, 4, 0), "") -> 28.806584
A36: 46070 | B36: Тухум | C36: решетка | D36: 10 | E36: 45000 | F36: =[1]Бозорлик!$D36*[1]Бозорлик!$E36 -> 450000 | G36: =IF(A36<>"", F36/ VLOOKUP(A36, 'Курс валют'!$A:$D, 4, 0), "") -> 37.037037
A37: 46070 | B37: Гречка | C37: кг | D37: 10 | E37: 14000 | F37: =[1]Бозорлик!$D37*[1]Бозорлик!$E37 -> 140000 | G37: =IF(A37<>"", F37/ VLOOKUP(A37, 'Курс валют'!$A:$D, 4, 0), "") -> 11.522634
A38: 46070 | B38: Доставка | C38: услуга | D38: 1 | E38: 70000 | F38: =[1]Бозорлик!$D38*[1]Бозорлик!$E38 -> 70000 | G38: =IF(A38<>"", F38/ VLOOKUP(A38, 'Курс валют'!$A:$D, 4, 0), "") -> 5.7613169
A39: 17.02.2026 Итог | F39: =SUBTOTAL(9,F33:F38) -> 1600000 | G39: =IF(A39<>"", F39/ VLOOKUP(A39, 'Курс валют'!$A:$D, 4, 0), "") -> #N/A
A40: 46071 | B40: Гушт | C40: кг | D40: 18 | E40: 100000 | F40: =[1]Бозорлик!$D40*[1]Бозорлик!$E40 -> 1800000 | G40: =IF(A40<>"", F40/ VLOOKUP(A40, 'Курс валют'!$A:$D, 4, 0), "") -> 149.00662
A41: 46071 | B41: Доставка | C41: услуга | D41: 1 | E41: 120000 | F41: =[1]Бозорлик!$D41*[1]Бозорлик!$E41 -> 120000 | G41: =IF(A41<>"", F41/ VLOOKUP(A41, 'Курс валют'!$A:$D, 4, 0), "") -> 9.9337748
A42: 18.02.2026 Итог | F42: =SUBTOTAL(9,F40:F41) -> 1920000 | G42: =IF(A42<>"", F42/ VLOOKUP(A42, 'Курс валют'!$A:$D, 4, 0), "") -> #N/A
A43: 46075 | B43: Канд | C43: кг | D43: 20 | E43: 16000 | F43: =[1]Бозорлик!$D43*[1]Бозорлик!$E43 -> 320000 | G43: =IF(A43<>"", F43/ VLOOKUP(A43, 'Курс валют'!$A:$D, 4, 0), "") -> 26.666667
A44: 46075 | B44: Чеснок | C44: кг | D44: 2 | E44: 30000 | F44: =[1]Бозорлик!$D44*[1]Бозорлик!$E44 -> 60000 | G44: =IF(A44<>"", F44/ VLOOKUP(A44, 'Курс валют'!$A:$D, 4, 0), "") -> 5
A45: 46075 | B45: Пахта ёг | C45: литр | D45: 10 | E45: 21000 | F45: =[1]Бозорлик!$D45*[1]Бозорлик!$E45 -> 210000 | G45: =IF(A45<>"", F45/ VLOOKUP(A45, 'Курс валют'!$A:$D, 4, 0), "") -> 17.5
A46: 46075 | B46: Писта ёг | C46: литр | D46: 10 | E46: 22000 | F46: =[1]Бозорлик!$D46*[1]Бозорлик!$E46 -> 220000 | G46: =IF(A46<>"", F46/ VLOOKUP(A46, 'Курс валют'!$A:$D, 4, 0), "") -> 18.333333
A47: 46075 | B47: Тухум | C47: решетка | D47: 10 | E47: 45000 | F47: =[1]Бозорлик!$D47*[1]Бозорлик!$E47 -> 450000 | G47: =IF(A47<>"", F47/ VLOOKUP(A47, 'Курс валют'!$A:$D, 4, 0), "") -> 37.5
A48: 46075 | B48: Картошка | C48: кг | D48: 68 | E48: 7280 | F48: =[1]Бозорлик!$D48*[1]Бозорлик!$E48 -> 495040 | G48: =IF(A48<>"", F48/ VLOOKUP(A48, 'Курс валют'!$A:$D, 4, 0), "") -> 41.253333
A49: 46075 | B49: Томат | C49: шт | D49: 2 | E49: 30000 | F49: =[1]Бозорлик!$D49*[1]Бозорлик!$E49 -> 60000 | G49: =IF(A49<>"", F49/ VLOOKUP(A49, 'Курс валют'!$A:$D, 4, 0), "") -> 5
A50: 46075 | B50: Доставка | C50: услуга | D50: 1 | E50: 80000 | F50: =[1]Бозорлик!$D50*[1]Бозорлик!$E50 -> 80000 | G50: =IF(A50<>"", F50/ VLOOKUP(A50, 'Курс валют'!$A:$D, 4, 0), "") -> 6.6666667
A51: 22.02.2026 Итог | F51: =SUBTOTAL(9,F43:F50) -> 1895040 | G51: =IF(A51<>"", F51/ VLOOKUP(A51, 'Курс валют'!$A:$D, 4, 0), "") -> #N/A
A52: 46080 | B52: Тухум | C52: решетка | D52: 10 | E52: 45000 | F52: =[1]Бозорлик!$D52*[1]Бозорлик!$E52 -> 450000 | G52: =IF(A52<>"", F52/ VLOOKUP(A52, 'Курс валют'!$A:$D, 4, 0), "") -> 37.251656
A53: 46080 | B53: Пиёз | C53: кг | D53: 36.25 | E53: 4000 | F53: =[1]Бозорлик!$D53*[1]Бозорлик!$E53 -> 145000 | G53: =IF(A53<>"", F53/ VLOOKUP(A53, 'Курс валют'!$A:$D, 4, 0), "") -> 12.003311
A54: 46080 | B54: Кук чой | C54: кг | D54: 2 | E54: 70000 | F54: =[1]Бозорлик!$D54*[1]Бозорлик!$E54 -> 140000 | G54: =IF(A54<>"", F54/ VLOOKUP(A54, 'Курс валют'!$A:$D, 4, 0), "") -> 11.589404
A55: 46080 | B55: Туруп | C55: кг | D55: 30 | E55: 6000 | F55: =[1]Бозорлик!$D55*[1]Бозорлик!$E55 -> 180000 | G55: =IF(A55<>"", F55/ VLOOKUP(A55, 'Курс валют'!$A:$D, 4, 0), "") -> 14.900662
A56: 46080 | B56: Гушт | C56: кг | D56: 25 | E56: 105000 | F56: =[1]Бозорлик!$D56*[1]Бозорлик!$E56 -> 2625000 | G56: =IF(A56<>"", F56/ VLOOKUP(A56, 'Курс валют'!$A:$D, 4, 0), "") -> 217.30132
A57: 27.02.2026 Итог | F57: =SUBTOTAL(9,F52:F56) -> 3540000 | G57: =IF(A57<>"", F57/ VLOOKUP(A57, 'Курс валют'!$A:$D, 4, 0), "") -> #N/A
A58: 46085 | B58: Гушт | C58: кг | D58: 27.5 | E58: 105000 | F58: =[1]Бозорлик!$D58*[1]Бозорлик!$E58 -> 2887500 | G58: =IF(A58<>"", F58/ VLOOKUP(A58, 'Курс валют'!$A:$D, 4, 0), "") -> 239.03146
A59: 04.03.2026 Итог | F59: =SUBTOTAL(9,F58:F58) -> 2887500 | G59: =IF(A59<>"", F59/ VLOOKUP(A59, 'Курс валют'!$A:$D, 4, 0), "") -> #N/A
A60: 46088 | B60: Сабзи | C60: кг | D60: 60 | E60: 6000 | F60: =[1]Бозорлик!$D60*[1]Бозорлик!$E60 -> 360000 | G60: =IF(A60<>"", F60/ VLOOKUP(A60, 'Курс валют'!$A:$D, 4, 0), "") -> 29.752066
A61: 46088 | B61: Тухум | C61: решетка | D61: 15 | E61: 48000 | F61: =[1]Бозорлик!$D61*[1]Бозорлик!$E61 -> 720000 | G61: =IF(A61<>"", F61/ VLOOKUP(A61, 'Курс валют'!$A:$D, 4, 0), "") -> 59.504132
A62: 46088 | B62: Сарёг | C62: кг | D62: 10 | E62: 48000 | F62: =[1]Бозорлик!$D62*[1]Бозорлик!$E62 -> 480000 | G62: =IF(A62<>"", F62/ VLOOKUP(A62, 'Курс валют'!$A:$D, 4, 0), "") -> 39.669421
A63: 46088 | B63: Чеснок | C63: кг | D63: 2 | E63: 30000 | F63: =[1]Бозорлик!$D63*[1]Бозорлик!$E63 -> 60000 | G63: =IF(A63<>"", F63/ VLOOKUP(A63, 'Курс валют'!$A:$D, 4, 0), "") -> 4.9586777
A64: 46088 | B64: Макарон | C64: кг | D64: 12 | E64: 12000 | F64: =[1]Бозорлик!$D64*[1]Бозорлик!$E64 -> 144000 | G64: =IF(A64<>"", F64/ VLOOKUP(A64, 'Курс валют'!$A:$D, 4, 0), "") -> 11.900826
A65: 46088 | B65: Пиёз | C65: кг | D65: 34 | E65: 4000 | F65: =[1]Бозорлик!$D65*[1]Бозорлик!$E65 -> 136000 | G65: =IF(A65<>"", F65/ VLOOKUP(A65, 'Курс валют'!$A:$D, 4, 0), "") -> 11.239669
A66: 46088 | B66: Пахта ёг | C66: лт | D66: 10 | E66: 21000 | F66: =[1]Бозорлик!$D66*[1]Бозорлик!$E66 -> 210000 | G66: =IF(A66<>"", F66/ VLOOKUP(A66, 'Курс валют'!$A:$D, 4, 0), "") -> 17.355372
A67: 46088 | B67: Писта ёг | C67: лт | D67: 10 | E67: 22000 | F67: =[1]Бозорлик!$D67*[1]Бозорлик!$E67 -> 220000 | G67: =IF(A67<>"", F67/ VLOOKUP(A67, 'Курс валют'!$A:$D, 4, 0), "") -> 18.181818
A68: 46088 | B68: Доставка | C68: услуга | D68: 1 | E68: 120000 | F68: =[1]Бозорлик!$D68*[1]Бозорлик!$E68 -> 120000 | G68: =IF(A68<>"", F68/ VLOOKUP(A68, 'Курс валют'!$A:$D, 4, 0), "") -> 9.9173554
A69: 07.03.2026 Итог | F69: =SUBTOTAL(9,F60:F68) -> 2450000 | G69: =IF(A69<>"", F69/ VLOOKUP(A69, 'Курс валют'!$A:$D, 4, 0), "") -> #N/A
A70: 46090 | B70: Гушт | C70: кг | D70: 20 | E70: 100000 | F70: =[1]Бозорлик!$D70*[1]Бозорлик!$E70 -> 2000000 | G70: =IF(A70<>"", F70/ VLOOKUP(A70, 'Курс валют'!$A:$D, 4, 0), "") -> 165.56291
A71: 09.03.2026 Итог | F71: =SUBTOTAL(9,F70:F70) -> 2000000 | G71: =IF(A71<>"", F71/ VLOOKUP(A71, 'Курс валют'!$A:$D, 4, 0), "") -> #N/A
A72: 46092 | B72: гуруч | C72: кг | D72: 80 | E72: 13000 | F72: =[1]Бозорлик!$D72*[1]Бозорлик!$E72 -> 1040000 | G72: =IF(A72<>"", F72/ VLOOKUP(A72, 'Курс валют'!$A:$D, 4, 0), "") -> 85.950413
A73: 11.03.2026 Итог | F73: =SUBTOTAL(9,F72:F72) -> 1040000 | G73: =IF(A73<>"", F73/ VLOOKUP(A73, 'Курс валют'!$A:$D, 4, 0), "") -> #N/A
A74: 46096 | B74: Тухум | C74: решетка | D74: 15 | E74: 48000 | F74: =[1]Бозорлик!$D74*[1]Бозорлик!$E74 -> 720000 | G74: =IF(A74<>"", F74/ VLOOKUP(A74, 'Курс валют'!$A:$D, 4, 0), "") -> 59.504132
A75: 46096 | B75: Пахта ёг | C75: литр | D75: 10 | E75: 22000 | F75: =[1]Бозорлик!$D75*[1]Бозорлик!$E75 -> 220000 | G75: =IF(A75<>"", F75/ VLOOKUP(A75, 'Курс валют'!$A:$D, 4, 0), "") -> 18.181818
A76: 46096 | B76: Писта ёг | C76: литр | D76: 10 | E76: 23000 | F76: =[1]Бозорлик!$D76*[1]Бозорлик!$E76 -> 230000 | G76: =IF(A76<>"", F76/ VLOOKUP(A76, 'Курс валют'!$A:$D, 4, 0), "") -> 19.008264
A77: 46096 | B77: Кук чой | C77: кг | D77: 2 | E77: 70000 | F77: =[1]Бозорлик!$D77*[1]Бозорлик!$E77 -> 140000 | G77: =IF(A77<>"", F77/ VLOOKUP(A77, 'Курс валют'!$A:$D, 4, 0), "") -> 11.570248
A78: 46096 | B78: Макарон | C78: кг | D78: 12 | E78: 12500 | F78: =[1]Бозорлик!$D78*[1]Бозорлик!$E78 -> 150000 | G78: =IF(A78<>"", F78/ VLOOKUP(A78, 'Курс валют'!$A:$D, 4, 0), "") -> 12.396694
A79: 46096 | B79: Томат | C79: шт | D79: 2 | E79: 35000 | F79: =[1]Бозорлик!$D79*[1]Бозорлик!$E79 -> 70000 | G79: =IF(A79<>"", F79/ VLOOKUP(A79, 'Курс валют'!$A:$D, 4, 0), "") -> 5.785124
A80: 46096 | B80: Чеснок | C80: кг | D80: 2 | E80: 30000 | F80: =[1]Бозорлик!$D80*[1]Бозорлик!$E80 -> 60000 | G80: =IF(A80<>"", F80/ VLOOKUP(A80, 'Курс валют'!$A:$D, 4, 0), "") -> 4.9586777
A81: 46096 | B81: Сабзи | C81: кг | D81: 114.16 | E81: 6000 | F81: =[1]Бозорлик!$D81*[1]Бозорлик!$E81 -> 684960 | G81: =IF(A81<>"", F81/ VLOOKUP(A81, 'Курс валют'!$A:$D, 4, 0), "") -> 56.608264
A82: 15.03.2026 Итог | F82: =SUBTOTAL(9,F74:F81) -> 2274960 | G82: =IF(A82<>"", F82/ VLOOKUP(A82, 'Курс валют'!$A:$D, 4, 0), "") -> #N/A
A83: 46097 | B83: Гушт | C83: кг | D83: 25 | E83: 100000 | F83: =[1]Бозорлик!$D83*[1]Бозорлик!$E83 -> 2500000 | G83: =IF(A83<>"", F83/ VLOOKUP(A83, 'Курс валют'!$A:$D, 4, 0), "") -> 208.33333
A84: 16.03.2026 Итог | F84: =SUBTOTAL(9,F83:F83) -> 2500000 | G84: =IF(A84<>"", F84/ VLOOKUP(A84, 'Курс валют'!$A:$D, 4, 0), "") -> #N/A
A85: 46102 | B85: Туруп | C85: кг | D85: 45 | E85: 6000 | F85: =[1]Бозорлик!$D85*[1]Бозорлик!$E85 -> 270000 | G85: =IF(A85<>"", F85/ VLOOKUP(A85, 'Курс валют'!$A:$D, 4, 0), "") -> 22.350993
A86: 46102 | B86: Сарёг | C86: кг | D86: 10 | E86: 48000 | F86: =[1]Бозорлик!$D86*[1]Бозорлик!$E86 -> 480000 | G86: =IF(A86<>"", F86/ VLOOKUP(A86, 'Курс валют'!$A:$D, 4, 0), "") -> 39.735099
A87: 46102 | B87: Тухум | C87: решетка | D87: 15 | E87: 48000 | F87: =[1]Бозорлик!$D87*[1]Бозорлик!$E87 -> 720000 | G87: =IF(A87<>"", F87/ VLOOKUP(A87, 'Курс валют'!$A:$D, 4, 0), "") -> 59.602649
A88: 46102 | B88: Мош | C88: кг | D88: 20 | E88: 15000 | F88: =[1]Бозорлик!$D88*[1]Бозорлик!$E88 -> 300000 | G88: =IF(A88<>"", F88/ VLOOKUP(A88, 'Курс валют'!$A:$D, 4, 0), "") -> 24.834437
A89: 46102 | B89: Картошка | C89: кг | D89: 60 | E89: 8500 | F89: =[1]Бозорлик!$D89*[1]Бозорлик!$E89 -> 510000 | G89: =IF(A89<>"", F89/ VLOOKUP(A89, 'Курс валют'!$A:$D, 4, 0), "") -> 42.218543
A90: 46102 | B90: Пиёз | C90: кг | D90: 34 | E90: 4000 | F90: =[1]Бозорлик!$D90*[1]Бозорлик!$E90 -> 136000 | G90: =IF(A90<>"", F90/ VLOOKUP(A90, 'Курс валют'!$A:$D, 4, 0), "") -> 11.258278
A91: 46102 | B91: Пахта ёг | C91: литр | D91: 5 | E91: 24000 | F91: =[1]Бозорлик!$D91*[1]Бозорлик!$E91 -> 120000 | G91: =IF(A91<>"", F91/ VLOOKUP(A91, 'Курс валют'!$A:$D, 4, 0), "") -> 9.9337748
A92: 46102 | B92: Писта ёг | C92: литр | D92: 5 | E92: 24000 | F92: =[1]Бозорлик!$D92*[1]Бозорлик!$E92 -> 120000 | G92: =IF(A92<>"", F92/ VLOOKUP(A92, 'Курс валют'!$A:$D, 4, 0), "") -> 9.9337748
A93: 46102 | B93: Канд | C93: кг | D93: 20 | E93: 17000 | F93: =[1]Бозорлик!$D93*[1]Бозорлик!$E93 -> 340000 | G93: =IF(A93<>"", F93/ VLOOKUP(A93, 'Курс валют'!$A:$D, 4, 0), "") -> 28.145695
A94: 46102 | B94: Кук чой | C94: кг | D94: 2 | E94: 70000 | F94: =[1]Бозорлик!$D94*[1]Бозорлик!$E94 -> 140000 | G94: =IF(A94<>"", F94/ VLOOKUP(A94, 'Курс валют'!$A:$D, 4, 0), "") -> 11.589404
A95: 21.03.2026 Итог | F95: =SUBTOTAL(9,F85:F94) -> 3136000 | G95: =IF(A95<>"", F95/ VLOOKUP(A95, 'Курс валют'!$A:$D, 4, 0), "") -> #N/A
A96: 46106 | B96: Гушт | C96: кг | D96: 25 | E96: 100000 | F96: =[1]Бозорлик!$D96*[1]Бозорлик!$E96 -> 2500000 | G96: =IF(A96<>"", F96/ VLOOKUP(A96, 'Курс валют'!$A:$D, 4, 0), "") -> 204.7502
A97: 25.03.2026 Итог | F97: =SUBTOTAL(9,F96:F96) -> 2500000 | G97: =IF(A97<>"", F97/ VLOOKUP(A97, 'Курс валют'!$A:$D, 4, 0), "") -> #N/A
A98: 46111 | B98: Тухум | C98: решетка | D98: 15 | E98: 48000 | F98: =[1]Бозорлик!$D98*[1]Бозорлик!$E98 -> 720000 | G98: =IF(A98<>"", F98/ VLOOKUP(A98, 'Курс валют'!$A:$D, 4, 0), "") -> 59.504132
A99: 46111 | B99: Пахта ёг | C99: литр | D99: 15 | E99: 24000 | F99: =[1]Бозорлик!$D99*[1]Бозорлик!$E99 -> 360000 | G99: =IF(A99<>"", F99/ VLOOKUP(A99, 'Курс валют'!$A:$D, 4, 0), "") -> 29.752066
A100: 46111 | B100: Писта ёг | C100: литр | D100: 10 | E100: 26000 | F100: =[1]Бозорлик!$D100*[1]Бозорлик!$E100 -> 260000 | G100: =IF(A100<>"", F100/ VLOOKUP(A100, 'Курс валют'!$A:$D, 4, 0), "") -> 21.487603
...

Sheet Снабжения
A1: КАРТОЧКА СКЛАДСКОГО УЧЕТА ТОВАРА
A2: Дата | B2: Наименование | C2: Ед.Изм | D2: Категория | E2: Приход | F2: Расход | G2: Цена за ед. | H2: Сумма прихода | I2: Сумма расхода | J2: Статус заказа | K2: Способ оплаты | L2: Кому отдано | M2: Ед.из | N2: Остатка | O2: Поставщик/Получатель
A3: 45962 | B3: Арава | C3: шт | D3: Прочее | E3: 4 | F3: 0 | G3: 690000 | H3: =G3*E3 -> 2760000 | I3: =H3*F3 -> 0 | J3: Завершен | K3: Наличные | M3: шт | N3: =SUMIF(B:B,B3,E:E)-SUMIF(B:B,B3,F:F) -> 4 | P3: =IF(A3<>"", Снабжения!H3 / VLOOKUP(A3, 'Курс валют'!$A:$D, 4, 0), "") -> 228.09917
A4: 45962 | B4: Лопата штиковой | C4: шт | D4: Ручной инструменты | E4: 10 | F4: 0 | G4: 17739 | H4: =G4*E4 -> 177390 | I4: =H4*F4 -> 0 | J4: Завершен | K4: Наличные | M4: шт | N4: =SUMIF(B:B,B4,E:E)-SUMIF(B:B,B4,F:F) -> 10 | P4: =IF(A4<>"", Снабжения!H4 / VLOOKUP(A4, 'Курс валют'!$A:$D, 4, 0), "") -> 14.660331
A5: 45962 | B5: Лопата сопковой | C5: шт | D5: Ручной инструменты | E5: 10 | F5: 0 | G5: 17739 | H5: =G5*E5 -> 177390 | I5: =H5*F5 -> 0 | J5: Завершен | K5: Наличные | M5: шт | N5: =SUMIF(B:B,B5,E:E)-SUMIF(B:B,B5,F:F) -> 5 | P5: =IF(A5<>"", Снабжения!H5 / VLOOKUP(A5, 'Курс валют'!$A:$D, 4, 0), "") -> 14.660331
A6: 45962 | B6: Кетмон | C6: шт | D6: Ручной инструменты | E6: 10 | F6: 0 | G6: 32562 | H6: =G6*E6 -> 325620 | I6: =H6*F6 -> 0 | J6: Завершен | K6: Наличные | M6: шт | N6: =SUMIF(B:B,B6,E:E)-SUMIF(B:B,B6,F:F) -> 10 | P6: =IF(A6<>"", Снабжения!H6 / VLOOKUP(A6, 'Курс валют'!$A:$D, 4, 0), "") -> 26.910744
A7: 45962 | B7: Даста лопата | C7: шт | D7: Ручной инструменты | E7: 20 | F7: 7 | G7: 8000 | H7: =G7*E7 -> 160000 | I7: =G7*F7 -> 56000 | J7: Завершен | K7: Наличные | M7: шт | N7: =SUMIF(B:B,B7,E:E)-SUMIF(B:B,B7,F:F) -> 13 | O7: 6 | P7: =IF(A7<>"", Снабжения!H7 / VLOOKUP(A7, 'Курс валют'!$A:$D, 4, 0), "") -> 13.22314
A8: 45962 | B8: Даста кетмон | C8: шт | D8: Ручной инструменты | E8: 10 | F8: 7 | G8: 8000 | H8: =G8*E8 -> 80000 | I8: =G8*F8 -> 56000 | J8: Завершен | K8: Наличные | M8: шт | N8: =SUMIF(B:B,B8,E:E)-SUMIF(B:B,B8,F:F) -> 3 | O8: 0 | P8: =IF(A8<>"", Снабжения!H8 / VLOOKUP(A8, 'Курс валют'!$A:$D, 4, 0), "") -> 6.6115702
A9: 45962 | B9: Леска | C9: шт | E9: 40 | F9: 13 | G9: 3280.5 | H9: =G9*E9 -> 131220 | I9: =G9*F9 -> 42646.5 | J9: Завершен | K9: Наличные | M9: лт | N9: =SUMIF(B:B,B9,E:E)-SUMIF(B:B,B9,F:F) -> 22 | O9: 5 | P9: =IF(A9<>"", Снабжения!H9 / VLOOKUP(A9, 'Курс валют'!$A:$D, 4, 0), "") -> 10.844628
A10: 45962 | B10: Кувалда | C10: шт | D10: Ручной инструменты | E10: 2 | F10: 0 | G10: 95700 | H10: =G10*E10 -> 191400 | I10: =G10*F10 -> 0 | J10: Завершен | K10: Наличные | M10: шт | N10: =SUMIF(B:B,B10,E:E)-SUMIF(B:B,B10,F:F) -> 2 | P10: =IF(A10<>"", Снабжения!H10 / VLOOKUP(A10, 'Курс валют'!$A:$D, 4, 0), "") -> 15.818182
A11: 45962 | B11: Болта | C11: шт | D11: Ручной инструменты | E11: 2 | F11: 0 | H11: =73554+60021 -> 133575 | I11: =G11*F11 -> 0 | J11: Завершен | K11: Наличные | M11: шт | N11: =SUMIF(B:B,B11,E:E)-SUMIF(B:B,B11,F:F) -> 2 | P11: =IF(A11<>"", Снабжения!H11 / VLOOKUP(A11, 'Курс валют'!$A:$D, 4, 0), "") -> 11.039256
A12: 45962 | B12: Болга | C12: шт | D12: Ручной инструменты | E12: 2 | F12: 0 | H12: =29281.5+26851.5 -> 56133 | I12: =G12*F12 -> 0 | J12: Завершен | K12: Наличные | M12: шт | N12: =SUMIF(B:B,B12,E:E)-SUMIF(B:B,B12,F:F) -> 10 | P12: =IF(A12<>"", Снабжения!H12 / VLOOKUP(A12, 'Курс валют'!$A:$D, 4, 0), "") -> 4.6390909
A13: 45962 | B13: Мих 70мм | C13: кг | D13: Мет.из | E13: 20 | G13: 11421 | H13: =G13*E13 -> 228420 | I13: =G13*F13 -> 0 | J13: Завершен | K13: Наличные | M13: шт | N13: =SUMIF(B:B,B13,E:E)-SUMIF(B:B,B13,F:F) -> 40 | O13: 98 | P13: =IF(A13<>"", Снабжения!H13 / VLOOKUP(A13, 'Курс валют'!$A:$D, 4, 0), "") -> 18.877686
A14: 45962 | B14: Мих 100мм | C14: кг | D14: Мет.из | E14: 20 | G14: 11421 | H14: =G14*E14 -> 228420 | I14: =G14*F14 -> 0 | J14: Завершен | K14: Наличные | M14: шт | N14: =SUMIF(B:B,B14,E:E)-SUMIF(B:B,B14,F:F) -> 20 | O14: 80 | P14: =IF(A14<>"", Снабжения!H14 / VLOOKUP(A14, 'Курс валют'!$A:$D, 4, 0), "") -> 18.877686
A15: 45962 | B15: Перчатка | C15: шт | E15: 100 | F15: 30 | G15: 1400 | H15: =G15*E15 -> 140000 | I15: =G15*F15 -> 42000 | J15: Завершен | K15: Наличные | M15: шт | N15: =SUMIF(B:B,B15,E:E)-SUMIF(B:B,B15,F:F) -> 309 | O15: 162 | P15: =IF(A15<>"", Снабжения!H15 / VLOOKUP(A15, 'Курс валют'!$A:$D, 4, 0), "") -> 11.570248
A16: 45962 | B16: Дюбель мих 50 | C16: кг | D16: Мет.из | E16: 20 | G16: 28066.5 | H16: =G16*E16 -> 561330 | I16: =G16*F16 -> 0 | J16: Завершен | K16: Наличные | M16: шт | N16: =SUMIF(B:B,B16,E:E)-SUMIF(B:B,B16,F:F) -> 80 | P16: =IF(A16<>"", Снабжения!H16 / VLOOKUP(A16, 'Курс валют'!$A:$D, 4, 0), "") -> 46.390909
A17: 45962 | B17: Аэрозол Красный | C17: шт | E17: 4 | F17: 4 | G17: 10935 | H17: =G17*E17 -> 43740 | I17: =G17*F17 -> 43740 | J17: Завершен | K17: Наличные | M17: шт | N17: =SUMIF(B:B,B17,E:E)-SUMIF(B:B,B17,F:F) -> 2 | P17: =IF(A17<>"", Снабжения!H17 / VLOOKUP(A17, 'Курс валют'!$A:$D, 4, 0), "") -> 3.614876
A18: 45964 | B18: Болгарка большая О220 | C18: шт | D18: Электроинструменты | E18: 1 | F18: 0 | G18: 748305 | H18: =E18*G18 -> 748305 | I18: =G18*F18 -> 0 | J18: Завершен | K18: Наличные | M18: шт | N18: =SUMIF(B:B,B18,E:E)-SUMIF(B:B,B18,F:F) -> 1 | P18: =IF(A18<>"", Снабжения!H18 / VLOOKUP(A18, 'Курс валют'!$A:$D, 4, 0), "") -> 62.515038
A19: 45964 | B19: Больгарка средняя О180 | C19: шт | D19: Электроинструменты | E19: 1 | F19: 0 | G19: 526585 | H19: =E19*G19 -> 526585 | I19: =G19*F19 -> 0 | J19: Завершен | K19: Наличные | M19: шт | N19: =SUMIF(B:B,B19,E:E)-SUMIF(B:B,B19,F:F) -> 1 | P19: =IF(A19<>"", Снабжения!H19 / VLOOKUP(A19, 'Курс валют'!$A:$D, 4, 0), "") -> 43.992063
A20: 45964 | B20: Пчелка О180 | C20: шт | D20: Электроинструменты | E20: 2 | F20: 0 | G20: 554300 | H20: =E20*G20 -> 1108600 | I20: =G20*F20 -> 0 | J20: Завершен | K20: Наличные | M20: шт | N20: =SUMIF(B:B,B20,E:E)-SUMIF(B:B,B20,F:F) -> 3 | P20: =IF(A20<>"", Снабжения!H20 / VLOOKUP(A20, 'Курс валют'!$A:$D, 4, 0), "") -> 92.614871
A21: 45964 | B21: Вибратор 4м-6м | C21: шт | D21: Электроинструменты | E21: 2 | F21: 0 | G21: =970025+1121132 -> 2091157 | H21: =970025+1121132 -> 2091157 | I21: =G21*F21 -> 0 | J21: Завершен | K21: Наличные | M21: шт | N21: =SUMIF(B:B,B21,E:E)-SUMIF(B:B,B21,F:F) -> 1 | P21: =IF(A21<>"", Снабжения!H21 / VLOOKUP(A21, 'Курс валют'!$A:$D, 4, 0), "") -> 174.69983
A22: 45964 | B22: Уровень длина(80см) | C22: шт | D22: Прочее | E22: 2 | F22: 0 | G22: 60250 | H22: =E22*G22 -> 120500 | I22: =G22*F22 -> 0 | J22: Завершен | K22: Наличные | M22: шт | N22: =SUMIF(B:B,B22,E:E)-SUMIF(B:B,B22,F:F) -> 2 | P22: =IF(A22<>"", Снабжения!H22 / VLOOKUP(A22, 'Курс валют'!$A:$D, 4, 0), "") -> 10.066834
A23: 45964 | B23: Уровень длина(60см) | C23: шт | D23: Прочее | E23: 2 | F23: 0 | G23: 51212.5 | H23: =E23*G23 -> 102425 | I23: =G23*F23 -> 0 | J23: Завершен | K23: Наличные | M23: шт | N23: =SUMIF(B:B,B23,E:E)-SUMIF(B:B,B23,F:F) -> 3 | P23: =IF(A23<>"", Снабжения!H23 / VLOOKUP(A23, 'Курс валют'!$A:$D, 4, 0), "") -> 8.5568087
A24: 45964 | B24: Отвес большой | C24: кг | D24: Прочее | E24: 1 | F24: 0 | G24: 9881 | H24: =E24*G24 -> 9881 | I24: =G24*F24 -> 0 | J24: Завершен | K24: Наличные | M24: шт | N24: =SUMIF(B:B,B24,E:E)-SUMIF(B:B,B24,F:F) -> 1 | P24: =IF(A24<>"", Снабжения!H24 / VLOOKUP(A24, 'Курс валют'!$A:$D, 4, 0), "") -> 0.82548037
A25: 45964 | B25: Шруповерт с аккум | C25: шт | D25: Электроинструменты | E25: 2 | F25: 0 | G25: 1108600 | H25: =E25*G25 -> 2217200 | I25: =G25*F25 -> 0 | J25: Завершен | K25: Наличные | M25: кг | N25: =SUMIF(B:B,B25,E:E)-SUMIF(B:B,B25,F:F) -> 2 | P25: =IF(A25<>"", Снабжения!H25 / VLOOKUP(A25, 'Курс валют'!$A:$D, 4, 0), "") -> 185.22974
A26: 45964 | B26: Перфоратор | C26: шт | D26: Электроинструменты | E26: 2 | F26: 0 | G26: 831450 | H26: =E26*G26 -> 1662900 | I26: =G26*F26 -> 0 | J26: Завершен | K26: Наличные | M26: м | N26: =SUMIF(B:B,B26,E:E)-SUMIF(B:B,B26,F:F) -> 2 | P26: =IF(A26<>"", Снабжения!H26 / VLOOKUP(A26, 'Курс валют'!$A:$D, 4, 0), "") -> 138.92231
A27: 45964 | B27: Тройник | C27: шт | D27: Электрика | E27: 10 | F27: 8 | G27: 10604 | H27: =E27*G27 -> 106040 | I27: =G27*F27 -> 84832 | J27: Завершен | K27: Наличные | M27: м | N27: =SUMIF(B:B,B27,E:E)-SUMIF(B:B,B27,F:F) -> 11 | O27: 12 | P27: =IF(A27<>"", Снабжения!H27 / VLOOKUP(A27, 'Курс валют'!$A:$D, 4, 0), "") -> 8.8588137
A28: 45964 | B28: Вилка | C28: шт | D28: Электрика | E28: 10 | F28: 0 | G28: 3374 | H28: =E28*G28 -> 33740 | I28: =G28*F28 -> 0 | J28: Завершен | K28: Наличные | M28: шт | N28: =SUMIF(B:B,B28,E:E)-SUMIF(B:B,B28,F:F) -> 8 | O28: 6 | P28: =IF(A28<>"", Снабжения!H28 / VLOOKUP(A28, 'Курс валют'!$A:$D, 4, 0), "") -> 2.8187135
A29: 45968 | B29: Этик Резина | C29: шт | D29: Прочее | E29: 20 | F29: 1 | G29: 55000 | H29: =20*55000 -> 1100000 | I29: =G29*F29 -> 55000 | J29: Завершен | K29: Наличные | M29: шт | N29: =SUMIF(B:B,B29,E:E)-SUMIF(B:B,B29,F:F) -> 19 | P29: =IF(A29<>"", Снабжения!H29 / VLOOKUP(A29, 'Курс валют'!$A:$D, 4, 0), "") -> 91.514143
A30: 45968 | B30: Метр 10м | C30: шт | D30: Прочее | E30: 5 | F30: 5 | G30: 31691 | H30: =5*31691 -> 158455 | I30: =G30*F30 -> 158455 | J30: Завершен | K30: Наличные | M30: шт | N30: =SUMIF(B:B,B30,E:E)-SUMIF(B:B,B30,F:F) -> 9 | P30: =IF(A30<>"", Снабжения!H30 / VLOOKUP(A30, 'Курс валют'!$A:$D, 4, 0), "") -> 13.182612
A31: 45968 | B31: Метр 5м | C31: шт | D31: Прочее | E31: 10 | F31: 10 | G31: 15062 | H31: =10*15062 -> 150620 | I31: =G31*F31 -> 150620 | J31: Завершен | K31: Наличные | M31: шт | N31: =SUMIF(B:B,B31,E:E)-SUMIF(B:B,B31,F:F) -> 10 | O31: 0 | P31: =IF(A31<>"", Снабжения!H31 / VLOOKUP(A31, 'Курс валют'!$A:$D, 4, 0), "") -> 12.530782
A32: 45968 | B32: Маркер | C32: шт | D32: Прочее | E32: 20 | F32: 2 | G32: 1205 | H32: =20*1205 -> 24100 | I32: =G32*F32 -> 2410 | J32: Завершен | K32: Наличные | M32: шт | N32: =SUMIF(B:B,B32,E:E)-SUMIF(B:B,B32,F:F) -> 128 | O32: 30 | P32: =IF(A32<>"", Снабжения!H32 / VLOOKUP(A32, 'Курс валют'!$A:$D, 4, 0), "") -> 2.0049917
A33: 45968 | B33: Мель | C33: шт | D33: Прочее | E33: 200 | F33: 2 | I33: =G33*F33 -> 0 | J33: Завершен | K33: Наличные | M33: почка | N33: =SUMIF(B:B,B33,E:E)-SUMIF(B:B,B33,F:F) -> 405 | O33: 525 | P33: =IF(A33<>"", Снабжения!H33 / VLOOKUP(A33, 'Курс валют'!$A:$D, 4, 0), "") -> 0
A34: 45968 | B34: Кабель ПВС 2х2,5 | C34: м | D34: Электрика | E34: 200 | F34: 190 | G34: 12652.64 | H34: =200*12652.64 -> 2530528 | I34: =G34*F34 -> 2404001.6 | J34: Завершен | K34: Наличные | M34: почка | N34: =SUMIF(B:B,B34,E:E)-SUMIF(B:B,B34,F:F) -> 74.5 | P34: =IF(A34<>"", Снабжения!H34 / VLOOKUP(A34, 'Курс валют'!$A:$D, 4, 0), "") -> 210.52646
A35: 45968 | B35: Кабель оддий 3х1,5 | C35: м | D35: Электрика | E35: 40 | F35: 40 | G35: 10163 | H35: =40*10163 -> 406520 | I35: =G35*F35 -> 406520 | J35: Завершен | K35: Наличные | M35: шт | N35: =SUMIF(B:B,B35,E:E)-SUMIF(B:B,B35,F:F) -> 0 | P35: =IF(A35<>"", Снабжения!H35 / VLOOKUP(A35, 'Курс валют'!$A:$D, 4, 0), "") -> 33.8203
A36: 45968 | B36: Акрил лампа 18W | C36: шт | D36: Электрика | E36: 4 | F36: 3 | G36: 14580.5 | H36: =4*14580.5 -> 58322 | I36: =G36*F36 -> 43741.5 | J36: Завершен | K36: Наличные | M36: шт | N36: =SUMIF(B:B,B36,E:E)-SUMIF(B:B,B36,F:F) -> 1 | P36: =IF(A36<>"", Снабжения!H36 / VLOOKUP(A36, 'Курс валют'!$A:$D, 4, 0), "") -> 4.8520799
A37: 45968 | B37: Акрил лампа 24W | C37: шт | D37: Электрика | E37: 1 | F37: 0 | G37: =17232 -> 17232 | H37: =17232 -> 17232 | I37: =G37*F37 -> 0 | J37: Завершен | K37: Наличные | M37: кг | N37: =SUMIF(B:B,B37,E:E)-SUMIF(B:B,B37,F:F) -> 1 | P37: =IF(A37<>"", Снабжения!H37 / VLOOKUP(A37, 'Курс валют'!$A:$D, 4, 0), "") -> 1.4336106
A38: 45968 | B38: Тройник | C38: шт | D38: Электрика | E38: 3 | F38: 3 | G38: 45488 | H38: =3*45488 -> 136464 | I38: =G38*F38 -> 136464 | J38: Завершен | K38: Наличные | M38: кг | N38: =SUMIF(B:B,B38,E:E)-SUMIF(B:B,B38,F:F) -> 11 | P38: =IF(A38<>"", Снабжения!H38 / VLOOKUP(A38, 'Курс валют'!$A:$D, 4, 0), "") -> 11.353078
A39: 45968 | B39: Акрил Лампа (Квадрат) | C39: шт | D39: Электрика | E39: 5 | F39: 5 | G39: 33000 | H39: =33000*5 -> 165000 | I39: =G39*F39 -> 165000 | J39: Завершен | K39: Наличные | M39: кг | N39: =SUMIF(B:B,B39,E:E)-SUMIF(B:B,B39,F:F) -> 0 | P39: =IF(A39<>"", Снабжения!H39 / VLOOKUP(A39, 'Курс валют'!$A:$D, 4, 0), "") -> 13.727121
A40: 45968 | B40: Вилка | C40: шт | D40: Электрика | E40: 3 | F40: 3 | G40: 13616 | H40: =3*13616 -> 40848 | I40: =G40*F40 -> 40848 | J40: Завершен | K40: Наличные | M40: рулон | N40: =SUMIF(B:B,B40,E:E)-SUMIF(B:B,B40,F:F) -> 8 | P40: =IF(A40<>"", Снабжения!H40 / VLOOKUP(A40, 'Курс валют'!$A:$D, 4, 0), "") -> 3.3983361
A41: 45968 | B41: Ошхона(Приборы) | H41: =520000+100000 -> 620000 | I41: =G41*F41 -> 0 | J41: Завершен | K41: Наличные | M41: шт | N41: =SUMIF(B:B,B41,E:E)-SUMIF(B:B,B41,F:F) -> 0 | P41: =IF(A41<>"", Снабжения!H41 / VLOOKUP(A41, 'Курс валют'!$A:$D, 4, 0), "") -> 51.580699
A42: 45973 | B42: Электрод MP-3 2.5 | C42: кг | D42: Расходники | E42: 20 | F42: 10 | G42: 42421.5 | H42: =G42*E42 -> 848430 | I42: =G42*F42 -> 424215 | J42: Завершен | K42: Наличные | M42: шт | N42: =SUMIF(B:B,B42,E:E)-SUMIF(B:B,B42,F:F) -> 41.5 | O42: 10 | P42: =IF(A42<>"", Снабжения!H42 / VLOOKUP(A42, 'Курс валют'!$A:$D, 4, 0), "") -> 70.7025
A43: 45973 | B43: Диск Отрезной 230 | C43: шт | D43: Расходники | E43: 25 | F43: 14 | G43: 11929.5 | H43: =G43*E43 -> 298237.5 | I43: =G43*F43 -> 167013 | J43: Завершен | K43: Наличные | M43: шт | N43: =SUMIF(B:B,B43,E:E)-SUMIF(B:B,B43,F:F) -> 87 | P43: =IF(A43<>"", Снабжения!H43 / VLOOKUP(A43, 'Курс валют'!$A:$D, 4, 0), "") -> 24.853125
A44: 45973 | B44: Диск Отрезной 180 | C44: шт | D44: Расходники | E44: 25 | F44: 10 | G44: 9037.5 | H44: =G44*E44 -> 225937.5 | I44: =G44*F44 -> 90375 | J44: Завершен | K44: Наличные | M44: шт | N44: =SUMIF(B:B,B44,E:E)-SUMIF(B:B,B44,F:F) -> 42 | O44: 0 | P44: =IF(A44<>"", Снабжения!H44 / VLOOKUP(A44, 'Курс валют'!$A:$D, 4, 0), "") -> 18.828125
A45: 45973 | B45: Диск тахта 180 | C45: шт | D45: Расходники | E45: 10 | F45: 0 | G45: 66275 | H45: =G45*E45 -> 662750 | I45: =G45*F45 -> 0 | J45: Завершен | K45: Наличные | M45: шт | N45: =SUMIF(B:B,B45,E:E)-SUMIF(B:B,B45,F:F) -> 8 | P45: =IF(A45<>"", Снабжения!H45 / VLOOKUP(A45, 'Курс валют'!$A:$D, 4, 0), "") -> 55.229167
A46: 45973 | B46: Бурь 14*160 | C46: шт | D46: Расходники | E46: 10 | F46: 0 | G46: 9037.5 | H46: =G46*E46 -> 90375 | I46: =G46*F46 -> 0 | J46: Завершен | K46: Наличные | M46: шт | N46: =SUMIF(B:B,B46,E:E)-SUMIF(B:B,B46,F:F) -> 8 | P46: =IF(A46<>"", Снабжения!H46 / VLOOKUP(A46, 'Курс валют'!$A:$D, 4, 0), "") -> 7.53125
A47: 45973 | B47: Сверло Тахта 18мм | C47: шт | D47: Расходники | E47: 20 | F47: 20 | G47: 10122 | H47: =G47*E47 -> 202440 | I47: =G47*F47 -> 202440 | J47: Завершен | K47: Наличные | M47: шт | N47: =SUMIF(B:B,B47,E:E)-SUMIF(B:B,B47,F:F) -> 20 | P47: =IF(A47<>"", Снабжения!H47 / VLOOKUP(A47, 'Курс валют'!$A:$D, 4, 0), "") -> 16.87
A48: 45973 | B48: Сверло по металлу 5мм | C48: шт | D48: Расходники | E48: 50 | F48: 0 | G48: 4338 | H48: =G48*E48 -> 216900 | I48: =G48*F48 -> 0 | J48: Завершен | K48: Наличные | M48: шт | N48: =SUMIF(B:B,B48,E:E)-SUMIF(B:B,B48,F:F) -> 43 | O48: 20 | P48: =IF(A48<>"", Снабжения!H48 / VLOOKUP(A48, 'Курс валют'!$A:$D, 4, 0), "") -> 18.075
A49: 45973 | B49: Перчатка | C49: шт | D49: Расходники | E49: 100 | F49: 70 | G49: 4699.5 | H49: =G49*E49 -> 469950 | I49: =G49*F49 -> 328965 | J49: Завершен | K49: Наличные | M49: шт | N49: =SUMIF(B:B,B49,E:E)-SUMIF(B:B,B49,F:F) -> 309 | P49: =IF(A49<>"", Снабжения!H49 / VLOOKUP(A49, 'Курс валют'!$A:$D, 4, 0), "") -> 39.1625
A50: 45973 | B50: Болторез 900мм | C50: шт | D50: Ручной инструменты | E50: 1 | F50: 1 | G50: 249796.5 | H50: =G50*E50 -> 249796.5 | I50: =G50*F50 -> 249796.5 | J50: Завершен | K50: Наличные | M50: шт | N50: =SUMIF(B:B,B50,E:E)-SUMIF(B:B,B50,F:F) -> 1 | P50: =IF(A50<>"", Снабжения!H50 / VLOOKUP(A50, 'Курс валют'!$A:$D, 4, 0), "") -> 20.816375
A51: 45973 | B51: Сим | C51: кг | D51: Мет.из | E51: 1000 | G51: 10242.5 | H51: =G51*E51 -> 10242500 | I51: =G51*F51 -> 0 | J51: Завершен | K51: Наличные | M51: шт | N51: =SUMIF(B:B,B51,E:E)-SUMIF(B:B,B51,F:F) -> 125 | O51: 825 | P51: =IF(A51<>"", Снабжения!H51 / VLOOKUP(A51, 'Курс валют'!$A:$D, 4, 0), "") -> 853.54167
A52: 45973 | B52: Сим 3,0 | C52: кг | D52: Мет.из | E52: 100 | G52: 9760.5 | H52: =G52*E52 -> 976050 | I52: =G52*F52 -> 0 | J52: Завершен | K52: Наличные | M52: шт | N52: =SUMIF(B:B,B52,E:E)-SUMIF(B:B,B52,F:F) -> 100 | P52: =IF(A52<>"", Снабжения!H52 / VLOOKUP(A52, 'Курс валют'!$A:$D, 4, 0), "") -> 81.3375
A53: 45973 | B53: Труба ПВХ 23О 2мм | C53: метр | D53: Расходники | E53: 100 | G53: 2688 | H53: =G53*E53 -> 268800 | I53: =G53*F53 -> 0 | J53: Завершен | K53: Наличные | M53: кг | N53: =SUMIF(B:B,B53,E:E)-SUMIF(B:B,B53,F:F) -> 400 | P53: =IF(A53<>"", Снабжения!H53 / VLOOKUP(A53, 'Курс валют'!$A:$D, 4, 0), "") -> 22.4
A54: 45973 | B54: Аэрозол Красный | C54: шт | E54: 1 | F54: 1 | G54: 11809 | H54: =G54*E54 -> 11809 | I54: =G54*F54 -> 11809 | J54: Завершен | K54: Наличные | M54: кг | N54: =SUMIF(B:B,B54,E:E)-SUMIF(B:B,B54,F:F) -> 2 | P54: =IF(A54<>"", Снабжения!H54 / VLOOKUP(A54, 'Курс валют'!$A:$D, 4, 0), "") -> 0.98408333
A55: 45973 | B55: Доставка | H55: 200000 | I55: =G55*F55 -> 0 | J55: Завершен | K55: Наличные | M55: тн | N55: =SUMIF(B:B,B55,E:E)-SUMIF(B:B,B55,F:F) -> 8 | P55: =IF(A55<>"", Снабжения!H55 / VLOOKUP(A55, 'Курс валют'!$A:$D, 4, 0), "") -> 16.666667
A56: 45973 | B56: Сим 6,0 | C56: кг | D56: Мет.из | E56: 2000 | G56: - | H56: - | I56: - | J56: Завершен | K56: Наличные | M56: шт | N56: =SUMIF(B:B,B56,E:E)-SUMIF(B:B,B56,F:F) -> 2000 | P56: =IF(A56<>"", Снабжения!H56 / VLOOKUP(A56, 'Курс валют'!$A:$D, 4, 0), "") -> #VALUE!
A57: 45973 | B57: Пализол | C57: рулон | D57: Кровля и изоляция | E57: 200 | F57: 200 | G57: - | H57: - | I57: - | J57: Завершен | K57: Наличные | M57: метр | N57: =SUMIF(B:B,B57,E:E)-SUMIF(B:B,B57,F:F) -> 0 | P57: =IF(A57<>"", Снабжения!H57 / VLOOKUP(A57, 'Курс валют'!$A:$D, 4, 0), "") -> #VALUE!
A58: 46058 | B58: Трос стропа 6м | C58: шт | D58: Расходники | E58: 1 | G58: 5370000 | H58: =G58*E58 -> 5370000 | N58: =SUMIF(B:B,B58,E:E)-SUMIF(B:B,B58,F:F) -> 1 | P58: =IF(A58<>"", Снабжения!H58 / VLOOKUP(A58, 'Курс валют'!$A:$D, 4, 0), "") -> 440.16393
A59: 46060 | B59: Фализол | C59: рулон | D59: Кровля и изоляция | E59: 35 | F59: 35 | G59: - | H59: - | I59: - | J59: Завершен | K59: Наличные | M59: м | N59: =SUMIF(B:B,B59,E:E)-SUMIF(B:B,B59,F:F) -> 0 | P59: =IF(A59<>"", Снабжения!H59 / VLOOKUP(A59, 'Курс валют'!$A:$D, 4, 0), "") -> #VALUE!
A60: 46060 | B60: Праймер | C60: шт | D60: Кровля и изоляция | E60: 20 | F60: 20 | G60: - | H60: - | I60: - | J60: Завершен | K60: Наличные | M60: шт | N60: =SUMIF(B:B,B60,E:E)-SUMIF(B:B,B60,F:F) -> 0 | P60: =IF(A60<>"", Снабжения!H60 / VLOOKUP(A60, 'Курс валют'!$A:$D, 4, 0), "") -> #VALUE!
A61: 46060 | B61: Бензин | C61: лт | D61: Кровля и изоляция | E61: 60 | F61: 60 | G61: - | H61: - | I61: - | J61: Завершен | K61: Наличные | M61: шт | N61: =SUMIF(B:B,B61,E:E)-SUMIF(B:B,B61,F:F) -> 0 | P61: =IF(A61<>"", Снабжения!H61 / VLOOKUP(A61, 'Курс валют'!$A:$D, 4, 0), "") -> #VALUE!
A62: 46060 | B62: Валик | C62: шт | D62: Расходники | E62: 4 | F62: 4 | G62: - | H62: - | I62: - | J62: Завершен | K62: Наличные | M62: рулон | N62: =SUMIF(B:B,B62,E:E)-SUMIF(B:B,B62,F:F) -> 9 | P62: =IF(A62<>"", Снабжения!H62 / VLOOKUP(A62, 'Курс валют'!$A:$D, 4, 0), "") -> #VALUE!
A63: 46060 | B63: Розетка | C63: шт | D63: Электрика | E63: 10 | G63: 3198 | H63: =G63*E63 -> 31980 | I63: =G63*F63 -> 0 | J63: Завершен | K63: Наличные | M63: шт | N63: =SUMIF(B:B,B63,E:E)-SUMIF(B:B,B63,F:F) -> 1 | O63: 2 | P63: =IF(A63<>"", Снабжения!H63 / VLOOKUP(A63, 'Курс валют'!$A:$D, 4, 0), "") -> 2.6213115
A64: 46061 | B64: Тройник | C64: шт | D64: Электрика | E64: 10 | G64: 10332 | H64: =G64*E64 -> 103320 | I64: =G64*F64 -> 0 | J64: Завершен | K64: Наличные | M64: шт | N64: =SUMIF(B:B,B64,E:E)-SUMIF(B:B,B64,F:F) -> 11 | P64: =IF(A64<>"", Снабжения!H64 / VLOOKUP(A64, 'Курс валют'!$A:$D, 4, 0), "") -> 8.4688525
A65: 46061 | B65: Мих 100мм | C65: кг | D65: Мет.из | E65: =5*20 -> 100 | G65: 10209 | H65: =G65*E65 -> 1020900 | I65: =G65*F65 -> 0 | J65: Завершен | K65: Наличные | M65: шт | N65: =SUMIF(B:B,B65,E:E)-SUMIF(B:B,B65,F:F) -> 20 | P65: =IF(A65<>"", Снабжения!H65 / VLOOKUP(A65, 'Курс валют'!$A:$D, 4, 0), "") -> 83.680328
A66: 46061 | B66: Мих 70мм | C66: кг | D66: Мет.из | E66: =10*20 -> 200 | G66: 10209 | H66: =G66*E66 -> 2041800 | I66: =G66*F66 -> 0 | J66: Завершен | K66: Наличные | M66: кг | N66: =SUMIF(B:B,B66,E:E)-SUMIF(B:B,B66,F:F) -> 40 | P66: =IF(A66<>"", Снабжения!H66 / VLOOKUP(A66, 'Курс валют'!$A:$D, 4, 0), "") -> 167.36066
A67: 46061 | B67: Дюбель мих 50 | C67: кг | D67: Мет.из | E67: =3*20 -> 60 | G67: 29274 | H67: =G67*E67 -> 1756440 | I67: =G67*F67 -> 0 | J67: Завершен | K67: Наличные | M67: шт | N67: =SUMIF(B:B,B67,E:E)-SUMIF(B:B,B67,F:F) -> 80 | P67: =IF(A67<>"", Снабжения!H67 / VLOOKUP(A67, 'Курс валют'!$A:$D, 4, 0), "") -> 143.97049
A68: 46061 | B68: Диск Отрезной 230 | C68: шт | E68: =2*25 -> 50 | G68: 12177 | H68: =G68*E68 -> 608850 | I68: =G68*F68 -> 0 | J68: Завершен | K68: Наличные | M68: шт | N68: =SUMIF(B:B,B68,E:E)-SUMIF(B:B,B68,F:F) -> 87 | P68: =IF(A68<>"", Снабжения!H68 / VLOOKUP(A68, 'Курс валют'!$A:$D, 4, 0), "") -> 49.905738
A69: 46061 | B69: Диск Отрезной 180 | C69: шт | E69: =2*25 -> 50 | G69: 9225 | H69: =G69*E69 -> 461250 | I69: =G69*F69 -> 0 | J69: Завершен | K69: Наличные | M69: шт | N69: =SUMIF(B:B,B69,E:E)-SUMIF(B:B,B69,F:F) -> 42 | P69: =IF(A69<>"", Снабжения!H69 / VLOOKUP(A69, 'Курс валют'!$A:$D, 4, 0), "") -> 37.807377
A70: 46061 | B70: Мель | C70: шт | E70: 1000 | G70: 15000 | H70: =G70*E70 -> 15000000 | I70: =G70*F70 -> 0 | J70: Завершен | K70: Наличные | M70: почка | N70: =SUMIF(B:B,B70,E:E)-SUMIF(B:B,B70,F:F) -> 405 | P70: =IF(A70<>"", Снабжения!H70 / VLOOKUP(A70, 'Курс валют'!$A:$D, 4, 0), "") -> 1229.5082
A71: 46061 | B71: Маркер | C71: шт | E71: 100 | G71: 1230 | H71: =G71*E71 -> 123000 | I71: =G71*F71 -> 0 | J71: Завершен | K71: Наличные | M71: почка | N71: =SUMIF(B:B,B71,E:E)-SUMIF(B:B,B71,F:F) -> 128 | P71: =IF(A71<>"", Снабжения!H71 / VLOOKUP(A71, 'Курс валют'!$A:$D, 4, 0), "") -> 10.081967
A72: 46061 | B72: Перчатка | C72: шт | E72: 500 | G72: 4428 | H72: =G72*E72 -> 2214000 | I72: =G72*F72 -> 0 | J72: Завершен | K72: Наличные | M72: шт | N72: =SUMIF(B:B,B72,E:E)-SUMIF(B:B,B72,F:F) -> 309 | P72: =IF(A72<>"", Снабжения!H72 / VLOOKUP(A72, 'Курс валют'!$A:$D, 4, 0), "") -> 181.47541
A73: 46061 | B73: Сверло Тахта 18мм | C73: шт | E73: 20 | G73: 19803 | H73: =G73*E73 -> 396060 | I73: =G73*F73 -> 0 | J73: Завершен | K73: Наличные | M73: шт | N73: =SUMIF(B:B,B73,E:E)-SUMIF(B:B,B73,F:F) -> 20 | P73: =IF(A73<>"", Снабжения!H73 / VLOOKUP(A73, 'Курс валют'!$A:$D, 4, 0), "") -> 32.463934
A74: 46061 | B74: Чалка 4Т | C74: шт | E74: 1 | G74: 135300 | H74: =G74*E74 -> 135300 | I74: =G74*F74 -> 0 | J74: Завершен | K74: Наличные | M74: шт | N74: =SUMIF(B:B,B74,E:E)-SUMIF(B:B,B74,F:F) -> 2 | P74: =IF(A74<>"", Снабжения!H74 / VLOOKUP(A74, 'Курс валют'!$A:$D, 4, 0), "") -> 11.090164
A75: 46061 | B75: Чалка 5Т | C75: шт | E75: 1 | G75: 250920 | H75: =G75*E75 -> 250920 | I75: =G75*F75 -> 0 | J75: Завершен | K75: Наличные | M75: шт | N75: =SUMIF(B:B,B75,E:E)-SUMIF(B:B,B75,F:F) -> 2 | P75: =IF(A75<>"", Снабжения!H75 / VLOOKUP(A75, 'Курс валют'!$A:$D, 4, 0), "") -> 20.567213
A76: 46061 | B76: Аэрозол Красный | C76: шт | E76: 10 | G76: 11070 | H76: =G76*E76 -> 110700 | I76: =G76*F76 -> 0 | J76: Завершен | K76: Наличные | M76: шт | N76: =SUMIF(B:B,B76,E:E)-SUMIF(B:B,B76,F:F) -> 2 | P76: =IF(A76<>"", Снабжения!H76 / VLOOKUP(A76, 'Курс валют'!$A:$D, 4, 0), "") -> 9.0737705
A77: 46061 | B77: Труба ПВХ 23О 2мм | C77: метр | D77: Расходники | E77: 300 | G77: 3500 | H77: =G77*E77 -> 1050000 | I77: =G77*F77 -> 0 | J77: Завершен | K77: Наличные | M77: м | N77: =SUMIF(B:B,B77,E:E)-SUMIF(B:B,B77,F:F) -> 400 | O77: 200 | P77: =IF(A77<>"", Снабжения!H77 / VLOOKUP(A77, 'Курс валют'!$A:$D, 4, 0), "") -> 86.065574
A78: 46061 | B78: Сварка аппарат | C78: шт | E78: 1 | G78: 1961850 | H78: =G78*E78 -> 1961850 | I78: =G78*F78 -> 0 | J78: Завершен | K78: Наличные | M78: шт | N78: =SUMIF(B:B,B78,E:E)-SUMIF(B:B,B78,F:F) -> 1 | P78: =IF(A78<>"", Снабжения!H78 / VLOOKUP(A78, 'Курс валют'!$A:$D, 4, 0), "") -> 160.80738
A79: 46061 | B79: Печка | C79: шт | E79: 2 | G79: 265000 | H79: =G79*E79 -> 530000 | I79: =G79*F79 -> 0 | J79: Завершен | K79: Наличные | M79: шт | N79: =SUMIF(B:B,B79,E:E)-SUMIF(B:B,B79,F:F) -> 2 | P79: =IF(A79<>"", Снабжения!H79 / VLOOKUP(A79, 'Курс валют'!$A:$D, 4, 0), "") -> 43.442623
A80: 46061 | B80: Доставка | C80: услуга | H80: 200000 | I80: =G80*F80 -> 0 | J80: Завершен | K80: Наличные | M80: услуга | N80: =SUMIF(B:B,B80,E:E)-SUMIF(B:B,B80,F:F) -> 8 | P80: =IF(A80<>"", Снабжения!H80 / VLOOKUP(A80, 'Курс валют'!$A:$D, 4, 0), "") -> 16.393443
A81: 46061 | B81: Тройник | C81: шт | D81: Электрика | F81: 3 | G81: 10332 | I81: =G81*F81 -> 30996 | M81: шт | N81: =SUMIF(B:B,B81,E:E)-SUMIF(B:B,B81,F:F) -> 11 | P81: =IF(A81<>"", Снабжения!H81 / VLOOKUP(A81, 'Курс валют'!$A:$D, 4, 0), "") -> 0
A82: 46063 | B82: Диск Отрезной 230 | C82: шт | D82: Расходники | F82: 5 | M82: шт | N82: =SUMIF(B:B,B82,E:E)-SUMIF(B:B,B82,F:F) -> 87 | P82: =IF(A82<>"", Снабжения!H82 / VLOOKUP(A82, 'Курс валют'!$A:$D, 4, 0), "") -> 0
A83: 46063 | B83: Перчатка | C83: шт | D83: Расходники | F83: 20 | M83: шт | N83: =SUMIF(B:B,B83,E:E)-SUMIF(B:B,B83,F:F) -> 309 | P83: =IF(A83<>"", Снабжения!H83 / VLOOKUP(A83, 'Курс валют'!$A:$D, 4, 0), "") -> 0
A84: 46063 | B84: Электрод MP-3 2.5 | C84: кг | F84: 2.5 | M84: кг | N84: =SUMIF(B:B,B84,E:E)-SUMIF(B:B,B84,F:F) -> 41.5 | P84: =IF(A84<>"", Снабжения!H84 / VLOOKUP(A84, 'Курс валют'!$A:$D, 4, 0), "") -> 0
A85: 46063 | B85: Перчатка | C85: шт | F85: 20 | N85: =SUMIF(B:B,#REF!,E:E)-SUMIF(B:B,#REF!,F:F) -> 0 | P85: =IF(A85<>"", Снабжения!H85 / VLOOKUP(A85, 'Курс валют'!$A:$D, 4, 0), "") -> 0
A86: 46065 | B86: Электрод MP-3 2.5 | C86: кг | F86: 1 | N86: =SUMIF(B:B,B85,E:E)-SUMIF(B:B,B85,F:F) -> 309 | P86: =IF(A86<>"", Снабжения!H86 / VLOOKUP(A86, 'Курс валют'!$A:$D, 4, 0), "") -> 0
A87: 46065 | B87: Кабель оддий 2х2,5 | C87: м | D87: Электрика | E87: 200 | G87: =13440 -> 13440 | H87: =G87*E87 -> 2688000 | M87: м | N87: =SUMIF(B:B,B87,E:E)-SUMIF(B:B,B87,F:F) -> 200 | P87: =IF(A87<>"", Снабжения!H87 / VLOOKUP(A87, 'Курс валют'!$A:$D, 4, 0), "") -> 219.78741
A88: 46066 | B88: Розетка | C88: шт | D88: Электрика | E88: 10 | G88: 30627 | H88: =G88*E88 -> 306270 | M88: шт | N88: =SUMIF(B:B,B88,E:E)-SUMIF(B:B,B88,F:F) -> 1 | P88: =IF(A88<>"", Снабжения!H88 / VLOOKUP(A88, 'Курс валют'!$A:$D, 4, 0), "") -> 25.104098
A89: 46066 | B89: Патрон | C89: шт | D89: Электрика | E89: 10 | F89: 7 | G89: 2460 | H89: =G89*E89 -> 24600 | M89: шт | N89: =SUMIF(B:B,B89,E:E)-SUMIF(B:B,B89,F:F) -> 2 | P89: =IF(A89<>"", Снабжения!H89 / VLOOKUP(A89, 'Курс валют'!$A:$D, 4, 0), "") -> 2.0163934
A90: 46066 | B90: Лампа 50W | C90: шт | D90: Электрика | E90: 10 | F90: 7 | G90: 52398 | H90: =G90*E90 -> 523980 | M90: шт | N90: =SUMIF(B:B,B90,E:E)-SUMIF(B:B,B90,F:F) -> 1 | P90: =IF(A90<>"", Снабжения!H90 / VLOOKUP(A90, 'Курс валют'!$A:$D, 4, 0), "") -> 42.94918
A91: 46066 | B91: Вилка | C91: шт | D91: Электрика | E91: 10 | G91: 3567 | H91: =G91*E91 -> 35670 | M91: шт | N91: =SUMIF(B:B,B91,E:E)-SUMIF(B:B,B91,F:F) -> 8 | P91: =IF(A91<>"", Снабжения!H91 / VLOOKUP(A91, 'Курс валют'!$A:$D, 4, 0), "") -> 2.9237705
A92: 46066 | B92: Электр коробка 100х100 | C92: шт | D92: Электрика | E92: 10 | F92: 2 | G92: 16000 | H92: =G92*E92 -> 160000 | M92: шт | N92: =SUMIF(B:B,B92,E:E)-SUMIF(B:B,B92,F:F) -> 6 | P92: =IF(A92<>"", Снабжения!H92 / VLOOKUP(A92, 'Курс валют'!$A:$D, 4, 0), "") -> 13.114754
A93: 46066 | B93: Кабель ПВС 2х4 | C93: м | D93: Электрика | E93: 50 | G93: 23072 | H93: =G93*E93 -> 1153600 | M93: м | N93: =SUMIF(B:B,B93,E:E)-SUMIF(B:B,B93,F:F) -> 0 | P93: =IF(A93<>"", Снабжения!H93 / VLOOKUP(A93, 'Курс валют'!$A:$D, 4, 0), "") -> 94.557377
A94: 46066 | B94: Розетка | C94: шт | D94: Электрика | E94: 1 | G94: 91512 | H94: =G94*E94 -> 91512 | M94: шт | N94: =SUMIF(B:B,B94,E:E)-SUMIF(B:B,B94,F:F) -> 1 | P94: =IF(A94<>"", Снабжения!H94 / VLOOKUP(A94, 'Курс валют'!$A:$D, 4, 0), "") -> 7.5009836
A95: 46066 | B95: Кабель ПВС 4х2,5 | C95: м | D95: Электрика | E95: 150 | G95: 25522 | H95: =G95*E95 -> 3828300 | M95: м | N95: =SUMIF(B:B,B95,E:E)-SUMIF(B:B,B95,F:F) -> 150 | P95: =IF(A95<>"", Снабжения!H95 / VLOOKUP(A95, 'Курс валют'!$A:$D, 4, 0), "") -> 313.79508
A96: 46066 | B96: Автомат 80А | C96: шт | D96: Электрика | E96: 3 | F96: 3 | G96: 129150 | H96: =E96*G96 -> 387450 | M96: шт | N96: =SUMIF(B:B,B96,E:E)-SUMIF(B:B,B96,F:F) -> 0 | P96: =IF(A96<>"", Снабжения!H96 / VLOOKUP(A96, 'Курс валют'!$A:$D, 4, 0), "") -> 31.758197
A97: 46066 | B97: Изолента | C97: шт | D97: Прочее | E97: 30 | F97: 19 | G97: 3936 | H97: =G97*E97 -> 118080 | M97: шт | N97: =SUMIF(B:B,B97,E:E)-SUMIF(B:B,B97,F:F) -> 8 | P97: =IF(A97<>"", Снабжения!H97 / VLOOKUP(A97, 'Курс валют'!$A:$D, 4, 0), "") -> 9.6786885
A98: 46066 | B98: Пена монтажная | C98: шт | D98: Стены | E98: 36 | G98: 54120 | H98: =G98*E98 -> 1948320 | M98: шт | N98: =SUMIF(B:B,B98,E:E)-SUMIF(B:B,B98,F:F) -> 33 | O98: 47 | P98: =IF(A98<>"", Снабжения!H98 / VLOOKUP(A98, 'Курс валют'!$A:$D, 4, 0), "") -> 159.69836
A99: 46066 | B99: Чалка 4Т | C99: шт | D99: Ручной инструменты | E99: 1 | G99: 135300 | H99: =G99*E99 -> 135300 | M99: шт | N99: =SUMIF(B:B,B99,E:E)-SUMIF(B:B,B99,F:F) -> 2 | P99: =IF(A99<>"", Снабжения!H99 / VLOOKUP(A99, 'Курс валют'!$A:$D, 4, 0), "") -> 11.090164
A100: 46066 | B100: Чалка 5Т | C100: шт | D100: Ручной инструменты | E100: 1 | G100: 250920 | H100: =G100*E100 -> 250920 | M100: шт | N100: =SUMIF(B:B,B100,E:E)-SUMIF(B:B,B100,F:F) -> 2 | P100: =IF(A100<>"", Снабжения!H100 / VLOOKUP(A100, 'Курс валют'!$A:$D, 4, 0), "") -> 20.567213
...

Sheet Арматура приход
A1: № | B1: Дата | C1: Номер Авто | D1: Использовано | E1: Катанка | F1: Использовано10 | G1: D8 | H1: Использовано2 | I1: D10 | J1: Использовано3 | K1: D12 | L1: Использовано4 | M1: D14 | N1: Использовано5 | O1: D16 | P1: Использовано6 | Q1: D18 | R1: Использовано7 | S1: D20 | T1: Использовано8 | U1: D22 | V1: Использовано9 | W1: D25 | X1: Итого | Y1: Угольник (40мм) 4 ст | Z1: Пруд (50) | AA1: Пруд (32) | AB1: Итого2 | AC1: Курс | AD1: В долларе
A2: 1 | B2: 45972 | D2: Да | F2: Да | H2: Да | J2: Да | K2: 3148 | L2: Да | M2: 3063 | N2: Да | P2: Да | Q2: 2873 | R2: Да | S2: 3033 | T2: Да | U2: 3018 | V2: Да | W2: 3053
A3: Приход | B3: 45972 | D3: Да | F3: Да | H3: Да | J3: Да | K3: 3163 | L3: Да | M3: 3058 | N3: Да | P3: Да | R3: Да | S3: 3033 | T3: Да | U3: 3013 | V3: Да | W3: 3048
B4: 45972 | D4: Да | F4: Да | H4: Да | J4: Да | K4: 3153 | L4: Да | M4: 3048 | N4: Да | P4: Да | R4: Да | S4: 3033 | T4: Да | V4: Да
B5: 45972 | D5: Да | F5: Да | H5: Да | J5: Да | K5: 3168 | L5: Да | M5: 3048 | N5: Да | P5: Да | R5: Да | S5: 3053 | T5: Да | V5: Да
B6: 45972 | D6: Да | F6: Да | H6: Да | J6: Да | K6: 3163 | L6: Да | M6: 3063 | N6: Да | P6: Да | R6: Да | T6: Да | V6: Да
B7: 45972 | D7: Да | F7: Да | H7: Да | J7: Да | K7: 3143 | L7: Да | M7: 3058 | N7: Да | P7: Да | R7: Да | T7: Да | V7: Да
B8: 45972 | D8: Да | F8: Да | H8: Да | J8: Да | K8: 3133 | L8: Да | M8: 3053 | N8: Да | P8: Да | R8: Да | T8: Да | V8: Да
B9: 45972 | D9: Да | F9: Да | H9: Да | J9: Да | K9: 3148 | L9: Да | M9: 3053 | N9: Да | P9: Да | R9: Да | T9: Да | V9: Да
B10: 45972 | D10: Да | F10: Да | H10: Да | J10: Да | K10: 3138 | L10: Да | M10: 3053 | N10: Да | P10: Да | R10: Да | T10: Да | V10: Да
B11: 45972 | D11: Да | F11: Да | H11: Да | J11: Да | K11: 3138 | L11: Да | M11: 3053 | N11: Да | P11: Да | R11: Да | T11: Да | V11: Да
B12: 45972 | D12: Да | F12: Да | H12: Да | J12: Да | L12: Да | M12: 3058 | N12: Да | P12: Да | R12: Да | T12: Да | V12: Да
B13: 45972 | D13: Да | F13: Да | H13: Да | J13: Да | L13: Да | M13: 3063 | N13: Да | P13: Да | R13: Да | T13: Да | V13: Да
B14: 45972 | D14: Да | F14: Да | H14: Да | J14: Да | L14: Да | M14: 3048 | N14: Да | P14: Да | R14: Да | T14: Да | V14: Да
B15: 45972 | D15: Да | F15: Да | H15: Да | J15: Да | L15: Да | M15: 3053 | N15: Да | P15: Да | R15: Да | T15: Да | V15: Да | X15: =SUM(K2:K11,M2:M15,Q2,S2:S5,U2:U4,W2:W3) -> 101424 | AB15: =(X15/1000)*640*AC15 -> 7.7471708e+08 | AC15: 11935 | AD15: =(X15/1000)*640 -> 64911.36
A16: 2 | B16: 45985 | D16: Да | F16: Да | H16: Да | J16: Да | L16: Да | N16: Да | P16: Да | R16: Да | T16: Да | V16: Да | Y16: =17*11.7 -> 198.9 | Z16: =11.7*2 -> 23.4 | AA16: =11.7*2 -> 23.4
A17: 3 | B17: 45990 | D17: Да | F17: Да | H17: Да | I17: 3135 | J17: Да | L17: Да | N17: Да | O17: 2600 | P17: Да | Q17: 2410 | R17: Да | T17: Да | U17: 1555 | V17: Да | W17: 2600
A18: Приход | B18: 45990 | D18: Да | F18: Да | H18: Да | I18: 3135 | J18: Да | L18: Да | N18: Да | O18: 5215 | P18: Да | Q18: 2450 | R18: Да | T18: Да | U18: 2485 | V18: Да | W18: 2580
A19: Жамол Ака | B19: 45990 | D19: Да | F19: Да | H19: Да | I19: 3110 | J19: Да | L19: Да | N19: Да | O19: 5200 | P19: Да | Q19: 2515 | R19: Да | T19: Да | U19: 2490 | V19: Да | W19: 2500
B20: 45990 | D20: Да | F20: Да | H20: Да | I20: 3130 | J20: Да | L20: Да | N20: Да | O20: 5135 | P20: Да | Q20: 2500 | R20: Да | T20: Да | U20: 2550 | V20: Да | W20: 2580
B21: 45990 | D21: Да | F21: Да | H21: Да | I21: 3125 | J21: Да | L21: Да | N21: Да | O21: 2555 | P21: Да | Q21: 2540 | R21: Да | T21: Да | U21: 2580 | V21: Да | W21: 2590
B22: 45990 | D22: Да | F22: Да | H22: Да | J22: Да | L22: Да | N22: Да | O22: 2560 | P22: Да | R22: Да | T22: Да | U22: 2580 | V22: Да | W22: 2585
B23: 45990 | D23: Да | F23: Да | H23: Да | J23: Да | L23: Да | N23: Да | O23: 2575 | P23: Да | R23: Да | T23: Да | U23: 2580 | V23: Да | W23: 2510
B24: 45990 | D24: Да | F24: Да | H24: Да | J24: Да | L24: Да | N24: Да | P24: Да | R24: Да | T24: Да | U24: 2585 | V24: Да | W24: 2570
B25: 45990 | D25: Да | F25: Да | H25: Да | J25: Да | L25: Да | N25: Да | P25: Да | R25: Да | T25: Да | U25: 2585 | V25: Да | W25: 2225
B26: 45990 | D26: Да | F26: Да | H26: Да | J26: Да | L26: Да | N26: Да | P26: Да | R26: Да | T26: Да | U26: 2585 | V26: Да | W26: 2165
B27: 45990 | D27: Да | F27: Да | H27: Да | J27: Да | L27: Да | N27: Да | P27: Да | R27: Да | T27: Да | U27: 2585 | V27: Да | W27: 2775
B28: 45990 | D28: Да | F28: Да | H28: Да | J28: Да | L28: Да | N28: Да | P28: Да | R28: Да | T28: Да | U28: 2590 | V28: Да | W28: 2590
B29: 45990 | D29: Да | F29: Да | H29: Да | J29: Да | L29: Да | N29: Да | P29: Да | R29: Да | T29: Да | U29: 2590 | V29: Да
B30: 45990 | D30: Да | F30: Да | H30: Да | J30: Да | L30: Да | N30: Да | P30: Да | R30: Да | T30: Да | U30: 2590 | V30: Да
B31: 45990 | D31: Да | F31: Да | H31: Да | J31: Да | L31: Да | N31: Да | P31: Да | R31: Да | T31: Да | U31: 2600 | V31: Да
B32: 45990 | D32: Да | F32: Да | H32: Да | J32: Да | L32: Да | N32: Да | P32: Да | R32: Да | T32: Да | U32: 2620 | V32: Да
B33: 45990 | D33: Да | F33: Да | H33: Да | J33: Да | L33: Да | N33: Да | P33: Да | R33: Да | T33: Да | U33: 2695 | V33: Да
B34: 45990 | D34: Да | F34: Да | H34: Да | J34: Да | L34: Да | N34: Да | P34: Да | R34: Да | T34: Да | U34: 2930 | V34: Да
B35: 45990 | D35: Да | F35: Да | H35: Да | J35: Да | L35: Да | N35: Да | P35: Да | R35: Да | T35: Да | U35: 3370 | V35: Да
B36: 45990 | D36: Да | F36: Да | H36: Да | J36: Да | L36: Да | N36: Да | P36: Да | R36: Да | T36: Да | U36: 3470 | V36: Да | X36: =SUM(I17:I21,O17:O23,Q17:Q21,U17:U36,W17:W28) -> 136775 | AB36: =(SUM(U32,U34,U36)/1000)*640*AC36 -> 68638592 | AC36: 11890 | AD36: =(SUM(U32,U34,U36)/1000)*640 -> 5772.8
A37: 4 | C37: 788 | D37: Да | F37: Да | H37: Да | J37: Да | L37: Да | N37: Да | O37: 5215 | P37: Да | Q37: 2450 | R37: Да | T37: Да | U37: 1555 | V37: Да | W37: 2590
A38: Возврат | D38: Да | F38: Да | H38: Да | J38: Да | L38: Да | N38: Да | O38: 5135 | P38: Да | Q38: 2410 | R38: Да | T38: Да | U38: 2485 | V38: Да
A39: Жамол Ака | D39: Да | F39: Да | H39: Да | J39: Да | L39: Да | N39: Да | O39: 2555 | P39: Да | R39: Да | T39: Да | U39: 2490 | V39: Да
D40: Да | F40: Да | H40: Да | J40: Да | L40: Да | N40: Да | O40: 2575 | P40: Да | R40: Да | T40: Да | U40: 2550 | V40: Да
D41: Да | F41: Да | H41: Да | J41: Да | L41: Да | N41: Да | O41: 2560 | P41: Да | R41: Да | T41: Да | U41: 2580 | V41: Да
D42: Да | F42: Да | H42: Да | J42: Да | L42: Да | N42: Да | P42: Да | R42: Да | T42: Да | U42: 2580 | V42: Да
C43: 928 | D43: Да | F43: Да | H43: Да | I43: 3125 | J43: Да | L43: Да | N43: Да | O43: 2600 | P43: Да | R43: Да | T43: Да | U43: 2580 | V43: Да | W43: 2585
D44: Да | F44: Да | H44: Да | J44: Да | L44: Да | N44: Да | O44: 5200 | P44: Да | R44: Да | T44: Да | U44: 2585 | V44: Да | W44: 2580
D45: Да | F45: Да | H45: Да | J45: Да | L45: Да | N45: Да | P45: Да | R45: Да | T45: Да | U45: 2585 | V45: Да | W45: 2165
D46: Да | F46: Да | H46: Да | J46: Да | L46: Да | N46: Да | P46: Да | R46: Да | T46: Да | U46: 2585 | V46: Да | W46: 2580
D47: Да | F47: Да | H47: Да | J47: Да | L47: Да | N47: Да | P47: Да | R47: Да | T47: Да | U47: 2585 | V47: Да | W47: 2500
D48: Да | F48: Да | H48: Да | J48: Да | L48: Да | N48: Да | P48: Да | R48: Да | T48: Да | U48: 2590 | V48: Да | W48: 2600
D49: Да | F49: Да | H49: Да | J49: Да | L49: Да | N49: Да | P49: Да | R49: Да | T49: Да | U49: 2590 | V49: Да | W49: 2590
D50: Да | F50: Да | H50: Да | J50: Да | L50: Да | N50: Да | P50: Да | R50: Да | T50: Да | U50: 2590 | V50: Да
C51: 605 | D51: Да | F51: Да | H51: Да | I51: 3130 | J51: Да | L51: Да | N51: Да | P51: Да | Q51: 2540 | R51: Да | T51: Да | U51: 2600 | V51: Да | W51: 2225
D52: Да | F52: Да | H52: Да | I52: 3110 | J52: Да | L52: Да | N52: Да | P52: Да | Q52: 2500 | R52: Да | T52: Да | U52: 2695 | V52: Да | W52: 2775
D53: Да | F53: Да | H53: Да | I53: 3135 | J53: Да | L53: Да | N53: Да | P53: Да | Q53: 2515 | R53: Да | T53: Да | U53: 3370 | V53: Да | W53: 2570
D54: Да | F54: Да | H54: Да | I54: 3135 | J54: Да | L54: Да | N54: Да | P54: Да | R54: Да | T54: Да | V54: Да | W54: 2510
D55: Да | F55: Да | H55: Да | J55: Да | L55: Да | N55: Да | P55: Да | R55: Да | T55: Да | V55: Да | W55: =SUM(I43:I54,O37:O44,Q37:Q53,U37:U53,W37:W54) -> 127755 | AB55: =(W55/1000)*640*AC55 -> 0
A56: 5 | B56: 46054 | C56: 85 805 BBA | D56: Да | E56: 2105 | F56: Да | H56: Да | I56: 1985 | J56: Да | K56: 2535 | L56: Да | N56: Да | P56: Да | Q56: 2465 | R56: Да | S56: 2540 | T56: Да | V56: Да
A57: Приход | B57: 46054 | D57: Да | F57: Да | H57: Да | I57: 1975 | J57: Да | K57: 2340 | L57: Да | N57: Да | P57: Да | Q57: 2515 | R57: Да | S57: =5040-S56 -> 2500 | T57: Да | V57: Да
B58: 46054 | D58: Да | F58: Да | H58: Да | J58: Да | K58: 2375 | L58: Да | N58: Да | P58: Да | R58: Да | T58: Да | V58: Да
B59: 46054 | C59: 30 7236 АА | D59: Да | F59: Да | H59: Да | J59: Да | L59: Да | N59: Да | P59: Да | R59: Да | T59: Да | U59: 2200 | V59: Да
B60: 46054 | D60: Да | F60: Да | H60: Да | J60: Да | L60: Да | N60: Да | P60: Да | R60: Да | T60: Да | U60: 2490 | V60: Да
B61: 46054 | D61: Да | F61: Да | H61: Да | J61: Да | L61: Да | N61: Да | P61: Да | R61: Да | T61: Да | U61: 2500 | V61: Да
B62: 46054 | D62: Да | F62: Да | H62: Да | J62: Да | L62: Да | N62: Да | P62: Да | R62: Да | T62: Да | U62: 2500 | V62: Да
B63: 46054 | D63: Да | F63: Да | H63: Да | J63: Да | L63: Да | N63: Да | P63: Да | R63: Да | T63: Да | U63: 2500 | V63: Да
B64: 46054 | D64: Да | F64: Да | H64: Да | J64: Да | L64: Да | N64: Да | P64: Да | R64: Да | T64: Да | U64: 2535 | V64: Да
B65: 46054 | D65: Да | F65: Да | H65: Да | J65: Да | L65: Да | N65: Да | P65: Да | R65: Да | T65: Да | U65: 2500 | V65: Да
B66: 46054 | D66: Да | F66: Да | H66: Да | J66: Да | L66: Да | N66: Да | P66: Да | R66: Да | T66: Да | U66: 2485 | V66: Да
B67: 46054 | D67: Да | F67: Да | H67: Да | J67: Да | L67: Да | N67: Да | P67: Да | R67: Да | T67: Да | U67: 2490 | V67: Да
B68: 46054 | D68: Да | F68: Да | H68: Да | J68: Да | L68: Да | N68: Да | P68: Да | R68: Да | T68: Да | U68: 2495 | V68: Да
B69: 46054 | C69: 30 850 ACA | D69: Да | F69: Да | H69: Да | J69: Да | L69: Да | M69: 2480 | N69: Да | P69: Да | R69: Да | T69: Да | V69: Да | W69: 2490
B70: 46054 | D70: Да | F70: Да | H70: Да | J70: Да | L70: Да | N70: Да | P70: Да | R70: Да | T70: Да | V70: Да | W70: 2490
B71: 46054 | D71: Да | F71: Да | H71: Да | J71: Да | L71: Да | N71: Да | P71: Да | R71: Да | T71: Да | V71: Да | W71: 2505
B72: 46054 | D72: Да | F72: Да | H72: Да | J72: Да | L72: Да | N72: Да | P72: Да | R72: Да | T72: Да | V72: Да | W72: 2495
B73: 46054 | D73: Да | F73: Да | H73: Да | J73: Да | L73: Да | N73: Да | P73: Да | R73: Да | T73: Да | V73: Да | W73: 2495
B74: 46054 | D74: Да | F74: Да | H74: Да | J74: Да | L74: Да | N74: Да | P74: Да | R74: Да | T74: Да | V74: Да | W74: 2495
B75: 46054 | D75: Да | F75: Да | H75: Да | J75: Да | L75: Да | N75: Да | P75: Да | R75: Да | T75: Да | V75: Да | W75: 2495
B76: 46054 | D76: Да | F76: Да | H76: Да | J76: Да | L76: Да | N76: Да | P76: Да | R76: Да | T76: Да | V76: Да | W76: 2505
B77: 46054 | D77: Да | F77: Да | H77: Да | J77: Да | L77: Да | N77: Да | P77: Да | R77: Да | T77: Да | V77: Да | W77: 2490 | X77: =SUM(E56,K56:K58,I56:I57,M69,Q56:Q57,S56:S57,U59:U68,W69:W77) -> 72970 | AB77: =(X77/1000)*640*AC77 -> 568115232 | AC77: 12165 | AD77: =(X77/1000)*640 -> 46700.8
A78: 6 | B78: 46070 | C78: 30 D 265 BB | D78: Да | E78: 1565 | F78: Да | H78: Да | J78: Да | L78: Да | M78: 5110 | N78: Да | P78: Да | R78: Да | T78: Да | V78: Да
A79: Приход | B79: 46070 | D79: Да | E79: 1580 | F79: Да | H79: Да | J79: Да | L79: Да | M79: 4975 | N79: Да | P79: Да | R79: Да | T79: Да | V79: Да
B80: 46070 | D80: Да | E80: 1560 | F80: Да | H80: Да | J80: Да | L80: Да | M80: 2445 | N80: Да | P80: Да | R80: Да | T80: Да | V80: Да
B81: 46070 | D81: Да | E81: 1560 | F81: Да | H81: Да | J81: Да | L81: Да | N81: Да | P81: Да | R81: Да | T81: Да | V81: Да
B82: 46070 | D82: Да | E82: 1550 | F82: Да | H82: Да | J82: Да | L82: Да | N82: Да | P82: Да | R82: Да | T82: Да | V82: Да
B83: 46070 | D83: Да | E83: 1565 | F83: Да | H83: Да | J83: Да | L83: Да | N83: Да | P83: Да | R83: Да | T83: Да | V83: Да
B84: 46070 | D84: Да | E84: 1555 | F84: Да | H84: Да | J84: Да | L84: Да | N84: Да | P84: Да | R84: Да | T84: Да | V84: Да
B85: 46070 | C85: 30 D 058 RB | D85: Да | F85: Да | H85: Да | J85: Да | L85: Да | M85: 2455 | N85: Да | P85: Да | R85: Да | T85: Да | V85: Да
B86: 46070 | D86: Да | F86: Да | H86: Да | J86: Да | L86: Да | M86: 2450 | N86: Да | P86: Да | R86: Да | T86: Да | V86: Да
B87: 46070 | D87: Да | F87: Да | H87: Да | J87: Да | L87: Да | M87: 2505 | N87: Да | P87: Да | R87: Да | T87: Да | V87: Да
B88: 46070 | D88: Да | F88: Да | H88: Да | J88: Да | L88: Да | M88: 2475 | N88: Да | P88: Да | R88: Да | T88: Да | V88: Да
B89: 46070 | D89: Да | F89: Да | H89: Да | J89: Да | L89: Да | M89: 2460 | N89: Да | P89: Да | R89: Да | T89: Да | V89: Да
B90: 46070 | D90: Да | F90: Да | H90: Да | J90: Да | L90: Да | M90: 2455 | N90: Да | P90: Да | R90: Да | T90: Да | V90: Да
B91: 46070 | D91: Да | F91: Да | H91: Да | J91: Да | L91: Да | M91: 2465 | N91: Да | P91: Да | R91: Да | T91: Да | V91: Да
B92: 46070 | D92: Да | F92: Да | H92: Да | J92: Да | L92: Да | M92: 2405 | N92: Да | P92: Да | R92: Да | T92: Да | V92: Да
B93: 46070 | D93: Да | F93: Да | H93: Да | J93: Да | L93: Да | M93: 2435 | N93: Да | P93: Да | R93: Да | T93: Да | V93: Да
B94: 46070 | D94: Да | F94: Да | H94: Да | J94: Да | L94: Да | M94: 2475 | N94: Да | P94: Да | R94: Да | T94: Да | V94: Да
B95: 46070 | D95: Да | F95: Да | H95: Да | J95: Да | L95: Да | M95: 2445 | N95: Да | P95: Да | R95: Да | T95: Да | V95: Да
B96: 46070 | C96: 30 064 WAA | D96: Да | E96: 1590 | F96: Да | H96: Да | J96: Да | K96: 2450 | L96: Да | N96: Да | P96: Да | R96: Да | T96: Да | V96: Да
B97: 46070 | D97: Да | E97: 1560 | F97: Да | H97: Да | J97: Да | K97: 2570 | L97: Да | N97: Да | P97: Да | R97: Да | T97: Да | V97: Да
B98: 46070 | D98: Да | E98: 1585 | F98: Да | H98: Да | J98: Да | K98: 2570 | L98: Да | N98: Да | P98: Да | R98: Да | T98: Да | V98: Да
B99: 46070 | D99: Да | F99: Да | H99: Да | J99: Да | K99: 2490 | L99: Да | N99: Да | P99: Да | R99: Да | T99: Да | V99: Да
B100: 46070 | D100: Да | F100: Да | H100: Да | J100: Да | K100: 2485 | L100: Да | N100: Да | P100: Да | R100: Да | T100: Да | V100: Да
...

Sheet Остаток
A1: ОСТАТОК АРМАТУРЫ В РЕАЛЬНОМ ВРЕМЕНИ
A3: Диаметр (D) | B3: Остаток шт/связок | C3: Остаток вес (кг) | D3: Итого использован
A4: Катанка | B4: =SUM('Арматура приход'!$E$2:$E$501,) -> 68805 | C4: =SUMIFS('Арматура приход'!$E$2:$E$501,'Арматура приход'!$D$2:$D$501,"Нет") -> 0 | D4: =B4-C4 -> 68805
A5: 8 | B5: =SUM('Арматура приход'!$G$2:$G$501,) -> 1575 | C5: =SUMIFS('Арматура приход'!$G$2:$G$501,'Арматура приход'!$F$2:$F$501,"Нет") -> 0 | D5: =B5-C5 -> 1575
A6: 10 | B6: =SUM('Арматура приход'!$I$2:$I$501,) -> 82145 | C6: =SUMIFS('Арматура приход'!$I$2:$I$501,'Арматура приход'!$H$2:$H$501,"Нет") -> 0 | D6: =B6-C6 -> 82145
A7: 12 | B7: =SUM('Арматура приход'!$K$2:$K$501,) -> 250200 | C7: =SUMIFS('Арматура приход'!$K$2:$K$501,'Арматура приход'!$J$2:$J$501,"Нет") -> 0 | D7: =B7-C7 -> 250200
A8: 14 | B8: =SUM('Арматура приход'!$M$2:$M$501,) -> 97237 | C8: =SUMIFS('Арматура приход'!$M$2:$M$501,'Арматура приход'!$L$2:$L$501,"Нет") -> 0 | D8: =B8-C8 -> 97237
A9: 16 | B9: =SUM('Арматура приход'!$O$2:$O$501,) -> 59240 | C9: =SUMIFS('Арматура приход'!$O$2:$O$501,'Арматура приход'!$N$2:$N$501,"Нет") -> 0 | D9: =B9-C9 -> 59240
A10: 18 | B10: =SUM('Арматура приход'!$Q$2:$Q$501,) -> 47678 | C10: =SUMIFS('Арматура приход'!$Q$2:$Q$501,'Арматура приход'!$P$2:$P$501,"Нет") -> 0 | D10: =B10-C10 -> 47678
A11: 20 | B11: =SUM('Арматура приход'!$S$2:$S$501,) -> 19667 | C11: =SUMIFS('Арматура приход'!$S$2:$S$501,'Арматура приход'!$R$2:$R$501,"Нет") -> 0 | D11: =B11-C11 -> 19667
A12: 22 | B12: =SUM('Арматура приход'!$U$2:$U$501,) -> 281381 | C12: =SUMIFS('Арматура приход'!$U$2:$U$501,'Арматура приход'!$T$2:$T$501,"Нет") -> 0 | D12: =B12-C12 -> 281381
A13: 25 | B13: =SUM('Арматура приход'!$W$2:$W$501,) -> 259861 | C13: =SUMIFS('Арматура приход'!$W$2:$W$501,'Арматура приход'!$V$2:$V$501,"Нет") -> 0 | D13: =B13-C13 -> 259861
A14: ИТОГО | B14: =SUM(B4:B13) -> 1167789 | C14: =SUM(C4:C13) -> 0 | D14: =SUM(D4:D13) -> 1167789

Sheet Срочный заказ
A1: СРОЧНО ЗАКАЗАТЬ — товары с низким остатком
A2: Порог остатка: | C2: ← измените, и список обновится
A4: № | B4: Наименование | C4: Ед.изм | D4: Категория | E4: Остаток | F4: Последняя цена за ед. | G4: Поставщик | H4: Не заказывать
A5: 1 | B5: сим | C5: кг | D5: Мет.из | E5: =SUMIF(Снабжения!B:B,B5,Снабжения!E:E)-SUMIF(Снабжения!B:B,B5,Снабжения!F:F) -> 125
A6: 2 | B6: розетка | C6: шт | D6: Электрика | E6: =SUMIF(Снабжения!B:B,B6,Снабжения!E:E)-SUMIF(Снабжения!B:B,B6,Снабжения!F:F) -> 1
A7: 3 | B7: Мих 100мм | C7: кг | D7: Мет.из | E7: =SUMIF(Снабжения!B:B,B7,Снабжения!E:E)-SUMIF(Снабжения!B:B,B7,Снабжения!F:F) -> 20 | F7: 9500 | G7: 80
A8: 4 | B8: Метр 10м | C8: шт | D8: Прочее | E8: =SUMIF(Снабжения!B:B,B8,Снабжения!E:E)-SUMIF(Снабжения!B:B,B8,Снабжения!F:F) -> 9 | F8: 31691
A9: 5 | B9: Кабель оддий 3х1,5 | C9: м | D9: Электрика | E9: =SUMIF(Снабжения!B:B,B9,Снабжения!E:E)-SUMIF(Снабжения!B:B,B9,Снабжения!F:F) -> 0 | F9: 10163
A10: 6 | B10: Акрил Лампа (Квадрат) | C10: шт | D10: Электрика | E10: =SUMIF(Снабжения!B:B,B10,Снабжения!E:E)-SUMIF(Снабжения!B:B,B10,Снабжения!F:F) -> 0 | F10: 33000
A11: 7 | B11: Ошхона(Приборы) | E11: =SUMIF(Снабжения!B:B,B11,Снабжения!E:E)-SUMIF(Снабжения!B:B,B11,Снабжения!F:F) -> 0
A12: 8 | B12: Пализол | C12: рулон | D12: Кровля и изоляция | E12: =SUMIF(Снабжения!B:B,B12,Снабжения!E:E)-SUMIF(Снабжения!B:B,B12,Снабжения!F:F) -> 0
A13: 9 | B13: Фализол | C13: рулон | D13: Кровля и изоляция | E13: =SUMIF(Снабжения!B:B,B13,Снабжения!E:E)-SUMIF(Снабжения!B:B,B13,Снабжения!F:F) -> 0
A14: 10 | B14: Праймер | C14: шт | D14: Кровля и изоляция | E14: =SUMIF(Снабжения!B:B,B14,Снабжения!E:E)-SUMIF(Снабжения!B:B,B14,Снабжения!F:F) -> 0
A15: 11 | B15: Бензин | C15: лт | D15: Кровля и изоляция | E15: =SUMIF(Снабжения!B:B,B15,Снабжения!E:E)-SUMIF(Снабжения!B:B,B15,Снабжения!F:F) -> 0
A16: 12 | B16: Кабель ПВС 2х4 | C16: метр | D16: Электрика | E16: =SUMIF(Снабжения!B:B,B16,Снабжения!E:E)-SUMIF(Снабжения!B:B,B16,Снабжения!F:F) -> 0 | F16: 23072
A17: 13 | B17: Автомат 80А | C17: шт | D17: Электрика | E17: =SUMIF(Снабжения!B:B,B17,Снабжения!E:E)-SUMIF(Снабжения!B:B,B17,Снабжения!F:F) -> 0 | F17: 129150
A18: 14 | B18: Супурги Кичкина | C18: шт | D18: Расходники | E18: =SUMIF(Снабжения!B:B,B18,Снабжения!E:E)-SUMIF(Снабжения!B:B,B18,Снабжения!F:F) -> 0 | F18: 32500
A19: 15 | B19: Мастерок | C19: шт | D19: Ручной инструменты | E19: =SUMIF(Снабжения!B:B,B19,Снабжения!E:E)-SUMIF(Снабжения!B:B,B19,Снабжения!F:F) -> 0 | F19: 30000
A20: 16 | B20: Пенопласт | C20: шт | D20: Расходники | E20: =SUMIF(Снабжения!B:B,B20,Снабжения!E:E)-SUMIF(Снабжения!B:B,B20,Снабжения!F:F) -> 0 | F20: 603684
A21: 17 | B21: Колодка | C21: шт | D21: Электрика | E21: =SUMIF(Снабжения!B:B,B21,Снабжения!E:E)-SUMIF(Снабжения!B:B,B21,Снабжения!F:F) -> 0 | F21: 11224
A22: 18 | B22: Кабель сварки | C22: метр | D22: Электрика | E22: =SUMIF(Снабжения!B:B,B22,Снабжения!E:E)-SUMIF(Снабжения!B:B,B22,Снабжения!F:F) -> 0 | F22: 74000
A23: 19 | B23: Инструмент набор | C23: шт | D23: Ручной инструменты | E23: =SUMIF(Снабжения!B:B,B23,Снабжения!E:E)-SUMIF(Снабжения!B:B,B23,Снабжения!F:F) -> 0 | F23: 410000
A24: 20 | B24: Солидол | C24: кг | D24: Расходники | E24: =SUMIF(Снабжения!B:B,B24,Снабжения!E:E)-SUMIF(Снабжения!B:B,B24,Снабжения!F:F) -> 0 | F24: 80000
A25: 21 | B25: Шприц для солидола | C25: шт | D25: Расходники | E25: =SUMIF(Снабжения!B:B,B25,Снабжения!E:E)-SUMIF(Снабжения!B:B,B25,Снабжения!F:F) -> 0 | F25: 300000
A26: 22 | B26: Профил 60/40/4+Доставка | C26: метр | D26: Мет.из | E26: =SUMIF(Снабжения!B:B,B26,Снабжения!E:E)-SUMIF(Снабжения!B:B,B26,Снабжения!F:F) -> 0
A27: 23 | B27: Запчасти труба | C27: шт | E27: =SUMIF(Снабжения!B:B,B27,Снабжения!E:E)-SUMIF(Снабжения!B:B,B27,Снабжения!F:F) -> 0 | F27: 200000
A28: 24 | B28: Щить Метал 60х40 | C28: шт | D28: Электрика | E28: =SUMIF(Снабжения!B:B,B28,Снабжения!E:E)-SUMIF(Снабжения!B:B,B28,Снабжения!F:F) -> 0
A29: 25 | B29: Кабель ПВС 5х6 | C29: метр | D29: Электрика | E29: =SUMIF(Снабжения!B:B,B29,Снабжения!E:E)-SUMIF(Снабжения!B:B,B29,Снабжения!F:F) -> 0
A30: 26 | B30: Папка-Мамка 380 | C30: шт | D30: Электрика | E30: =SUMIF(Снабжения!B:B,B30,Снабжения!E:E)-SUMIF(Снабжения!B:B,B30,Снабжения!F:F) -> 0
A31: 27 | B31: Автомат 250А | C31: шт | D31: Электрика | E31: =SUMIF(Снабжения!B:B,B31,Снабжения!E:E)-SUMIF(Снабжения!B:B,B31,Снабжения!F:F) -> 0
A32: 28 | B32: Автомат 160А | C32: шт | D32: Электрика | E32: =SUMIF(Снабжения!B:B,B32,Снабжения!E:E)-SUMIF(Снабжения!B:B,B32,Снабжения!F:F) -> 0
A33: 29 | B33: Автомат 40А | C33: шт | D33: Электрика | E33: =SUMIF(Снабжения!B:B,B33,Снабжения!E:E)-SUMIF(Снабжения!B:B,B33,Снабжения!F:F) -> 0
A34: 30 | B34: Автомат 25А | C34: шт | D34: Электрика | E34: =SUMIF(Снабжения!B:B,B34,Снабжения!E:E)-SUMIF(Снабжения!B:B,B34,Снабжения!F:F) -> 0
A35: 31 | B35: Ноль клемма | C35: шт | D35: Электрика | E35: =SUMIF(Снабжения!B:B,B35,Снабжения!E:E)-SUMIF(Снабжения!B:B,B35,Снабжения!F:F) -> 0
A36: 32 | B36: Наконечник алюмин | C36: шт | D36: Электрика | E36: =SUMIF(Снабжения!B:B,B36,Снабжения!E:E)-SUMIF(Снабжения!B:B,B36,Снабжения!F:F) -> 0
A37: 33 | B37: Прожектор | C37: шт | D37: Электрика | E37: =SUMIF(Снабжения!B:B,B37,Снабжения!E:E)-SUMIF(Снабжения!B:B,B37,Снабжения!F:F) -> 0
A38: 34 | B38: Динорейка | C38: шт | D38: Электрика | E38: =SUMIF(Снабжения!B:B,B38,Снабжения!E:E)-SUMIF(Снабжения!B:B,B38,Снабжения!F:F) -> 0
A39: 35 | B39: Леска | C39: шт | D39: Расходники | E39: =SUMIF(Снабжения!B:B,B39,Снабжения!E:E)-SUMIF(Снабжения!B:B,B39,Снабжения!F:F) -> 22 | F39: 4900 | G39: 5
A40: 36 | B40: Болгарка большая О220 | C40: шт | D40: Электроинструменты | E40: =SUMIF(Снабжения!B:B,B40,Снабжения!E:E)-SUMIF(Снабжения!B:B,B40,Снабжения!F:F) -> 1 | F40: 748305
A41: 37 | B41: Больгарка средняя О180 | C41: шт | D41: Электроинструменты | E41: =SUMIF(Снабжения!B:B,B41,Снабжения!E:E)-SUMIF(Снабжения!B:B,B41,Снабжения!F:F) -> 1 | F41: 526585
A42: 38 | B42: Вибратор 4м-6м | C42: шт | D42: Расходники | E42: =SUMIF(Снабжения!B:B,B42,Снабжения!E:E)-SUMIF(Снабжения!B:B,B42,Снабжения!F:F) -> 1 | F42: 515000
A43: 39 | B43: Уровень длина(60см) | C43: шт | D43: Расходники | E43: =SUMIF(Снабжения!B:B,B43,Снабжения!E:E)-SUMIF(Снабжения!B:B,B43,Снабжения!F:F) -> 3 | F43: 51212.5
A44: 40 | B44: Отвес большой | C44: кг | D44: Прочее | E44: =SUMIF(Снабжения!B:B,B44,Снабжения!E:E)-SUMIF(Снабжения!B:B,B44,Снабжения!F:F) -> 0 | F44: 9881
A45: 41 | B45: Акрил лампа 18W | C45: шт | D45: Электрика | E45: =SUMIF(Снабжения!B:B,B45,Снабжения!E:E)-SUMIF(Снабжения!B:B,B45,Снабжения!F:F) -> 1 | F45: 14580.5
A46: 42 | B46: Акрил лампа 24W | C46: шт | D46: Электрика | E46: =SUMIF(Снабжения!B:B,B46,Снабжения!E:E)-SUMIF(Снабжения!B:B,B46,Снабжения!F:F) -> 1 | F46: 17232
A47: 43 | B47: Болторез 900мм | C47: шт | D47: Ручной инструменты | E47: =SUMIF(Снабжения!B:B,B47,Снабжения!E:E)-SUMIF(Снабжения!B:B,B47,Снабжения!F:F) -> 1 | F47: 263520
A48: 44 | B48: Трос стропа 6м | C48: шт | D48: Расходники | E48: =SUMIF(Снабжения!B:B,B48,Снабжения!E:E)-SUMIF(Снабжения!B:B,B48,Снабжения!F:F) -> 1 | F48: 5370000
A49: 45 | B49: Сварка аппарат | C49: шт | E49: =SUMIF(Снабжения!B:B,B49,Снабжения!E:E)-SUMIF(Снабжения!B:B,B49,Снабжения!F:F) -> 1 | F49: 1961850
A50: 46 | B50: Лампа 50W | C50: шт | D50: Электрика | E50: =SUMIF(Снабжения!B:B,B50,Снабжения!E:E)-SUMIF(Снабжения!B:B,B50,Снабжения!F:F) -> 1 | F50: 52398
A51: 47 | B51: Супурги Котта | C51: шт | D51: Прочее | E51: =SUMIF(Снабжения!B:B,B51,Снабжения!E:E)-SUMIF(Снабжения!B:B,B51,Снабжения!F:F) -> 1 | F51: 32500
A52: 48 | B52: Весы 200кг | C52: шт | D52: Прочее | E52: =SUMIF(Снабжения!B:B,B52,Снабжения!E:E)-SUMIF(Снабжения!B:B,B52,Снабжения!F:F) -> 1 | F52: 250000
A53: 49 | B53: Патрон дрел | C53: шт | D53: Расходники | E53: =SUMIF(Снабжения!B:B,B53,Снабжения!E:E)-SUMIF(Снабжения!B:B,B53,Снабжения!F:F) -> 0 | F53: 29402
A54: 50 | B54: Бочка для воды 1 тонна | C54: шт | D54: Прочее | E54: =SUMIF(Снабжения!B:B,B54,Снабжения!E:E)-SUMIF(Снабжения!B:B,B54,Снабжения!F:F) -> 1 | F54: 1050000
A55: 51 | B55: Карчер | C55: шт | D55: Электроинструменты | E55: =SUMIF(Снабжения!B:B,B55,Снабжения!E:E)-SUMIF(Снабжения!B:B,B55,Снабжения!F:F) -> 1 | F55: 2900000
A56: 52 | B56: Турбофен | C56: шт | D56: Электроинструменты | E56: =SUMIF(Снабжения!B:B,B56,Снабжения!E:E)-SUMIF(Снабжения!B:B,B56,Снабжения!F:F) -> 1 | F56: 900000
A57: 53 | B57: Болгарка средняя О180 | C57: шт | D57: Электроинструменты | E57: =SUMIF(Снабжения!B:B,B57,Снабжения!E:E)-SUMIF(Снабжения!B:B,B57,Снабжения!F:F) -> 1 | F57: 698000
A58: 54 | B58: Полиэтиновый пленка | C58: рулон | D58: Расходники | E58: =SUMIF(Снабжения!B:B,B58,Снабжения!E:E)-SUMIF(Снабжения!B:B,B58,Снабжения!F:F) -> 1 | F58: 964410
A59: 55 | B59: Вертолет | C59: шт | D59: Электроинструменты | E59: =SUMIF(Снабжения!B:B,B59,Снабжения!E:E)-SUMIF(Снабжения!B:B,B59,Снабжения!F:F) -> 0 | F59: 4880000
A60: 56 | B60: Кувалда | C60: шт | D60: Ручной инструменты | E60: =SUMIF(Снабжения!B:B,B60,Снабжения!E:E)-SUMIF(Снабжения!B:B,B60,Снабжения!F:F) -> 2 | F60: 95700
A61: 57 | B61: Болта | C61: шт | D61: Ручной инструменты | E61: =SUMIF(Снабжения!B:B,B61,Снабжения!E:E)-SUMIF(Снабжения!B:B,B61,Снабжения!F:F) -> 2
A62: 58 | B62: Аэрозол Красный | C62: шт | D62: Расходники | E62: =SUMIF(Снабжения!B:B,B62,Снабжения!E:E)-SUMIF(Снабжения!B:B,B62,Снабжения!F:F) -> 2 | F62: 11070
A63: 59 | B63: Уровень длина(80см) | C63: шт | D63: Прочее | E63: =SUMIF(Снабжения!B:B,B63,Снабжения!E:E)-SUMIF(Снабжения!B:B,B63,Снабжения!F:F) -> 2 | F63: 60250
A64: 60 | B64: Шруповерт с аккум | C64: шт | D64: Электроинструменты | E64: =SUMIF(Снабжения!B:B,B64,Снабжения!E:E)-SUMIF(Снабжения!B:B,B64,Снабжения!F:F) -> 2 | F64: 1108600
A65: 61 | B65: Перфоратор | C65: шт | D65: Электроинструменты | E65: =SUMIF(Снабжения!B:B,B65,Снабжения!E:E)-SUMIF(Снабжения!B:B,B65,Снабжения!F:F) -> 2 | F65: 831450
A66: 62 | B66: Чалка 4Т | C66: шт | D66: Ручной инструменты | E66: =SUMIF(Снабжения!B:B,B66,Снабжения!E:E)-SUMIF(Снабжения!B:B,B66,Снабжения!F:F) -> 2 | F66: 135300
A67: 63 | B67: Чалка 5Т | C67: шт | D67: Ручной инструменты | E67: =SUMIF(Снабжения!B:B,B67,Снабжения!E:E)-SUMIF(Снабжения!B:B,B67,Снабжения!F:F) -> 2 | F67: 250920
A68: 64 | B68: Печка | C68: шт | E68: =SUMIF(Снабжения!B:B,B68,Снабжения!E:E)-SUMIF(Снабжения!B:B,B68,Снабжения!F:F) -> 2 | F68: 265000
A69: 65 | B69: Патрон | C69: шт | D69: Электрика | E69: =SUMIF(Снабжения!B:B,B69,Снабжения!E:E)-SUMIF(Снабжения!B:B,B69,Снабжения!F:F) -> 2 | F69: 2460
A70: 66 | B70: Вибратор глубынний | C70: шт | D70: Электроинструменты | E70: =SUMIF(Снабжения!B:B,B70,Снабжения!E:E)-SUMIF(Снабжения!B:B,B70,Снабжения!F:F) -> 2 | F70: 549000
A71: 67 | B71: Фонарь | C71: шт | D71: Прочее | E71: =SUMIF(Снабжения!B:B,B71,Снабжения!E:E)-SUMIF(Снабжения!B:B,B71,Снабжения!F:F) -> 2 | F71: 227500
A72: 68 | B72: Диск отрезной 180 | C72: шт | D72: Расходники | E72: =SUMIF(Снабжения!B:B,B72,Снабжения!E:E)-SUMIF(Снабжения!B:B,B72,Снабжения!F:F) -> 42 | F72: 9150
A73: 69 | B73: Сварка маска | C73: шт | D73: Расходники | E73: =SUMIF(Снабжения!B:B,B73,Снабжения!E:E)-SUMIF(Снабжения!B:B,B73,Снабжения!F:F) -> 2 | F73: 133346
A74: 70 | B74: Гвоздодёр | C74: шт | D74: Ручной инструменты | E74: =SUMIF(Снабжения!B:B,B74,Снабжения!E:E)-SUMIF(Снабжения!B:B,B74,Снабжения!F:F) -> 0 | F74: 135000
A75: 71 | B75: Опора | C75: коп | D75: Расходники | E75: =SUMIF(Снабжения!B:B,B75,Снабжения!E:E)-SUMIF(Снабжения!B:B,B75,Снабжения!F:F) -> 20
A76: 72 | B76: Аэрозол Белый | C76: шт | D76: Расходники | E76: =SUMIF(Снабжения!B:B,B76,Снабжения!E:E)-SUMIF(Снабжения!B:B,B76,Снабжения!F:F) -> 2 | F76: 14000
A77: 73 | B77: Даста кетмон | C77: шт | D77: Ручной инструменты | E77: =SUMIF(Снабжения!B:B,B77,Снабжения!E:E)-SUMIF(Снабжения!B:B,B77,Снабжения!F:F) -> 3 | F77: 8000
A78: 74 | B78: Пчелка О180 | C78: шт | D78: Электроинструменты | E78: =SUMIF(Снабжения!B:B,B78,Снабжения!E:E)-SUMIF(Снабжения!B:B,B78,Снабжения!F:F) -> 3 | F78: 738000
A79: 75 | B79: Арава | C79: шт | D79: Прочее | E79: =SUMIF(Снабжения!B:B,B79,Снабжения!E:E)-SUMIF(Снабжения!B:B,B79,Снабжения!F:F) -> 4 | F79: 690000
A80: 76 | B80: Метр 5м | C80: шт | D80: Расходники | E80: =SUMIF(Снабжения!B:B,B80,Снабжения!E:E)-SUMIF(Снабжения!B:B,B80,Снабжения!F:F) -> 10 | F80: 17000
A81: 77 | B81: Лопата сопковой | C81: шт | D81: Расходники | E81: =SUMIF(Снабжения!B:B,B81,Снабжения!E:E)-SUMIF(Снабжения!B:B,B81,Снабжения!F:F) -> 5 | F81: 17739
A82: 78 | B82: Доставка | C82: услуга | E82: =SUMIF(Снабжения!B:B,B82,Снабжения!E:E)-SUMIF(Снабжения!B:B,B82,Снабжения!F:F) -> 8 | F82: 130000 | H82: ✓
A83: 79 | B83: Вертолет Диск | C83: шт | D83: Расходники | E83: =SUMIF(Снабжения!B:B,B83,Снабжения!E:E)-SUMIF(Снабжения!B:B,B83,Снабжения!F:F) -> 4 | F83: 395200
A84: 80 | B84: Скотч | C84: шт | D84: Расходники | E84: =SUMIF(Снабжения!B:B,B84,Снабжения!E:E)-SUMIF(Снабжения!B:B,B84,Снабжения!F:F) -> 0 | F84: 26000
A85: 81 | B85: Электр коробка 100х100 | C85: шт | D85: Расходники | E85: =SUMIF(Снабжения!B:B,B85,Снабжения!E:E)-SUMIF(Снабжения!B:B,B85,Снабжения!F:F) -> 6 | F85: 16000
A86: 82 | B86: Бурь 14*160 | C86: шт | D86: Расходники | E86: =SUMIF(Снабжения!B:B,B86,Снабжения!E:E)-SUMIF(Снабжения!B:B,B86,Снабжения!F:F) -> 8 | F86: 9037.5
A87: 83 | B87: Сверло тахта 23мм | C87: шт | D87: Расходники | E87: =SUMIF(Снабжения!B:B,B87,Снабжения!E:E)-SUMIF(Снабжения!B:B,B87,Снабжения!F:F) -> 7 | F87: 28548
A88: 84 | B88: Лопата штиковой | C88: шт | D88: Ручной инструменты | E88: =SUMIF(Снабжения!B:B,B88,Снабжения!E:E)-SUMIF(Снабжения!B:B,B88,Снабжения!F:F) -> 10 | F88: 17739
A89: 85 | B89: Кетмон | C89: шт | D89: Ручной инструменты | E89: =SUMIF(Снабжения!B:B,B89,Снабжения!E:E)-SUMIF(Снабжения!B:B,B89,Снабжения!F:F) -> 10 | F89: 32562
A90: 86 | B90: Болга | C90: шт | D90: Расходники | E90: =SUMIF(Снабжения!B:B,B90,Снабжения!E:E)-SUMIF(Снабжения!B:B,B90,Снабжения!F:F) -> 10 | F90: 79666
A91: 87 | B91: Изолента | C91: шт | D91: Электрика | E91: =SUMIF(Снабжения!B:B,B91,Снабжения!E:E)-SUMIF(Снабжения!B:B,B91,Снабжения!F:F) -> 8 | F91: 3904
A92: 88 | B92: Ремень | C92: шт | D92: Расходники | E92: =SUMIF(Снабжения!B:B,B92,Снабжения!E:E)-SUMIF(Снабжения!B:B,B92,Снабжения!F:F) -> 0 | F92: 15000
A93: 89 | B93: Валик | C93: шт | D93: Расходники | E93: =SUMIF(Снабжения!B:B,B93,Снабжения!E:E)-SUMIF(Снабжения!B:B,B93,Снабжения!F:F) -> 9 | F93: 13800
A94: 90 | B94: Тройник | C94: шт | D94: Расходники | E94: =SUMIF(Снабжения!B:B,B94,Снабжения!E:E)-SUMIF(Снабжения!B:B,B94,Снабжения!F:F) -> 11 | F94: 10200 | G94: 12
A95: 91 | B95: Даста лопата | C95: шт | D95: Ручной инструменты | E95: =SUMIF(Снабжения!B:B,B95,Снабжения!E:E)-SUMIF(Снабжения!B:B,B95,Снабжения!F:F) -> 13 | F95: 8000 | G95: 6
A96: 92 | B96: Диск отрезной 230 | C96: шт | D96: Расходники | E96: =SUMIF(Снабжения!B:B,B96,Снабжения!E:E)-SUMIF(Снабжения!B:B,B96,Снабжения!F:F) -> 87 | F96: 12078
A97: 93 | B97: Пена монтажная | C97: шт | D97: Расходники | E97: =SUMIF(Снабжения!B:B,B97,Снабжения!E:E)-SUMIF(Снабжения!B:B,B97,Снабжения!F:F) -> 33 | F97: 45000 | G97: 47
A98: 94 | B98: Подшибник | C98: шт | D98: Расходники | E98: =SUMIF(Снабжения!B:B,B98,Снабжения!E:E)-SUMIF(Снабжения!B:B,B98,Снабжения!F:F) -> 0 | F98: 5000
A99: 95 | B99: Электрод MP-3 2.5 | C99: кг | D99: Расходники | E99: =SUMIF(Снабжения!B:B,B99,Снабжения!E:E)-SUMIF(Снабжения!B:B,B99,Снабжения!F:F) -> 41.5 | F99: 34000 | G99: 10
A100: 96 | B100: Вилка | C100: шт | D100: Расходники | E100: =SUMIF(Снабжения!B:B,B100,Снабжения!E:E)-SUMIF(Снабжения!B:B,B100,Снабжения!F:F) -> 8 | F100: 5600 | G100: 6
A101: 97 | B101: Бурь 14*350 | C101: шт | D101: Расходники | E101: =SUMIF(Снабжения!B:B,B101,Снабжения!E:E)-SUMIF(Снабжения!B:B,B101,Снабжения!F:F) -> 18 | F101: 24000
...

Sheet Контакты
A1: 📞 КОНТАКТЫ • GREEN TASHKENT
A3: № | B3: 👤 Имя | C3: 💼 Должность / Что делает | D3: 📱 Телефон | E3: 🏢 Организация | F3: 📝 Примечание
A4: =ROW()-3 -> 1 | B4: Нурсаид | C4: Разнорабочий,Охрана | D4: +998 93 763 22 32 | E4: Мева Шарбат Илмий Экспереминтал
A5: =ROW()-3 -> 2 | B5: Артизан | C5: Сув чикариш хизмати | D5: +998 99 200 80 00 | E5: -
A6: =ROW()-3 -> 3 | B6: Олим Ака | C6: Повар | D6: +998 93 094 26 67 | E6: Мева Шарбат Илмий Экспереминтал
A7: =ROW()-3 -> 4 | B7: Мурод Ака | C7: Бозорлик | D7: +998 88 188 81 14 | E7: Юнусобод Бозор
A8: =ROW()-3 -> 5 | B8: Миродил | C8: Охрана | D8: +998 97 599 94 01 | E8: Мева Шарбат Илмий Экспереминтал
A9: =ROW()-3 -> 6 | B9: Садулла Ака | C9: Бухгалтерия | D9: +998 97 146 69 46 | E9: Мева Шарбат Илмий Экспереминтал
A10: =ROW()-3 -> 7 | B10: Хабибулло | C10: Менеджер | D10: +998 99 895 52 72 | E10: Мева Шарбат Илмий Экспереминтал
A11: =ROW()-3 -> 8 | B11: Миржалол | C11: Разнорабочий,Охрана | D11: +998 93 042 49 39 | E11: Мева Шарбат Илмий Экспереминтал
A12: =ROW()-3 -> 9 | B12: Фазлиддин Ака | C12: Электрик | D12: +998 90 933 90 07 | E12: Мева Шарбат Илмий Экспереминтал
A13: =ROW()-3 -> 10 | B13: Элер | C13: Экскаватор 140В | D13: +998 97 035 27 35 | E13: -
A14: =ROW()-3 -> 11 | B14: Хайрулла | C14: Мой Опалубка | D14: +998 90 973 07 08 | E14: -
A15: =ROW()-3 -> 12 | B15: - | C15: Экскаватор 60В | D15: +998 95 767 97 87 | E15: -
... A23: =ROW()-3 -> 20 | B23: Дилшод Ака | C23: Ремень-Подшибники | D23: +998 98 368 33 31 | E23: -
A24: =ROW()-3 -> 21 | B24: Камера | C24: Камера наблюдение | D24: +998 95 551 90 90
A25: =ROW()-3 -> 22 | D25: +998
A26: =ROW()-3 -> 23 | D26: +998
A27: =ROW()-3 -> 24 | D27: +998
A28: =ROW()-3 -> 25 | D28: +998
A29: =ROW()-3 -> 26 | D29: +998
A30: =ROW()-3 -> 27 | D30: +998
A31: =ROW()-3 -> 28 | D31: +998
A32: =ROW()-3 -> 29 | D32: +998
A33: =ROW()-3 -> 30 | D33: +998
A34: =ROW()-3 -> 31 | D34: +998
A35: =ROW()-3 -> 32 | D35: +998
A36: =ROW()-3 -> 33 | D36: +998
... A53: =ROW()-3 -> 50 | D53: +998

Sheet Бетон
A1: Дата | B1: Грузоотправитель | C1: Номер авто | D1: Марка бетона | E1: Кол-во | F1: Сумма | G1: По доллару
A2: 45978 | B2: ООО "ADAMANT SAVDO PLYUS" | C2: 01 125 QKA | D2: М400 | E2: 9 | F2: =IF(D2="М400", E2*740000, IF(D2="M150", E2*600000, IF(D2="M300", E2*670000, IF(D2="M350", E2*700000, 0)))) -> 6660000 | G2: =IF(A2<>"", F2/ VLOOKUP(A2, '[1]Курс валют'!$A:$D, 4, 0), "") -> 564.40678
A3: 45978 | B3: ООО "ADAMANT SAVDO PLYUS" | C3: 01 М021795 | D3: М400 | E3: 10 | F3: =IF(D3="М400", E3*740000, IF(D3="M150", E3*600000, IF(D3="M300", E3*670000, IF(D3="M350", E3*700000, 0)))) -> 7400000 | G3: =IF(A3<>"", F3/ VLOOKUP(A3, '[1]Курс валют'!$A:$D, 4, 0), "") -> 627.11864
A4: 45978 | B4: ООО "ADAMANT SAVDO PLYUS" | C4: 01 W 646 TB | D4: М400 | E4: 9 | F4: =IF(D4="М400", E4*740000, IF(D4="M150", E4*600000, IF(D4="M300", E4*670000, IF(D4="M350", E4*700000, 0)))) -> 6660000 | G4: =IF(A4<>"", F4/ VLOOKUP(A4, '[1]Курс валют'!$A:$D, 4, 0), "") -> 564.40678
A5: 45978 | B5: ООО "ADAMANT SAVDO PLYUS" | C5: 01 910 VKA | D5: М400 | E5: 10 | F5: =IF(D5="М400", E5*740000, IF(D5="M150", E5*600000, IF(D5="M300", E5*670000, IF(D5="M350", E5*700000, 0)))) -> 7400000 | G5: =IF(A5<>"", F5/ VLOOKUP(A5, '[1]Курс валют'!$A:$D, 4, 0), "") -> 627.11864
A6: 45978 | B6: ООО "ADAMANT SAVDO PLYUS" | C6: 01 908 VKA | D6: М400 | E6: 10 | F6: =IF(D6="М400", E6*740000, IF(D6="M150", E6*600000, IF(D6="M300", E6*670000, IF(D6="M350", E6*700000, 0)))) -> 7400000 | G6: =IF(A6<>"", F6/ VLOOKUP(A6, '[1]Курс валют'!$A:$D, 4, 0), "") -> 627.11864
A7: 45978 | B7: ООО "ADAMANT SAVDO PLYUS" | C7: 40 783 YBA | D7: М400 | E7: 10 | F7: =IF(D7="М400", E7*740000, IF(D7="M150", E7*600000, IF(D7="M300", E7*670000, IF(D7="M350", E7*700000, 0)))) -> 7400000 | G7: =IF(A7<>"", F7/ VLOOKUP(A7, '[1]Курс валют'!$A:$D, 4, 0), "") -> 627.11864
A8: 45978 | B8: ООО "ADAMANT SAVDO PLYUS" | C8: 01 906 VKA | D8: М400 | E8: 10 | F8: =IF(D8="М400", E8*740000, IF(D8="M150", E8*600000, IF(D8="M300", E8*670000, IF(D8="M350", E8*700000, 0)))) -> 7400000 | G8: =IF(A8<>"", F8/ VLOOKUP(A8, '[1]Курс валют'!$A:$D, 4, 0), "") -> 627.11864
A9: 45978 | B9: ООО "ADAMANT SAVDO PLYUS" | C9: 01 731 FJA | D9: М400 | E9: 12 | F9: =IF(D9="М400", E9*740000, IF(D9="M150", E9*600000, IF(D9="M300", E9*670000, IF(D9="M350", E9*700000, 0)))) -> 8880000 | G9: =IF(A9<>"", F9/ VLOOKUP(A9, '[1]Курс валют'!$A:$D, 4, 0), "") -> 752.54237
A10: 45978 | B10: ООО "ADAMANT SAVDO PLYUS" | C10: 01 M021797 | D10: М400 | E10: 10 | F10: =IF(D10="М400", E10*740000, IF(D10="M150", E10*600000, IF(D10="M300", E10*670000, IF(D10="M350", E10*700000, 0)))) -> 7400000 | G10: =IF(A10<>"", F10/ VLOOKUP(A10, '[1]Курс валют'!$A:$D, 4, 0), "") -> 627.11864
A11: 45978 | B11: ООО "ADAMANT SAVDO PLYUS" | C11: 01 917 JFA | D11: М400 | E11: 10 | F11: =IF(D11="М400", E11*740000, IF(D11="M150", E11*600000, IF(D11="M300", E11*670000, IF(D11="M350", E11*700000, 0)))) -> 7400000 | G11: =IF(A11<>"", F11/ VLOOKUP(A11, '[1]Курс валют'!$A:$D, 4, 0), "") -> 627.11864
A12: 45978 | B12: ООО "ADAMANT SAVDO PLYUS" | C12: 01 908 VKA | D12: М400 | E12: 10 | F12: =IF(D12="М400", E12*740000, IF(D12="M150", E12*600000, IF(D12="M300", E12*670000, IF(D12="M350", E12*700000, 0)))) -> 7400000 | G12: =IF(A12<>"", F12/ VLOOKUP(A12, '[1]Курс валют'!$A:$D, 4, 0), "") -> 627.11864
A13: 45978 | B13: ООО "ADAMANT SAVDO PLYUS" | C13: 01 729 FJA | D13: М400 | E13: 10 | F13: =IF(D13="М400", E13*740000, IF(D13="M150", E13*600000, IF(D13="M300", E13*670000, IF(D13="M350", E13*700000, 0)))) -> 7400000 | G13: =IF(A13<>"", F13/ VLOOKUP(A13, '[1]Курс валют'!$A:$D, 4, 0), "") -> 627.11864
A14: 17.11.2025 Итог | E14: =SUBTOTAL(9,E2:E13) -> 120 | F14: =SUBTOTAL(9,F2:F13) -> 88800000
A15: 45990 | B15: ООО "ADAMANT SAVDO PLYUS" | C15: 01 M021798 | D15: М400 | E15: 8.5 | F15: =IF(D15="М400", E15*740000, IF(D15="M150", E15*600000, IF(D15="M300", E15*670000, IF(D15="M350", E15*700000, 0)))) -> 6290000 | G15: =IF(A15<>"", F15/ VLOOKUP(A15, '[1]Курс валют'!$A:$D, 4, 0), "") -> 542.24138
A16: 29.11.2025 Итог | E16: =SUBTOTAL(9,E15:E15) -> 8.5 | F16: =SUBTOTAL(9,F15:F15) -> 6290000
A17: 46058 | B17: ООО "ADAMANT SAVDO PLYUS" | C17: 01 162 HLA | D17: M150 | E17: 12 | F17: =IF(D17="М400", E17*740000, IF(D17="M150", E17*600000, IF(D17="M300", E17*670000, IF(D17="M350", E17*700000, 0)))) -> 7200000 | G17: =IF(A17<>"", F17/ VLOOKUP(A17, '[1]Курс валют'!$A:$D, 4, 0), "") -> 590.16393
A18: 46058 | B18: ООО "ADAMANT SAVDO PLYUS" | C18: 01 569 HGA | D18: M150 | E18: 12 | F18: =IF(D18="М400", E18*740000, IF(D18="M150", E18*600000, IF(D18="M300", E18*670000, IF(D18="M350", E18*700000, 0)))) -> 7200000 | G18: =IF(A18<>"", F18/ VLOOKUP(A18, '[1]Курс валют'!$A:$D, 4, 0), "") -> 590.16393
A19: 46058 | B19: ООО "ADAMANT SAVDO PLYUS" | C19: 01 169 HLA | D19: M150 | E19: 9 | F19: =IF(D19="М400", E19*740000, IF(D19="M150", E19*600000, IF(D19="M300", E19*670000, IF(D19="M350", E19*700000, 0)))) -> 5400000 | G19: =IF(A19<>"", F19/ VLOOKUP(A19, '[1]Курс валют'!$A:$D, 4, 0), "") -> 442.62295
A20: 46058 | B20: ООО "ADAMANT SAVDO PLYUS" | C20: 01 168 HLA | D20: M150 | E20: 12 | F20: =IF(D20="М400", E20*740000, IF(D20="M150", E20*600000, IF(D20="M300", E20*670000, IF(D20="M350", E20*700000, 0)))) -> 7200000 | G20: =IF(A20<>"", F20/ VLOOKUP(A20, '[1]Курс валют'!$A:$D, 4, 0), "") -> 590.16393
A21: 46058 | B21: ООО "ADAMANT SAVDO PLYUS" | C21: 01 908 VKA | D21: M150 | E21: 10 | F21: =IF(D21="М400", E21*740000, IF(D21="M150", E21*600000, IF(D21="M300", E21*670000, IF(D21="M350", E21*700000, 0)))) -> 6000000 | G21: =IF(A21<>"", F21/ VLOOKUP(A21, '[1]Курс валют'!$A:$D, 4, 0), "") -> 491.80328
A22: 46058 | B22: ООО "ADAMANT SAVDO PLYUS" | C22: 01 125 QKA | D22: M150 | E22: 9 | F22: =IF(D22="М400", E22*740000, IF(D22="M150", E22*600000, IF(D22="M300", E22*670000, IF(D22="M350", E22*700000, 0)))) -> 5400000 | G22: =IF(A22<>"", F22/ VLOOKUP(A22, '[1]Курс валют'!$A:$D, 4, 0), "") -> 442.62295
A23: 46058 | B23: ООО "ADAMANT SAVDO PLYUS" | C23: 01 652 WLA | D23: M150 | E23: 9 | F23: =IF(D23="М400", E23*740000, IF(D23="M150", E23*600000, IF(D23="M300", E23*670000, IF(D23="M350", E23*700000, 0)))) -> 5400000 | G23: =IF(A23<>"", F23/ VLOOKUP(A23, '[1]Курс валют'!$A:$D, 4, 0), "") -> 442.62295
A24: 46058 | B24: ООО "ADAMANT SAVDO PLYUS" | C24: 01 M021797 | D24: M150 | E24: 10 | F24: =IF(D24="М400", E24*740000, IF(D24="M150", E24*600000, IF(D24="M300", E24*670000, IF(D24="M350", E24*700000, 0)))) -> 6000000 | G24: =IF(A24<>"", F24/ VLOOKUP(A24, '[1]Курс валют'!$A:$D, 4, 0), "") -> 491.80328
A25: 46058 | B25: ООО "ADAMANT SAVDO PLYUS" | C25: 01 M021795 | D25: M150 | E25: 10 | F25: =IF(D25="М400", E25*740000, IF(D25="M150", E25*600000, IF(D25="M300", E25*670000, IF(D25="M350", E25*700000, 0)))) -> 6000000 | G25: =IF(A25<>"", F25/ VLOOKUP(A25, '[1]Курс валют'!$A:$D, 4, 0), "") -> 491.80328
A26: 46058 | B26: ООО "ADAMANT SAVDO PLYUS" | C26: 01 481 BFA | D26: M150 | E26: 9 | F26: =IF(D26="М400", E26*740000, IF(D26="M150", E26*600000, IF(D26="M300", E26*670000, IF(D26="M350", E26*700000, 0)))) -> 5400000 | G26: =IF(A26<>"", F26/ VLOOKUP(A26, '[1]Курс валют'!$A:$D, 4, 0), "") -> 442.62295
A27: 46058 | B27: ООО "ADAMANT SAVDO PLYUS" | C27: 01 276 PLA | D27: M150 | E27: 10 | F27: =IF(D27="М400", E27*740000, IF(D27="M150", E27*600000, IF(D27="M300", E27*670000, IF(D27="M350", E27*700000, 0)))) -> 6000000 | G27: =IF(A27<>"", F27/ VLOOKUP(A27, '[1]Курс валют'!$A:$D, 4, 0), "") -> 491.80328
A28: 46058 | B28: ООО "ADAMANT SAVDO PLYUS" | C28: 01 539 LKA | D28: M150 | E28: 9 | F28: =IF(D28="М400", E28*740000, IF(D28="M150", E28*600000, IF(D28="M300", E28*670000, IF(D28="M350", E28*700000, 0)))) -> 5400000 | G28: =IF(A28<>"", F28/ VLOOKUP(A28, '[1]Курс валют'!$A:$D, 4, 0), "") -> 442.62295
... A47: 46058 | B47: ООО "ADAMANT SAVDO PLYUS" | C47: 01 276 PLA | D47: M150 | E47: 10 | F47: =IF(D47="М400", E47*740000, IF(D47="M150", E47*600000, IF(D47="M300", E47*670000, IF(D47="M350", E47*700000, 0)))) -> 6000000 | G47: =IF(A47<>"", F47/ VLOOKUP(A47, '[1]Курс валют'!$A:$D, 4, 0), "") -> 491.80328
A48: 05.02.2026 Итог | E48: =SUBTOTAL(9,E17:E47) -> 310 | F48: =SUBTOTAL(9,F17:F47) -> 186000000
A49: 46067 | B49: ООО "ADAMANT SAVDO PLYUS" | C49: 01 273 PLA | D49: M300 | E49: 10 | F49: =IF(D49="М400", E49*740000, IF(D49="M150", E49*600000, IF(D49="M300", E49*670000, IF(D49="M350", E49*700000, 0)))) -> 6700000 | G49: =IF(A49<>"", F49/ VLOOKUP(A49, '[1]Курс валют'!$A:$D, 4, 0), "") -> 550.0821
A50: 46067 | B50: ООО "ADAMANT SAVDO PLYUS" | C50: 01 M021796 | D50: M300 | E50: 10 | F50: =IF(D50="М400", E50*740000, IF(D50="M150", E50*600000, IF(D50="M300", E50*670000, IF(D50="M350", E50*700000, 0)))) -> 6700000 | G50: =IF(A50<>"", F50/ VLOOKUP(A50, '[1]Курс валют'!$A:$D, 4, 0), "") -> 550.0821
A51: 46067 | B51: ООО "ADAMANT SAVDO PLYUS" | C51: 01 908 VKA | D51: M300 | E51: 10 | F51: =IF(D51="М400", E51*740000, IF(D51="M150", E51*600000, IF(D51="M300", E51*670000, IF(D51="M350", E51*700000, 0)))) -> 6700000 | G51: =IF(A51<>"", F51/ VLOOKUP(A51, '[1]Курс валют'!$A:$D, 4, 0), "") -> 550.0821
A52: 46067 | B52: ООО "ADAMANT SAVDO PLYUS" | C52: 01 162 HLA | D52: M300 | E52: 12 | F52: =IF(D52="М400", E52*740000, IF(D52="M150", E52*600000, IF(D52="M300", E52*670000, IF(D52="M350", E52*700000, 0)))) -> 8040000 | G52: =IF(A52<>"", F52/ VLOOKUP(A52, '[1]Курс валют'!$A:$D, 4, 0), "") -> 660.09852
A53: 46067 | B53: ООО "ADAMANT SAVDO PLYUS" | C53: 01 569 HGA | D53: M300 | E53: 12 | F53: =IF(D53="М400", E53*740000, IF(D53="M150", E53*600000, IF(D53="M300", E53*670000, IF(D53="M350", E53*700000, 0)))) -> 8040000 | G53: =IF(A53<>"", F53/ VLOOKUP(A53, '[1]Курс валют'!$A:$D, 4, 0), "") -> 660.09852
A54: 46067 | B54: ООО "ADAMANT SAVDO PLYUS" | C54: 01 M021798 | D54: M300 | E54: 10 | F54: =IF(D54="М400", E54*740000, IF(D54="M150", E54*600000, IF(D54="M300", E54*670000, IF(D54="M350", E54*700000, 0)))) -> 6700000 | G54: =IF(A54<>"", F54/ VLOOKUP(A54, '[1]Курс валют'!$A:$D, 4, 0), "") -> 550.0821
A55: 46067 | B55: ООО "ADAMANT SAVDO PLYUS" | C55: 01 652 WLA | D55: M300 | E55: 9 | F55: =IF(D55="М400", E55*740000, IF(D55="M150", E55*600000, IF(D55="M300", E55*670000, IF(D55="M350", E55*700000, 0)))) -> 6030000 | G55: =IF(A55<>"", F55/ VLOOKUP(A55, '[1]Курс валют'!$A:$D, 4, 0), "") -> 495.07389
A56: 46067 | B56: ООО "ADAMANT SAVDO PLYUS" | C56: 01 972 CJA | D56: M300 | E56: 9 | F56: =IF(D56="М400", E56*740000, IF(D56="M150", E56*600000, IF(D56="M300", E56*670000, IF(D56="M350", E56*700000, 0)))) -> 6030000 | G56: =IF(A56<>"", F56/ VLOOKUP(A56, '[1]Курс валют'!$A:$D, 4, 0), "") -> 495.07389
A57: 46067 | B57: ООО "ADAMANT SAVDO PLYUS" | C57: 01 125 QKA | D57: M300 | E57: 9 | F57: =IF(D57="М400", E57*740000, IF(D57="M150", E57*600000, IF(D57="M300", E57*670000, IF(D57="M350", E57*700000, 0)))) -> 6030000 | G57: =IF(A57<>"", F57/ VLOOKUP(A57, '[1]Курс валют'!$A:$D, 4, 0), "") -> 495.07389
A58: 46067 | B58: ООО "ADAMANT SAVDO PLYUS" | C58: 01 731 FJA | D58: M300 | E58: 12 | F58: =IF(D58="М400", E58*740000, IF(D58="M150", E58*600000, IF(D58="M300", E58*670000, IF(D58="M350", E58*700000, 0)))) -> 8040000 | G58: =IF(A58<>"", F58/ VLOOKUP(A58, '[1]Курс валют'!$A:$D, 4, 0), "") -> 660.09852
A59: 46067 | B59: ООО "ADAMANT SAVDO PLYUS" | C59: 01 729 FJA | D59: M300 | E59: 12 | F59: =IF(D59="М400", E59*740000, IF(D59="M150", E59*600000, IF(D59="M300", E59*670000, IF(D59="M350", E59*700000, 0)))) -> 8040000 | G59: =IF(A59<>"", F59/ VLOOKUP(A59, '[1]Курс валют'!$A:$D, 4, 0), "") -> 660.09852
A60: 46067 | B60: ООО "ADAMANT SAVDO PLYUS" | C60: 01 169 HLA | D60: M300 | E60: 9 | F60: =IF(D60="М400", E60*740000, IF(D60="M150", E60*600000, IF(D60="M300", E60*670000, IF(D60="M350", E60*700000, 0)))) -> 6030000 | G60: =IF(A60<>"", F60/ VLOOKUP(A60, '[1]Курс валют'!$A:$D, 4, 0), "") -> 495.07389
... A77: 46067 | B77: ООО "ADAMANT SAVDO PLYUS" | C77: 01 163 HLA | D77: M300 | E77: 9 | F77: =IF(D77="М400", E77*740000, IF(D77="M150", E77*600000, IF(D77="M300", E77*670000, IF(D77="M350", E77*700000, 0)))) -> 6030000 | G77: =IF(A77<>"", F77/ VLOOKUP(A77, '[1]Курс валют'!$A:$D, 4, 0), "") -> 495.07389
A78: 14.02.2026 Итог | E78: =SUBTOTAL(9,E49:E77) -> 287 | F78: =SUBTOTAL(9,F49:F77) -> 192290000
A79: 46072 | B79: ООО "ADAMANT SAVDO PLYUS" | C79: 01 354 HMA | D79: M300 | E79: 9 | F79: =IF(D79="М400", E79*740000, IF(D79="M150", E79*600000, IF(D79="M300", E79*670000, IF(D79="M350", E79*700000, 0)))) -> 6030000 | G79: =IF(A79<>"", F79/ VLOOKUP(A79, '[1]Курс валют'!$A:$D, 4, 0), "") -> 502.5
A80: 46072 | B80: ООО "ADAMANT SAVDO PLYUS" | C80: 01 354 HMA | D80: M150 | E80: 9 | F80: =IF(D80="М400", E80*740000, IF(D80="M150", E80*600000, IF(D80="M300", E80*670000, IF(D80="M350", E80*700000, 0)))) -> 5400000 | G80: =IF(A80<>"", F80/ VLOOKUP(A80, '[1]Курс валют'!$A:$D, 4, 0), "") -> 450
A81: 46072 | B81: ООО "ADAMANT SAVDO PLYUS" | C81: 01 M021794 | D81: M150 | E81: 9 | F81: =IF(D81="М400", E81*740000, IF(D81="M150", E81*600000, IF(D81="M300", E81*670000, IF(D81="M350", E81*700000, 0)))) -> 5400000 | G81: =IF(A81<>"", F81/ VLOOKUP(A81, '[1]Курс валют'!$A:$D, 4, 0), "") -> 450
A82: 46072 | B82: ООО "ADAMANT SAVDO PLYUS" | C82: 01 906 VKA | D82: M150 | E82: 10 | F82: =IF(D82="М400", E82*740000, IF(D82="M150", E82*600000, IF(D82="M300", E82*670000, IF(D82="M350", E82*700000, 0)))) -> 6000000 | G82: =IF(A82<>"", F82/ VLOOKUP(A82, '[1]Курс валют'!$A:$D, 4, 0), "") -> 500
A83: 46072 | B83: ООО "ADAMANT SAVDO PLYUS" | C83: 01 162 HLA | D83: M150 | E83: 12 | F83: =IF(D83="М400", E83*740000, IF(D83="M150", E83*600000, IF(D83="M300", E83*670000, IF(D83="M350", E83*700000, 0)))) -> 7200000 | G83: =IF(A83<>"", F83/ VLOOKUP(A83, '[1]Курс валют'!$A:$D, 4, 0), "") -> 600
A84: 46072 | B84: ООО "ADAMANT SAVDO PLYUS" | C84: 01 512 TLA | D84: M150 | E84: 9 | F84: =IF(D84="М400", E84*740000, IF(D84="M150", E84*600000, IF(D84="M300", E84*670000, IF(D84="M350", E84*700000, 0)))) -> 5400000 | G84: =IF(A84<>"", F84/ VLOOKUP(A84, '[1]Курс валют'!$A:$D, 4, 0), "") -> 450
A85: 46072 | B85: ООО "ADAMANT SAVDO PLYUS" | C85: 01 125 QKA | D85: M150 | E85: 9 | F85: =IF(D85="М400", E85*740000, IF(D85="M150", E85*600000, IF(D85="M300", E85*670000, IF(D85="M350", E85*700000, 0)))) -> 5400000 | G85: =IF(A85<>"", F85/ VLOOKUP(A85, '[1]Курс валют'!$A:$D, 4, 0), "") -> 450
A86: 46072 | B86: ООО "ADAMANT SAVDO PLYUS" | C86: 01 276 PLA | D86: M300 | E86: 10 | F86: =IF(D86="М400", E86*740000, IF(D86="M150", E86*600000, IF(D86="M300", E86*670000, IF(D86="M350", E86*700000, 0)))) -> 6700000 | G86: =IF(A86<>"", F86/ VLOOKUP(A86, '[1]Курс валют'!$A:$D, 4, 0), "") -> 558.33333
A87: 46072 | B87: ООО "ADAMANT SAVDO PLYUS" | C87: 01 539 LKA | D87: M300 | E87: 6 | F87: =IF(D87="М400", E87*740000, IF(D87="M150", E87*600000, IF(D87="M300", E87*670000, IF(D87="M350", E87*700000, 0)))) -> 4020000 | G87: =IF(A87<>"", F87/ VLOOKUP(A87, '[1]Курс валют'!$A:$D, 4, 0), "") -> 335
A88: 46072 | B88: ООО "ADAMANT SAVDO PLYUS" | C88: 01 354 HMA | D88: M300 | E88: 9 | F88: =IF(D88="М400", E88*740000, IF(D88="M150", E88*600000, IF(D88="M300", E88*670000, IF(D88="M350", E88*700000, 0)))) -> 6030000 | G88: =IF(A88<>"", F88/ VLOOKUP(A88, '[1]Курс валют'!$A:$D, 4, 0), "") -> 502.5
A89: 46072 | B89: ООО "ADAMANT SAVDO PLYUS" | C89: 01 650 WLA | D89: M300 | E89: 9 | F89: =IF(D89="М400", E89*740000, IF(D89="M150", E89*600000, IF(D89="M300", E89*670000, IF(D89="M350", E89*700000, 0)))) -> 6030000 | G89: =IF(A89<>"", F89/ VLOOKUP(A89, '[1]Курс валют'!$A:$D, 4, 0), "") -> 502.5
A90: 46072 | B90: ООО "ADAMANT SAVDO PLYUS" | C90: 01 125 QKA | D90: M300 | E90: 9 | F90: =IF(D90="М400", E90*740000, IF(D90="M150", E90*600000, IF(D90="M300", E90*670000, IF(D90="M350", E90*700000, 0)))) -> 6030000 | G90: =IF(A90<>"", F90/ VLOOKUP(A90, '[1]Курс валют'!$A:$D, 4, 0), "") -> 502.5
... A128: 46072 | B128: ООО "ADAMANT SAVDO PLYUS" | C128: 01 965 OHA | D128: M300 | E128: 12 | F128: =IF(D128="М400", E128*740000, IF(D128="M150", E128*600000, IF(D128="M300", E128*670000, IF(D128="M350", E128*700000, 0)))) -> 8040000 | G128: =IF(A128<>"", F128/ VLOOKUP(A128, '[1]Курс валют'!$A:$D, 4, 0), "") -> 670
A129: 19.02.2026 Итог | E129: =SUBTOTAL(9,E79:E128) -> 483 | F129: =SUBTOTAL(9,F79:F128) -> 319550000
A130: 46075 | B130: ООО "ADAMANT SAVDO PLYUS" | C130: 01 169 HLA | D130: M300 | E130: 9 | F130: =IF(D130="М400", E130*740000, IF(D130="M150", E130*600000, IF(D130="M300", E130*670000, IF(D130="M350", E130*700000, 0)))) -> 6030000 | G130: =IF(A130<>"", F130/ VLOOKUP(A130, '[1]Курс валют'!$A:$D, 4, 0), "") -> 502.5
A131: 46075 | B131: ООО "ADAMANT SAVDO PLYUS" | C131: 01 M021796 | D131: M300 | E131: 10 | F131: =IF(D131="М400", E131*740000, IF(D131="M150", E131*600000, IF(D131="M300", E131*670000, IF(D131="M350", E131*700000, 0)))) -> 6700000 | G131: =IF(A131<>"", F131/ VLOOKUP(A131, '[1]Курс валют'!$A:$D, 4, 0), "") -> 558.33333
A132: 46075 | B132: ООО "ADAMANT SAVDO PLYUS" | C132: 01 163 HLA | D132: M300 | E132: 9 | F132: =IF(D132="М400", E132*740000, IF(D132="M150", E132*600000, IF(D132="M300", E132*670000, IF(D132="M350", E132*700000, 0)))) -> 6030000 | G132: =IF(A132<>"", F132/ VLOOKUP(A132, '[1]Курс валют'!$A:$D, 4, 0), "") -> 502.5
A133: 46075 | B133: ООО "ADAMANT SAVDO PLYUS" | C133: 01 125 QKA | D133: M300 | E133: 9 | F133: =IF(D133="М400", E133*740000, IF(D133="M150", E133*600000, IF(D133="M300", E133*670000, IF(D133="M350", E133*700000, 0)))) -> 6030000 | G133: =IF(A133<>"", F133/ VLOOKUP(A133, '[1]Курс валют'!$A:$D, 4, 0), "") -> 502.5
A134: 46075 | B134: ООО "ADAMANT SAVDO PLYUS" | C134: 01 910 VKA | D134: M300 | E134: 10 | F134: =IF(D134="М400", E134*740000, IF(D134="M150", E134*600000, IF(D134="M300", E134*670000, IF(D134="M350", E134*700000, 0)))) -> 6700000 | G134: =IF(A134<>"", F134/ VLOOKUP(A134, '[1]Курс валют'!$A:$D, 4, 0), "") -> 558.33333
A135: 46075 | B135: ООО "ADAMANT SAVDO PLYUS" | C135: 01 162 HLA | D135: M300 | E135: 12 | F135: =IF(D135="М400", E135*740000, IF(D135="M150", E135*600000, IF(D135="M300", E135*670000, IF(D135="M350", E135*700000, 0)))) -> 8040000 | G135: =IF(A135<>"", F135/ VLOOKUP(A135, '[1]Курс валют'!$A:$D, 4, 0), "") -> 670
A136: 46075 | B136: ООО "ADAMANT SAVDO PLYUS" | C136: 01 652 WLA | D136: M300 | E136: 9 | F136: =IF(D136="М400", E136*740000, IF(D136="M150", E136*600000, IF(D136="M300", E136*670000, IF(D136="M350", E136*700000, 0)))) -> 6030000 | G136: =IF(A136<>"", F136/ VLOOKUP(A136, '[1]Курс валют'!$A:$D, 4, 0), "") -> 502.5
A137: 46075 | B137: ООО "ADAMANT SAVDO PLYUS" | C137: 01 726 FJA | D137: M300 | E137: 12 | F137: =IF(D137="М400", E137*740000, IF(D137="M150", E137*600000, IF(D137="M300", E137*670000, IF(D137="M350", E137*700000, 0)))) -> 8040000 | G137: =IF(A137<>"", F137/ VLOOKUP(A137, '[1]Курс валют'!$A:$D, 4, 0), "") -> 670
A138: 46075 | B138: ООО "ADAMANT SAVDO PLYUS" | C138: 01 481 BFA | D138: M300 | E138: 10 | F138: =IF(D138="М400", E138*740000, IF(D138="M150", E138*600000, IF(D138="M300", E138*670000, IF(D138="M350", E138*700000, 0)))) -> 6700000 | G138: =IF(A138<>"", F138/ VLOOKUP(A138, '[1]Курс валют'!$A:$D, 4, 0), "") -> 558.33333
A139: 46075 | B139: ООО "ADAMANT SAVDO PLYUS" | C139: 01 W 227 TB | D139: M300 | E139: 9 | F139: =IF(D139="М400", E139*740000, IF(D139="M150", E139*600000, IF(D139="M300", E139*670000, IF(D139="M350", E139*700000, 0)))) -> 6030000 | G139: =IF(A139<>"", F139/ VLOOKUP(A139, '[1]Курс валют'!$A:$D, 4, 0), "") -> 502.5
A140: 46075 | B140: ООО "ADAMANT SAVDO PLYUS" | C140: 01 650 WLA | D140: M300 | E140: 9 | F140: =IF(D140="М400", E140*740000, IF(D140="M150", E140*600000, IF(D140="M300", E140*670000, IF(D140="M350", E140*700000, 0)))) -> 6030000 | G140: =IF(A140<>"", F140/ VLOOKUP(A140, '[1]Курс валют'!$A:$D, 4, 0), "") -> 502.5
A141: 46075 | B141: ООО "ADAMANT SAVDO PLYUS" | C141: 01 512 TLA | D141: M300 | E141: 9 | F141: =IF(D141="М400", E141*740000, IF(D141="M150", E141*600000, IF(D141="M300", E141*670000, IF(D141="M350", E141*700000, 0)))) -> 6030000 | G141: =IF(A141<>"", F141/ VLOOKUP(A141, '[1]Курс валют'!$A:$D, 4, 0), "") -> 502.5
... A173: 46075 | B173: ООО "ADAMANT SAVDO PLYUS" | C173: 01 652 WLA | D173: M300 | E173: 9 | F173: =IF(D173="М400", E173*740000, IF(D173="M150", E173*600000, IF(D173="M300", E173*670000, IF(D173="M350", E173*700000, 0)))) -> 6030000 | G173: =IF(A173<>"", F173/ VLOOKUP(A173, '[1]Курс валют'!$A:$D, 4, 0), "") -> 502.5
A174: 22.02.2026 Итог | E174: =SUBTOTAL(9,E130:E173) -> 435 | F174: =SUBTOTAL(9,F130:F173) -> 291450000
A175: 46078 | B175: ООО "ADAMANT SAVDO PLYUS" | C175: 01 273 PLA | D175: M300 | E175: 10 | F175: =IF(D175="М400", E175*740000, IF(D175="M150", E175*600000, IF(D175="M300", E175*670000, IF(D175="M350", E175*700000, 0)))) -> 6700000 | G175: =IF(A175<>"", F175/ VLOOKUP(A175, '[1]Курс валют'!$A:$D, 4, 0), "") -> 554.63576
A176: 46078 | B176: ООО "ADAMANT SAVDO PLYUS" | C176: 01 569 HGA | D176: M300 | E176: 12 | F176: =IF(D176="М400", E176*740000, IF(D176="M150", E176*600000, IF(D176="M300", E176*670000, IF(D176="M350", E176*700000, 0)))) -> 8040000 | G176: =IF(A176<>"", F176/ VLOOKUP(A176, '[1]Курс валют'!$A:$D, 4, 0), "") -> 665.56291
A177: 46078 | B177: ООО "ADAMANT SAVDO PLYUS" | C177: 01 651 WLA | D177: M300 | E177: 9 | F177: =IF(D177="М400", E177*740000, IF(D177="M150", E177*600000, IF(D177="M300", E177*670000, IF(D177="M350", E177*700000, 0)))) -> 6030000 | G177: =IF(A177<>"", F177/ VLOOKUP(A177, '[1]Курс валют'!$A:$D, 4, 0), "") -> 499.17219
A178: 46078 | B178: ООО "ADAMANT SAVDO PLYUS" | C178: 01 726 FJA | D178: M300 | E178: 12 | F178: =IF(D178="М400", E178*740000, IF(D178="M150", E178*600000, IF(D178="M300", E178*670000, IF(D178="M350", E178*700000, 0)))) -> 8040000 | G178: =IF(A178<>"", F178/ VLOOKUP(A178, '[1]Курс валют'!$A:$D, 4, 0), "") -> 665.56291
A179: 46078 | B179: ООО "ADAMANT SAVDO PLYUS" | C179: 01 965 OHA | D179: M300 | E179: 12 | F179: =IF(D179="М400", E179*740000, IF(D179="M150", E179*600000, IF(D179="M300", E179*670000, IF(D179="M350", E179*700000, 0)))) -> 8040000 | G179: =IF(A179<>"", F179/ VLOOKUP(A179, '[1]Курс валют'!$A:$D, 4, 0), "") -> 665.56291
A180: 46078 | B180: ООО "ADAMANT SAVDO PLYUS" | C180: 01 728 FJA | D180: M300 | E180: 12 | F180: =IF(D180="М400", E180*740000, IF(D180="M150", E180*600000, IF(D180="M300", E180*670000, IF(D180="M350", E180*700000, 0)))) -> 8040000 | G180: =IF(A180<>"", F180/ VLOOKUP(A180, '[1]Курс валют'!$A:$D, 4, 0), "") -> 665.56291
A181: 46078 | B181: ООО "ADAMANT SAVDO PLYUS" | C181: 01 168 HLA | D181: M300 | E181: 12 | F181: =IF(D181="М400", E181*740000, IF(D181="M150", E181*600000, IF(D181="M300", E181*670000, IF(D181="M350", E181*700000, 0)))) -> 8040000 | G181: =IF(A181<>"", F181/ VLOOKUP(A181, '[1]Курс валют'!$A:$D, 4, 0), "") -> 665.56291
A182: 46078 | B182: ООО "ADAMANT SAVDO PLYUS" | C182: 01 731 FJA | D182: M300 | E182: 12 | F182: =IF(D182="М400", E182*740000, IF(D182="M150", E182*600000, IF(D182="M300", E182*670000, IF(D182="M350", E182*700000, 0)))) -> 8040000 | G182: =IF(A182<>"", F182/ VLOOKUP(A182, '[1]Курс валют'!$A:$D, 4, 0), "") -> 665.56291
A183: 46078 | B183: ООО "ADAMANT SAVDO PLYUS" | C183: 01 906 VKA | D183: M300 | E183: 10 | F183: =IF(D183="М400", E183*740000, IF(D183="M150", E183*600000, IF(D183="M300", E183*670000, IF(D183="M350", E183*700000, 0)))) -> 6700000 | G183: =IF(A183<>"", F183/ VLOOKUP(A183, '[1]Курс валют'!$A:$D, 4, 0), "") -> 554.63576
A184: 46078 | B184: ООО "ADAMANT SAVDO PLYUS" | C184: 01 481 BFA | D184: M300 | E184: 9 | F184: =IF(D184="М400", E184*740000, IF(D184="M150", E184*600000, IF(D184="M300", E184*670000, IF(D184="M350", E184*700000, 0)))) -> 6030000 | G184: =IF(A184<>"", F184/ VLOOKUP(A184, '[1]Курс валют'!$A:$D, 4, 0), "") -> 499.17219
A185: 46078 | B185: ООО "ADAMANT SAVDO PLYUS" | C185: 01 162 HLA | D185: M300 | E185: 12 | F185: =IF(D185="М400", E185*740000, IF(D185="M150", E185*600000, IF(D185="M300", E185*670000, IF(D185="M350", E185*700000, 0)))) -> 8040000 | G185: =IF(A185<>"", F185/ VLOOKUP(A185, '[1]Курс валют'!$A:$D, 4, 0), "") -> 665.56291
A186: 46078 | B186: ООО "ADAMANT SAVDO PLYUS" | C186: 01 650 WLA | D186: M300 | E186: 9 | F186: =IF(D186="М400", E186*740000, IF(D186="M150", E186*600000, IF(D186="M300", E186*670000, IF(D186="M350", E186*700000, 0)))) -> 6030000 | G186: =IF(A186<>"", F186/ VLOOKUP(A186, '[1]Курс валют'!$A:$D, 4, 0), "") -> 499.17219
... A236: 46078 | B236: ООО "ADAMANT SAVDO PLYUS" | C236: 01 650 WLA | D236: M300 | E236: 9 | F236: =IF(D236="М400", E236*740000, IF(D236="M150", E236*600000, IF(D236="M300", E236*670000, IF(D236="M350", E236*700000, 0)))) -> 6030000 | G236: =IF(A236<>"", F236/ VLOOKUP(A236, '[1]Курс валют'!$A:$D, 4, 0), "") -> 499.17219
A237: 25.02.2026 Итог | E237: =SUBTOTAL(9,E175:E236) -> 630 | F237: =SUBTOTAL(9,F175:F236) -> 422100000
A238: 46081 | B238: ООО "ADAMANT SAVDO PLYUS" | C238: 01 590 BDA | D238: M300 | E238: 5 | F238: =IF(D238="М400", E238*740000, IF(D238="M150", E238*600000, IF(D238="M300", E238*670000, IF(D238="M350", E238*700000, 0)))) -> 3350000 | G238: =IF(A238<>"", F238/ VLOOKUP(A238, '[1]Курс валют'!$A:$D, 4, 0), "") -> 277.31788
A239: 46081 | B239: ООО "ADAMANT SAVDO PLYUS" | C239: 01 906 VKA | D239: M300 | E239: 10 | F239: =IF(D239="М400", E239*740000, IF(D239="M150", E239*600000, IF(D239="M300", E239*670000, IF(D239="M350", E239*700000, 0)))) -> 6700000 | G239: =IF(A239<>"", F239/ VLOOKUP(A239, '[1]Курс валют'!$A:$D, 4, 0), "") -> 554.63576
A240: 46081 | B240: ООО "ADAMANT SAVDO PLYUS" | C240: 01 569 HGA | D240: M300 | E240: 12 | F240: =IF(D240="М400", E240*740000, IF(D240="M150", E240*600000, IF(D240="M300", E240*670000, IF(D240="M350", E240*700000, 0)))) -> 8040000 | G240: =IF(A240<>"", F240/ VLOOKUP(A240, '[1]Курс валют'!$A:$D, 4, 0), "") -> 665.56291
A241: 46081 | B241: ООО "ADAMANT SAVDO PLYUS" | C241: 01 M 021797 | D241: M300 | E241: 9 | F241: =IF(D241="М400", E241*740000, IF(D241="M150", E241*600000, IF(D241="M300", E241*670000, IF(D241="M350", E241*700000, 0)))) -> 6030000 | G241: =IF(A241<>"", F241/ VLOOKUP(A241, '[1]Курс валют'!$A:$D, 4, 0), "") -> 499.17219
A242: 46081 | B242: ООО "ADAMANT SAVDO PLYUS" | C242: 01 276 PLA | D242: M300 | E242: 10 | F242: =IF(D242="М400", E242*740000, IF(D242="M150", E242*600000, IF(D242="M300", E242*670000, IF(D242="M350", E242*700000, 0)))) -> 6700000 | G242: =IF(A242<>"", F242/ VLOOKUP(A242, '[1]Курс валют'!$A:$D, 4, 0), "") -> 554.63576
A243: 46081 | B243: ООО "ADAMANT SAVDO PLYUS" | C243: 01 481 BFA | D243: M300 | E243: 10 | F243: =IF(D243="М400", E243*740000, IF(D243="M150", E243*600000, IF(D243="M300", E243*670000, IF(D243="M350", E243*700000, 0)))) -> 6700000 | G243: =IF(A243<>"", F243/ VLOOKUP(A243, '[1]Курс валют'!$A:$D, 4, 0), "") -> 554.63576
A244: 46081 | B244: ООО "ADAMANT SAVDO PLYUS" | C244: 01 M 021794 | D244: M300 | E244: 10 | F244: =IF(D244="М400", E244*740000, IF(D244="M150", E244*600000, IF(D244="M300", E244*670000, IF(D244="M350", E244*700000, 0)))) -> 6700000 | G244: =IF(A244<>"", F244/ VLOOKUP(A244, '[1]Курс валют'!$A:$D, 4, 0), "") -> 554.63576
A245: 46081 | B245: ООО "ADAMANT SAVDO PLYUS" | C245: 01 540 LKA | D245: M300 | E245: 9 | F245: =IF(D245="М400", E245*740000, IF(D245="M150", E245*600000, IF(D245="M300", E245*670000, IF(D245="M350", E245*700000, 0)))) -> 6030000 | G245: =IF(A245<>"", F245/ VLOOKUP(A245, '[1]Курс валют'!$A:$D, 4, 0), "") -> 499.17219
A246: 46081 | B246: ООО "ADAMANT SAVDO PLYUS" | C246: 01 M 021793 | D246: M300 | E246: 10 | F246: =IF(D246="М400", E246*740000, IF(D246="M150", E246*600000, IF(D246="M300", E246*670000, IF(D246="M350", E246*700000, 0)))) -> 6700000 | G246: =IF(A246<>"", F246/ VLOOKUP(A246, '[1]Курс валют'!$A:$D, 4, 0), "") -> 554.63576
A247: 46081 | B247: ООО "ADAMANT SAVDO PLYUS" | C247: 01 796 FJA | D247: M300 | E247: 12 | F247: =IF(D247="М400", E247*740000, IF(D247="M150", E247*600000, IF(D247="M300", E247*670000, IF(D247="M350", E247*700000, 0)))) -> 8040000 | G247: =IF(A247<>"", F247/ VLOOKUP(A247, '[1]Курс валют'!$A:$D, 4, 0), "") -> 665.56291
A248: 46081 | B248: ООО "ADAMANT SAVDO PLYUS" | C248: 40 783 YBA | D248: M300 | E248: 10 | F248: =IF(D248="М400", E248*740000, IF(D248="M150", E248*600000, IF(D248="M300", E248*670000, IF(D248="M350", E248*700000, 0)))) -> 6700000 | G248: =IF(A248<>"", F248/ VLOOKUP(A248, '[1]Курс валют'!$A:$D, 4, 0), "") -> 554.63576
A249: 46081 | B249: ООО "ADAMANT SAVDO PLYUS" | C249: 01 972 CJA | D249: M300 | E249: 10 | F249: =IF(D249="М400", E249*740000, IF(D249="M150", E249*600000, IF(D249="M300", E249*670000, IF(D249="M350", E249*700000, 0)))) -> 6700000 | G249: =IF(A249<>"", F249/ VLOOKUP(A249, '[1]Курс валют'!$A:$D, 4, 0), "") -> 554.63576
... A302: 46081 | B302: ООО "ADAMANT SAVDO PLYUS" | C302: 01 568 HGA | D302: M300 | E302: 10 | F302: =IF(D302="М400", E302*740000, IF(D302="M150", E302*600000, IF(D302="M300", E302*670000, IF(D302="M350", E302*700000, 0)))) -> 6700000 | G302: =IF(A302<>"", F302/ VLOOKUP(A302, '[1]Курс валют'!$A:$D, 4, 0), "") -> 554.63576
A303: 28.02.2026 Итог | E303: =SUBTOTAL(9,E238:E302) -> 636 | F303: =SUBTOTAL(9,F238:F302) -> 426120000
...

Sheet Строй.Мат
A1: Дата | B1: № | C1: Наименование товара | D1: Поставщик | E1: Покупатель | F1: Заказчик | G1: Ед.изм | H1: Кол-во | I1: Цена | J1: Цена $ | K1: Цена с НДС | L1: Цена с НДС $ | M1: Стоимость | N1: Стоимость | O1: Доставка | P1: По доллару
A2: 45962 | B2: 1 | C2: Бадья | D2: - | E2: Улканбаев Равшан | F2: МЕВА ШАРБАТ ИЛМИЙ ЭКСПЕРИМЕНТАЛ ВИНОЧИЛИК | G2: шт | H2: 1 | I2: 4700000 | J2: =IF(AND(ISNUMBER(I2),A2<>""), I2/VLOOKUP(A2,'[1]Курс валют'!$A:$D,4,0), "") -> 388.42975 | K2: - | L2: =IF(AND(ISNUMBER(K2),A2<>""), K2/VLOOKUP(A2,'[1]Курс валют'!$A:$D,4,0), "") | M2: =I2*H2 -> 4700000 | O2: 1750000 | P2: =IF(A2<>"", (M2+O2) / VLOOKUP(A2, 'Курс валют'!$A:$D, 4, 0), "")+N2 -> 533.05785
A3: 01.11.2025 Итог | J3: =IF(AND(ISNUMBER(I3),A3<>""), I3/VLOOKUP(A3,'[1]Курс валют'!$A:$D,4,0), "") | L3: =IF(AND(ISNUMBER(K3),A3<>""), K3/VLOOKUP(A3,'[1]Курс валют'!$A:$D,4,0), "") | M3: =SUBTOTAL(9,M2:M2) -> 4700000 | P3: =IF(A3<>"", (M3+O3) / VLOOKUP(A3, 'Курс валют'!$A:$D, 4, 0), "")+N3 -> #N/A
A4: 45963 | B4: 2 | C4: Фиксатор | D4: - | E4: Улканбаев Равшан | F4: МЕВА ШАРБАТ ИЛМИЙ ЭКСПЕРИМЕНТАЛ ВИНОЧИЛИК | G4: шт | H4: 5500 | I4: =2400000/[1]Строй.Мат!$H4 -> 436.36364 | J4: =IF(AND(ISNUMBER(I4),A4<>""), I4/VLOOKUP(A4,'[1]Курс валют'!$A:$D,4,0), "") -> 0.036454773 | K4: - | L4: =IF(AND(ISNUMBER(K4),A4<>""), K4/VLOOKUP(A4,'[1]Курс валют'!$A:$D,4,0), "") | M4: =I4*H4 -> 2400000 | P4: =IF(A4<>"", (M4+O4) / VLOOKUP(A4, 'Курс валют'!$A:$D, 4, 0), "")+N4 -> 200.50125
A5: 02.11.2025 Итог | J5: =IF(AND(ISNUMBER(I5),A5<>""), I5/VLOOKUP(A5,'[1]Курс валют'!$A:$D,4,0), "") | L5: =IF(AND(ISNUMBER(K5),A5<>""), K5/VLOOKUP(A5,'[1]Курс валют'!$A:$D,4,0), "") | M5: =SUBTOTAL(9,M4:M4) -> 2400000 | P5: =IF(A5<>"", (M5+O5) / VLOOKUP(A5, 'Курс валют'!$A:$D, 4, 0), "")+N5 -> #N/A
A6: 45964 | B6: 1 | C6: Тахта 6х0,05х0,1 | D6: - | E6: Шерзод Ака | F6: МЕВА ШАРБАТ ИЛМИЙ ЭКСПЕРИМЕНТАЛ ВИНОЧИЛИК | G6: м3 | H6: 8.005 | J6: 305 | L6: =J6*H6 -> 2441.525 | N6: =L6 -> 2441.525 | P6: =IF(A6<>"", (M6+O6) / VLOOKUP(A6, 'Курс валют'!$A:$D, 4, 0), "")+N6 -> 2441.525
A7: 03.11.2025 Итог | J7: =IF(AND(ISNUMBER(I7),A7<>""), I7/VLOOKUP(A7,'[1]Курс валют'!$A:$D,4,0), "") | L7: =IF(AND(ISNUMBER(K7),A7<>""), K7/VLOOKUP(A7,'[1]Курс валют'!$A:$D,4,0), "") | M7: =SUBTOTAL(9,M6:M6) -> 0 | P7: =IF(A7<>"", (M7+O7) / VLOOKUP(A7, 'Курс валют'!$A:$D, 4, 0), "")+N7 -> #N/A
A8: 46063 | B8: 1 | C8: Опалубка 330х120 | D8: ОМАД ДУНЕСИ | E8: Шерзод Ака | F8: МЕВА ШАРБАТ ИЛМИЙ ЭКСПЕРИМЕНТАЛ ВИНОЧИЛИК | G8: шт | H8: 47 | I8: - | J8: =IF(AND(ISNUMBER(I8),A8<>""), I8/VLOOKUP(A8,'[1]Курс валют'!$A:$D,4,0), "") | K8: - | L8: =IF(AND(ISNUMBER(K8),A8<>""), K8/VLOOKUP(A8,'[1]Курс валют'!$A:$D,4,0), "") | M8: 0 | O8: =7700000 -> 7700000 | P8: =IF(A8<>"", (M8+O8) / VLOOKUP(A8, 'Курс валют'!$A:$D, 4, 0), "")+N8 -> 631.14754
A9: 46063 | B9: 2 | C9: Опалубка 330х90 | D9: ОМАД ДУНЕСИ | E9: Шерзод Ака | F9: МЕВА ШАРБАТ ИЛМИЙ ЭКСПЕРИМЕНТАЛ ВИНОЧИЛИК | G9: шт | H9: 8 | I9: - | J9: =IF(AND(ISNUMBER(I9),A9<>""), I9/VLOOKUP(A9,'[1]Курс валют'!$A:$D,4,0), "") | K9: - | L9: =IF(AND(ISNUMBER(K9),A9<>""), K9/VLOOKUP(A9,'[1]Курс валют'!$A:$D,4,0), "") | M9: 0 | P9: =IF(A9<>"", (M9+O9) / VLOOKUP(A9, 'Курс валют'!$A:$D, 4, 0), "")+N9 -> 0
A10: 46063 | B10: 3 | C10: Опалубка 330х80 | D10: ОМАД ДУНЕСИ | E10: Шерзод Ака | F10: МЕВА ШАРБАТ ИЛМИЙ ЭКСПЕРИМЕНТАЛ ВИНОЧИЛИК | G10: шт | H10: 8 | I10: - | J10: =IF(AND(ISNUMBER(I10),A10<>""), I10/VLOOKUP(A10,'[1]Курс валют'!$A:$D,4,0), "") | K10: - | L10: =IF(AND(ISNUMBER(K10),A10<>""), K10/VLOOKUP(A10,'[1]Курс валют'!$A:$D,4,0), "") | M10: 0 | P10: =IF(A10<>"", (M10+O10) / VLOOKUP(A10, 'Курс валют'!$A:$D, 4, 0), "")+N10 -> 0
A11: 46063 | B11: 4 | C11: Опалубка 330х72 | D11: ОМАД ДУНЕСИ | E11: Шерзод Ака | F11: МЕВА ШАРБАТ ИЛМИЙ ЭКСПЕРИМЕНТАЛ ВИНОЧИЛИК | G11: шт | H11: 6 | I11: - | J11: =IF(AND(ISNUMBER(I11),A11<>""), I11/VLOOKUP(A11,'[1]Курс валют'!$A:$D,4,0), "") | K11: - | L11: =IF(AND(ISNUMBER(K11),A11<>""), K11/VLOOKUP(A11,'[1]Курс валют'!$A:$D,4,0), "") | M11: 0 | P11: =IF(A11<>"", (M11+O11) / VLOOKUP(A11, 'Курс валют'!$A:$D, 4, 0), "")+N11 -> 0
A12: 46063 | B12: 5 | C12: Опалубка 330х60 | D12: ОМАД ДУНЕСИ | E12: Шерзод Ака | F12: МЕВА ШАРБАТ ИЛМИЙ ЭКСПЕРИМЕНТАЛ ВИНОЧИЛИК | G12: шт | H12: 7 | I12: - | J12: =IF(AND(ISNUMBER(I12),A12<>""), I12/VLOOKUP(A12,'[1]Курс валют'!$A:$D,4,0), "") | K12: - | L12: =IF(AND(ISNUMBER(K12),A12<>""), K12/VLOOKUP(A12,'[1]Курс валют'!$A:$D,4,0), "") | M12: 0 | P12: =IF(A12<>"", (M12+O12) / VLOOKUP(A12, 'Курс валют'!$A:$D, 4, 0), "")+N12 -> 0
A13: 46063 | B13: 6 | C13: Опалубка 330х50 | D13: ОМАД ДУНЕСИ | E13: Шерзод Ака | F13: МЕВА ШАРБАТ ИЛМИЙ ЭКСПЕРИМЕНТАЛ ВИНОЧИЛИК | G13: шт | H13: 2 | I13: - | J13: =IF(AND(ISNUMBER(I13),A13<>""), I13/VLOOKUP(A13,'[1]Курс валют'!$A:$D,4,0), "") | K13: - | L13: =IF(AND(ISNUMBER(K13),A13<>""), K13/VLOOKUP(A13,'[1]Курс валют'!$A:$D,4,0), "") | M13: 0 | P13: =IF(A13<>"", (M13+O13) / VLOOKUP(A13, 'Курс валют'!$A:$D, 4, 0), "")+N13 -> 0
A14: 46063 | B14: 7 | C14: Узел 30х30 | D14: ОМАД ДУНЕСИ | E14: Шерзод Ака | F14: МЕВА ШАРБАТ ИЛМИЙ ЭКСПЕРИМЕНТАЛ ВИНОЧИЛИК | G14: шт | H14: 4 | I14: - | J14: =IF(AND(ISNUMBER(I14),A14<>""), I14/VLOOKUP(A14,'[1]Курс валют'!$A:$D,4,0), "") | K14: - | L14: =IF(AND(ISNUMBER(K14),A14<>""), K14/VLOOKUP(A14,'[1]Курс валют'!$A:$D,4,0), "") | M14: 0 | P14: =IF(A14<>"", (M14+O14) / VLOOKUP(A14, 'Курс валют'!$A:$D, 4, 0), "")+N14 -> 0
A15: 46063 | B15: 8 | C15: Захват сарик | D15: ОМАД ДУНЕСИ | E15: Шерзод Ака | F15: МЕВА ШАРБАТ ИЛМИЙ ЭКСПЕРИМЕНТАЛ ВИНОЧИЛИК | G15: шт | H15: 2 | I15: - | J15: =IF(AND(ISNUMBER(I15),A15<>""), I15/VLOOKUP(A15,'[1]Курс валют'!$A:$D,4,0), "") | K15: - | L15: =IF(AND(ISNUMBER(K15),A15<>""), K15/VLOOKUP(A15,'[1]Курс валют'!$A:$D,4,0), "") | M15: 0 | P15: =IF(A15<>"", (M15+O15) / VLOOKUP(A15, 'Курс валют'!$A:$D, 4, 0), "")+N15 -> 0
A16: 46063 | B16: 9 | C16: Стойка кора 2м | D16: ОМАД ДУНЕСИ | E16: Шерзод Ака | F16: МЕВА ШАРБАТ ИЛМИЙ ЭКСПЕРИМЕНТАЛ ВИНОЧИЛИК | G16: шт | H16: 150 | I16: - | J16: =IF(AND(ISNUMBER(I16),A16<>""), I16/VLOOKUP(A16,'[1]Курс валют'!$A:$D,4,0), "") | K16: - | L16: =IF(AND(ISNUMBER(K16),A16<>""), K16/VLOOKUP(A16,'[1]Курс валют'!$A:$D,4,0), "") | M16: 0 | P16: =IF(A16<>"", (M16+O16) / VLOOKUP(A16, 'Курс валют'!$A:$D, 4, 0), "")+N16 -> 0
A17: 46063 | B17: 10 | C17: Замок клин | D17: ОМАД ДУНЕСИ | E17: Шерзод Ака | F17: МЕВА ШАРБАТ ИЛМИЙ ЭКСПЕРИМЕНТАЛ ВИНОЧИЛИК | G17: шт | H17: 126 | I17: - | J17: =IF(AND(ISNUMBER(I17),A17<>""), I17/VLOOKUP(A17,'[1]Курс валют'!$A:$D,4,0), "") | K17: - | L17: =IF(AND(ISNUMBER(K17),A17<>""), K17/VLOOKUP(A17,'[1]Курс валют'!$A:$D,4,0), "") | M17: 0 | P17: =IF(A17<>"", (M17+O17) / VLOOKUP(A17, 'Курс валют'!$A:$D, 4, 0), "")+N17 -> 0
A18: 46063 | B18: 11 | C18: Замок универсал | D18: ОМАД ДУНЕСИ | E18: Шерзод Ака | F18: МЕВА ШАРБАТ ИЛМИЙ ЭКСПЕРИМЕНТАЛ ВИНОЧИЛИК | G18: шт | H18: 140 | I18: - | J18: =IF(AND(ISNUMBER(I18),A18<>""), I18/VLOOKUP(A18,'[1]Курс валют'!$A:$D,4,0), "") | K18: - | L18: =IF(AND(ISNUMBER(K18),A18<>""), K18/VLOOKUP(A18,'[1]Курс валют'!$A:$D,4,0), "") | M18: 0 | P18: =IF(A18<>"", (M18+O18) / VLOOKUP(A18, 'Курс валют'!$A:$D, 4, 0), "")+N18 -> 0
A19: 46063 | B19: 12 | C19: Пятка | D19: ОМАД ДУНЕСИ | E19: Шерзод Ака | F19: МЕВА ШАРБАТ ИЛМИЙ ЭКСПЕРИМЕНТАЛ ВИНОЧИЛИК | G19: шт | H19: 20 | I19: - | J19: =IF(AND(ISNUMBER(I19),A19<>""), I19/VLOOKUP(A19,'[1]Курс валют'!$A:$D,4,0), "") | K19: - | L19: =IF(AND(ISNUMBER(K19),A19<>""), K19/VLOOKUP(A19,'[1]Курс валют'!$A:$D,4,0), "") | M19: 0 | P19: =IF(A19<>"", (M19+O19) / VLOOKUP(A19, 'Курс валют'!$A:$D, 4, 0), "")+N19 -> 0
A20: 46063 | B20: 13 | C20: Адаптер | D20: ОМАД ДУНЕСИ | E20: Шерзод Ака | F20: МЕВА ШАРБАТ ИЛМИЙ ЭКСПЕРИМЕНТАЛ ВИНОЧИЛИК | G20: шт | H20: 40 | I20: - | J20: =IF(AND(ISNUMBER(I20),A20<>""), I20/VLOOKUP(A20,'[1]Курс валют'!$A:$D,4,0), "") | K20: - | L20: =IF(AND(ISNUMBER(K20),A20<>""), K20/VLOOKUP(A20,'[1]Курс валют'!$A:$D,4,0), "") | M20: 0 | P20: =IF(A20<>"", (M20+O20) / VLOOKUP(A20, 'Курс валют'!$A:$D, 4, 0), "")+N20 -> 0
... A24: 46063 | B24: 17 | C24: Колобок | D24: ОМАД ДУНЕСИ | E24: Шерзод Ака | F24: МЕВА ШАРБАТ ИЛМИЙ ЭКСПЕРИМЕНТАЛ ВИНОЧИЛИК | G24: шт | H24: 160 | I24: - | J24: =IF(AND(ISNUMBER(I24),A24<>""), I24/VLOOKUP(A24,'[1]Курс валют'!$A:$D,4,0), "") | K24: - | L24: =IF(AND(ISNUMBER(K24),A24<>""), K24/VLOOKUP(A24,'[1]Курс валют'!$A:$D,4,0), "") | M24: 0 | P24: =IF(A24<>"", (M24+O24) / VLOOKUP(A24, 'Курс валют'!$A:$D, 4, 0), "")+N24 -> 0
A25: 10.02.2026 Итог | J25: =IF(AND(ISNUMBER(I25),A25<>""), I25/VLOOKUP(A25,'[1]Курс валют'!$A:$D,4,0), "") | L25: =IF(AND(ISNUMBER(K25),A25<>""), K25/VLOOKUP(A25,'[1]Курс валют'!$A:$D,4,0), "") | M25: =SUBTOTAL(9,M8:M24) -> 0 | P25: =IF(A25<>"", (M25+O25) / VLOOKUP(A25, 'Курс валют'!$A:$D, 4, 0), "")+N25 -> #N/A
A26: 46081 | B26: 1 | C26: Леса | D26: ОРА ПРОГРЕС БИЗНЕС | E26: Диер Ака | F26: МЕВА ШАРБАТ ИЛМИЙ ЭКСПЕРИМЕНТАЛ ВИНОЧИЛИК | G26: шт | H26: 18 | I26: - | J26: =IF(AND(ISNUMBER(I26),A26<>""), I26/VLOOKUP(A26,'[1]Курс валют'!$A:$D,4,0), "") | K26: - | L26: =IF(AND(ISNUMBER(K26),A26<>""), K26/VLOOKUP(A26,'[1]Курс валют'!$A:$D,4,0), "") | M26: 0 | P26: =IF(A26<>"", (M26+O26) / VLOOKUP(A26, 'Курс валют'!$A:$D, 4, 0), "")+N26 -> 0
A27: 46081 | B27: 2 | C27: Тахта | D27: ОРА ПРОГРЕС БИЗНЕС | E27: Диер Ака | F27: МЕВА ШАРБАТ ИЛМИЙ ЭКСПЕРИМЕНТАЛ ВИНОЧИЛИК | G27: шт | H27: 10 | I27: - | J27: =IF(AND(ISNUMBER(I27),A27<>""), I27/VLOOKUP(A27,'[1]Курс валют'!$A:$D,4,0), "") | K27: - | L27: =IF(AND(ISNUMBER(K27),A27<>""), K27/VLOOKUP(A27,'[1]Курс валют'!$A:$D,4,0), "") | M27: 0 | P27: =IF(A27<>"", (M27+O27) / VLOOKUP(A27, 'Курс валют'!$A:$D, 4, 0), "")+N27 -> 0
A28: 28.02.2026 Итог | J28: =IF(AND(ISNUMBER(I28),A28<>""), I28/VLOOKUP(A28,'[1]Курс валют'!$A:$D,4,0), "") | L28: =IF(AND(ISNUMBER(K28),A28<>""), K28/VLOOKUP(A28,'[1]Курс валют'!$A:$D,4,0), "") | M28: =SUBTOTAL(9,M26:M27) -> 0 | P28: =IF(A28<>"", (M28+O28) / VLOOKUP(A28, 'Курс валют'!$A:$D, 4, 0), "")+N28 -> #N/A
A29: 46082 | B29: 1 | C29: Колонна 300х90 | D29: ОМАД ДУНЕСИ | E29: Шерзод Ака | F29: МЕВА ШАРБАТ ИЛМИЙ ЭКСПЕРИМЕНТАЛ ВИНОЧИЛИК | G29: шт | H29: 48 | I29: - | J29: =IF(AND(ISNUMBER(I29),A29<>""), I29/VLOOKUP(A29,'[1]Курс валют'!$A:$D,4,0), "") | K29: - | L29: =IF(AND(ISNUMBER(K29),A29<>""), K29/VLOOKUP(A29,'[1]Курс валют'!$A:$D,4,0), "") | M29: 0 | P29: =IF(A29<>"", (M29+O29) / VLOOKUP(A29, 'Курс валют'!$A:$D, 4, 0), "")+N29 -> 0
A30: 46082 | B30: 2 | C30: Распорка 300/212 | D30: ОМАД ДУНЕСИ | E30: Шерзод Ака | F30: МЕВА ШАРБАТ ИЛМИЙ ЭКСПЕРИМЕНТАЛ ВИНОЧИЛИК | G30: шт | H30: 20 | I30: - | J30: =IF(AND(ISNUMBER(I30),A30<>""), I30/VLOOKUP(A30,'[1]Курс валют'!$A:$D,4,0), "") | K30: - | L30: =IF(AND(ISNUMBER(K30),A30<>""), K30/VLOOKUP(A30,'[1]Курс валют'!$A:$D,4,0), "") | M30: 0 | P30: =IF(A30<>"", (M30+O30) / VLOOKUP(A30, 'Курс валют'!$A:$D, 4, 0), "")+N30 -> 0
A31: 46082 | B31: 3 | C31: Распорка 185/117 | D31: ОМАД ДУНЕСИ | E31: Шерзод Ака | F31: МЕВА ШАРБАТ ИЛМИЙ ЭКСПЕРИМЕНТАЛ ВИНОЧИЛИК | G31: шт | H31: 20 | I31: - | J31: =IF(AND(ISNUMBER(I31),A31<>""), I31/VLOOKUP(A31,'[1]Курс валют'!$A:$D,4,0), "") | K31: - | L31: =IF(AND(ISNUMBER(K31),A31<>""), K31/VLOOKUP(A31,'[1]Курс валют'!$A:$D,4,0), "") | M31: 0 | P31: =IF(A31<>"", (M31+O31) / VLOOKUP(A31, 'Курс валют'!$A:$D, 4, 0), "")+N31 -> 0
A32: 46082 | B32: 4 | C32: Колонна 300х120 | D32: ОМАД ДУНЕСИ | E32: Шерзод Ака | F32: МЕВА ШАРБАТ ИЛМИЙ ЭКСПЕРИМЕНТАЛ ВИНОЧИЛИК | G32: шт | H32: 48 | I32: - | J32: =IF(AND(ISNUMBER(I32),A32<>""), I32/VLOOKUP(A32,'[1]Курс валют'!$A:$D,4,0), "") | K32: - | L32: =IF(AND(ISNUMBER(K32),A32<>""), K32/VLOOKUP(A32,'[1]Курс валют'!$A:$D,4,0), "") | M32: 0 | P32: =IF(A32<>"", (M32+O32) / VLOOKUP(A32, 'Курс валют'!$A:$D, 4, 0), "")+N32 -> 0
A33: 46082 | B33: 5 | C33: Замок универсал | D33: ОМАД ДУНЕСИ | E33: Шерзод Ака | F33: МЕВА ШАРБАТ ИЛМИЙ ЭКСПЕРИМЕНТАЛ ВИНОЧИЛИК | G33: шт | H33: 202 | I33: - | J33: =IF(AND(ISNUMBER(I33),A33<>""), I33/VLOOKUP(A33,'[1]Курс валют'!$A:$D,4,0), "") | K33: - | L33: =IF(AND(ISNUMBER(K33),A33<>""), K33/VLOOKUP(A33,'[1]Курс валют'!$A:$D,4,0), "") | M33: 0 | P33: =IF(A33<>"", (M33+O33) / VLOOKUP(A33, 'Курс валют'!$A:$D, 4, 0), "")+N33 -> 0
A34: 46082 | B34: 6 | C34: Угол 300х30 | D34: ОМАД ДУНЕСИ | E34: Шерзод Ака | F34: МЕВА ШАРБАТ ИЛМИЙ ЭКСПЕРИМЕНТАЛ ВИНОЧИЛИК | G34: шт | H34: 20 | I34: - | J34: =IF(AND(ISNUMBER(I34),A34<>""), I34/VLOOKUP(A34,'[1]Курс валют'!$A:$D,4,0), "") | K34: - | L34: =IF(AND(ISNUMBER(K34),A34<>""), K34/VLOOKUP(A34,'[1]Курс валют'!$A:$D,4,0), "") | M34: 0 | P34: =IF(A34<>"", (M34+O34) / VLOOKUP(A34, 'Курс валют'!$A:$D, 4, 0), "")+N34 -> 0
A35: 46082 | B35: 7 | C35: Внут угол 300х50х30 | D35: ОМАД ДУНЕСИ | E35: Шерзод Ака | F35: МЕВА ШАРБАТ ИЛМИЙ ЭКСПЕРИМЕНТАЛ ВИНОЧИЛИК | G35: шт | H35: 2 | I35: - | J35: =IF(AND(ISNUMBER(I35),A35<>""), I35/VLOOKUP(A35,'[1]Курс валют'!$A:$D,4,0), "") | K35: - | L35: =IF(AND(ISNUMBER(K35),A35<>""), K35/VLOOKUP(A35,'[1]Курс валют'!$A:$D,4,0), "") | M35: 0 | P35: =IF(A35<>"", (M35+O35) / VLOOKUP(A35, 'Курс валют'!$A:$D, 4, 0), "")+N35 -> 0
A36: 46082 | B36: 8 | C36: Болт для колон | D36: ОМАД ДУНЕСИ | E36: Шерзод Ака | F36: МЕВА ШАРБАТ ИЛМИЙ ЭКСПЕРИМЕНТАЛ ВИНОЧИЛИК | G36: шт | H36: 150 | I36: - | J36: =IF(AND(ISNUMBER(I36),A36<>""), I36/VLOOKUP(A36,'[1]Курс валют'!$A:$D,4,0), "") | K36: - | L36: =IF(AND(ISNUMBER(K36),A36<>""), K36/VLOOKUP(A36,'[1]Курс валют'!$A:$D,4,0), "") | M36: 0 | P36: =IF(A36<>"", (M36+O36) / VLOOKUP(A36, 'Курс валют'!$A:$D, 4, 0), "")+N36 -> 0
A37: 46082 | B37: 9 | C37: Пятка | D37: ОМАД ДУНЕСИ | E37: Шерзод Ака | F37: МЕВА ШАРБАТ ИЛМИЙ ЭКСПЕРИМЕНТАЛ ВИНОЧИЛИК | G37: шт | H37: 20 | I37: - | J37: =IF(AND(ISNUMBER(I37),A37<>""), I37/VLOOKUP(A37,'[1]Курс валют'!$A:$D,4,0), "") | K37: - | L37: =IF(AND(ISNUMBER(K37),A37<>""), K37/VLOOKUP(A37,'[1]Курс валют'!$A:$D,4,0), "") | M37: 0 | P37: =IF(A37<>"", (M37+O37) / VLOOKUP(A37, 'Курс валют'!$A:$D, 4, 0), "")+N37 -> 0
A38: 46082 | B38: 10 | C38: Адаптер подкоса | D38: ОМАД ДУНЕСИ | E38: Шерзод Ака | F38: МЕВА ШАРБАТ ИЛМИЙ ЭКСПЕРИМЕНТАЛ ВИНОЧИЛИК | G38: шт | H38: 40 | I38: - | J38: =IF(AND(ISNUMBER(I38),A38<>""), I38/VLOOKUP(A38,'[1]Курс валют'!$A:$D,4,0), "") | K38: - | L38: =IF(AND(ISNUMBER(K38),A38<>""), K38/VLOOKUP(A38,'[1]Курс валют'!$A:$D,4,0), "") | M38: 0 | P38: =IF(A38<>"", (M38+O38) / VLOOKUP(A38, 'Курс валют'!$A:$D, 4, 0), "")+N38 -> 0
A39: 46082 | B39: 11 | C39: Колон 300х120 | D39: ОМАД ДУНЕСИ | E39: Шерзод Ака | F39: МЕВА ШАРБАТ ИЛМИЙ ЭКСПЕРИМЕНТАЛ ВИНОЧИЛИК | G39: шт | H39: 32 | I39: - | J39: =IF(AND(ISNUMBER(I39),A39<>""), I39/VLOOKUP(A39,'[1]Курс валют'!$A:$D,4,0), "") | K39: - | L39: =IF(AND(ISNUMBER(K39),A39<>""), K39/VLOOKUP(A39,'[1]Курс валют'!$A:$D,4,0), "") | M39: 0 | P39: =IF(A39<>"", (M39+O39) / VLOOKUP(A39, 'Курс валют'!$A:$D, 4, 0), "")+N39 -> 0
A40: 46082 | B40: 12 | C40: Колон 300х60 | D40: ОМАД ДУНЕСИ | E40: Шерзод Ака | F40: МЕВА ШАРБАТ ИЛМИЙ ЭКСПЕРИМЕНТАЛ ВИНОЧИЛИК | G40: шт | H40: 50 | I40: - | J40: =IF(AND(ISNUMBER(I40),A40<>""), I40/VLOOKUP(A40,'[1]Курс валют'!$A:$D,4,0), "") | K40: - | L40: =IF(AND(ISNUMBER(K40),A40<>""), K40/VLOOKUP(A40,'[1]Курс валют'!$A:$D,4,0), "") | M40: 0 | P40: =IF(A40<>"", (M40+O40) / VLOOKUP(A40, 'Курс валют'!$A:$D, 4, 0), "")+N40 -> 0
... A43: 46082 | B43: 15 | C43: Тайрот | D43: ОМАД ДУНЕСИ | E43: Шерзод Ака | F43: МЕВА ШАРБАТ ИЛМИЙ ЭКСПЕРИМЕНТАЛ ВИНОЧИЛИК | G43: шт | H43: 300 | I43: - | J43: =IF(AND(ISNUMBER(I43),A43<>""), I43/VLOOKUP(A43,'[1]Курс валют'!$A:$D,4,0), "") | K43: - | L43: =IF(AND(ISNUMBER(K43),A43<>""), K43/VLOOKUP(A43,'[1]Курс валют'!$A:$D,4,0), "") | M43: 0 | P43: =IF(A43<>"", (M43+O43) / VLOOKUP(A43, 'Курс валют'!$A:$D, 4, 0), "")+N43 -> 0
A44: 01.03.2026 Итог | J44: =IF(AND(ISNUMBER(I44),A44<>""), I44/VLOOKUP(A44,'[1]Курс валют'!$A:$D,4,0), "") | L44: =IF(AND(ISNUMBER(K44),A44<>""), K44/VLOOKUP(A44,'[1]Курс валют'!$A:$D,4,0), "") | M44: =SUBTOTAL(9,M29:M43) -> 0 | P44: =IF(A44<>"", (M44+O44) / VLOOKUP(A44, 'Курс валют'!$A:$D, 4, 0), "")+N44 -> #N/A
A45: 46091 | B45: 1 | C45: Балка 3,3м | D45: АЗИЯ ФОРМВОРК | E45: Улканбаев Равшан | F45: МЕВА ШАРБАТ ИЛМИЙ ЭКСПЕРИМЕНТАЛ ВИНОЧИЛИК | G45: шт | H45: 14 | I45: 96500 | K45: 96500 | M45: =[1]Строй.Мат!$I45*[1]Строй.Мат!$H45*3.3 -> 4458300 | O45: 1100000 | P45: =IF(A45<>"", (M45+O45) / VLOOKUP(A45, 'Курс валют'!$A:$D, 4, 0), "")+N45 -> 463.19167
A46: 46091 | B46: 2 | C46: Балка 3,6м | D46: АЗИЯ ФОРМВОРК | E46: Улканбаев Равшан | F46: МЕВА ШАРБАТ ИЛМИЙ ЭКСПЕРИМЕНТАЛ ВИНОЧИЛИК | G46: шт | H46: 200 | I46: 96500 | K46: 96500 | M46: =[1]Строй.Мат!$I46*[1]Строй.Мат!$H46*3.6 -> 69480000 | P46: =IF(A46<>"", (M46+O46) / VLOOKUP(A46, 'Курс валют'!$A:$D, 4, 0), "")+N46 -> 5790
A47: 46091 | B47: 3 | C47: Балка 3,9м | D47: АЗИЯ ФОРМВОРК | E47: Улканбаев Равшан | F47: МЕВА ШАРБАТ ИЛМИЙ ЭКСПЕРИМЕНТАЛ ВИНОЧИЛИК | G47: шт | H47: 158 | I47: 96500 | K47: 96500 | M47: =[1]Строй.Мат!$I47*[1]Строй.Мат!$H47*3.9 -> 59463300 | P47: =IF(A47<>"", (M47+O47) / VLOOKUP(A47, 'Курс валют'!$A:$D, 4, 0), "")+N47 -> 4955.275
A48: 10.03.2026 Итог | M48: =SUBTOTAL(9,M45:M47) -> 133401600 | P48: =IF(A48<>"", (M48+O48) / VLOOKUP(A48, 'Курс валют'!$A:$D, 4, 0), "")+N48 -> #N/A
A49: 46092 | B49: 1 | C49: Балка 1,5м | D49: АЛВООД ФОРМВОРК | E49: Улканбаев Равшан | F49: МЕВА ШАРБАТ ИЛМИЙ ЭКСПЕРИМЕНТАЛ ВИНОЧИЛИК | G49: шт | H49: 142 | I49: 142500 | K49: - | M49: =[1]Строй.Мат!$I49*[1]Строй.Мат!$H49 -> 20235000 | O49: 1300000 | P49: =IF(A49<>"", (M49+O49) / VLOOKUP(A49, 'Курс валют'!$A:$D, 4, 0), "")+N49 -> 1779.7521
A50: 46092 | B50: 2 | C50: Балка 2,45 | D50: АЛВООД ФОРМВОРК | E50: Улканбаев Равшан | F50: МЕВА ШАРБАТ ИЛМИЙ ЭКСПЕРИМЕНТАЛ ВИНОЧИЛИК | G50: шт | H50: 50 | I50: 232750 | K50: - | M50: =[1]Строй.Мат!$I50*[1]Строй.Мат!$H50 -> 11637500 | P50: =IF(A50<>"", (M50+O50) / VLOOKUP(A50, 'Курс валют'!$A:$D, 4, 0), "")+N50 -> 961.77686
A51: 46092 | B51: 3 | C51: Балка 2м | D51: АЛВООД ФОРМВОРК | E51: Улканбаев Равшан | F51: МЕВА ШАРБАТ ИЛМИЙ ЭКСПЕРИМЕНТАЛ ВИНОЧИЛИК | G51: шт | H51: 50 | I51: 190000 | K51: - | M51: =[1]Строй.Мат!$I51*[1]Строй.Мат!$H51 -> 9500000 | P51: =IF(A51<>"", (M51+O51) / VLOOKUP(A51, 'Курс валют'!$A:$D, 4, 0), "")+N51 -> 785.12397
A52: 46092 | B52: 4 | C52: Балка 3,3м | D52: АЛВООД ФОРМВОРК | E52: Улканбаев Равшан | F52: МЕВА ШАРБАТ ИЛМИЙ ЭКСПЕРИМЕНТАЛ ВИНОЧИЛИК | G52: шт | H52: 90 | I52: 313500 | K52: - | M52: =[1]Строй.Мат!$I52*[1]Строй.Мат!$H52 -> 28215000 | P52: =IF(A52<>"", (M52+O52) / VLOOKUP(A52, 'Курс валют'!$A:$D, 4, 0), "")+N52 -> 2331.8182
A53: 46092 | B53: 5 | C53: Фанера | D53: АЛВООД ФОРМВОРК | E53: Улканбаев Равшан | F53: МЕВА ШАРБАТ ИЛМИЙ ЭКСПЕРИМЕНТАЛ ВИНОЧИЛИК | G53: шт | H53: 200 | I53: 465000 | K53: - | M53: =[1]Строй.Мат!$I53*[1]Строй.Мат!$H53 -> 93000000 | P53: =IF(A53<>"", (M53+O53) / VLOOKUP(A53, 'Курс валют'!$A:$D, 4, 0), "")+N53 -> 7685.9504
A54: 46092 | B54: 6 | C54: Балка | D54: ОМАД ДУНЕСИ | E54: Шерзод Ака | F54: МЕВА ШАРБАТ ИЛМИЙ ЭКСПЕРИМЕНТАЛ ВИНОЧИЛИК | G54: шт | H54: 215 | I54: - | K54: - | M54: 0 | P54: =IF(A54<>"", (M54+O54) / VLOOKUP(A54, 'Курс валют'!$A:$D, 4, 0), "")+N54 -> 0
A55: 46092 | B55: 7 | C55: Фанера | D55: ОМАД ДУНЕСИ | E55: Шерзод Ака | F55: МЕВА ШАРБАТ ИЛМИЙ ЭКСПЕРИМЕНТАЛ ВИНОЧИЛИК | G55: шт | H55: 152 | I55: - | K55: - | M55: 0 | P55: =IF(A55<>"", (M55+O55) / VLOOKUP(A55, 'Курс валют'!$A:$D, 4, 0), "")+N55 -> 0
A56: 46092 | B56: 8 | C56: Замок универсал | D56: ОМАД ДУНЕСИ | E56: Шерзод Ака | F56: МЕВА ШАРБАТ ИЛМИЙ ЭКСПЕРИМЕНТАЛ ВИНОЧИЛИК | G56: шт | H56: 60 | I56: - | K56: - | M56: 0 | P56: =IF(A56<>"", (M56+O56) / VLOOKUP(A56, 'Курс валют'!$A:$D, 4, 0), "")+N56 -> 0
A57: 46092 | B57: 9 | C57: Пятка | D57: ОМАД ДУНЕСИ | E57: Шерзод Ака | F57: МЕВА ШАРБАТ ИЛМИЙ ЭКСПЕРИМЕНТАЛ ВИНОЧИЛИК | G57: шт | H57: 492 | I57: - | K57: - | M57: 0 | P57: =IF(A57<>"", (M57+O57) / VLOOKUP(A57, 'Курс валют'!$A:$D, 4, 0), "")+N57 -> 0
A58: 11.03.2026 Итог | M58: =SUBTOTAL(9,M49:M57) -> 162587500 | P58: =IF(A58<>"", (M58+O58) / VLOOKUP(A58, 'Курс валют'!$A:$D, 4, 0), "")+N58 -> #N/A
A59: 46095 | B59: 1 | C59: Тахта 6х0,05х0,1 | D59: - | E59: Шерзод Ака | F59: МЕВА ШАРБАТ ИЛМИЙ ЭКСПЕРИМЕНТАЛ ВИНОЧИЛИК | G59: м3 | H59: =6*0.05*0.1*347 -> 10.41 | I59: - | K59: - | M59: 0 | P59: =IF(A59<>"", (M59+O59) / VLOOKUP(A59, 'Курс валют'!$A:$D, 4, 0), "")+N59 -> 0
A60: 14.03.2026 Итог | M60: =SUBTOTAL(9,M59:M59) -> 0 | P60: =IF(A60<>"", (M60+O60) / VLOOKUP(A60, 'Курс валют'!$A:$D, 4, 0), "")+N60 -> #N/A
A61: 46097 | B61: 1 | C61: Консолы строительные | D61: - | F61: МЕВА ШАРБАТ ИЛМИЙ ЭКСПЕРИМЕНТАЛ ВИНОЧИЛИК | G61: шт | H61: 500 | I61: - | K61: - | M61: 0 | P61: =IF(A61<>"", (M61+O61) / VLOOKUP(A61, 'Курс валют'!$A:$D, 4, 0), "")+N61 -> 0
A62: 16.03.2026 Итог | M62: =SUBTOTAL(9,M61:M61) -> 0 | P62: =IF(A62<>"", (M62+O62) / VLOOKUP(A62, 'Курс валют'!$A:$D, 4, 0), "")+N62 -> #N/A
A63: 46099 | B63: 1 | C63: Балка 1,45 (германские) | D63: ПЕРИ-ФС | E63: Улканбаев Равшан | F63: МЕВА ШАРБАТ ИЛМИЙ ЭКСПЕРИМЕНТАЛ ВИНОЧИЛИК | G63: шт | H63: 100 | I63: - | K63: - | M63: 0 | O63: 700000 | P63: =IF(A63<>"", (M63+O63) / VLOOKUP(A63, 'Курс валют'!$A:$D, 4, 0), "")+N63 -> 57.613169
A64: 46099 | B64: 2 | C64: Болт стяжной 1м | D64: АЗИЯ ФОРМВОРК | E64: Улканбаев Равшан | F64: МЕВА ШАРБАТ ИЛМИЙ ЭКСПЕРИМЕНТАЛ ВИНОЧИЛИК | G64: шт | H64: 100 | I64: 30000 | K64: - | M64: =[1]Строй.Мат!$I64*[1]Строй.Мат!$H64 -> 3000000 | O64: 500000 | P64: =IF(A64<>"", (M64+O64) / VLOOKUP(A64, 'Курс валют'!$A:$D, 4, 0), "")+N64 -> 288.06584
A65: 46099 | B65: 3 | C65: Болт стяжной 1,5м | D65: АЗИЯ ФОРМВОРК | E65: Улканбаев Равшан | F65: МЕВА ШАРБАТ ИЛМИЙ ЭКСПЕРИМЕНТАЛ ВИНОЧИЛИК | G65: шт | H65: 10 | I65: 45000 | K65: - | M65: =[1]Строй.Мат!$I65*[1]Строй.Мат!$H65 -> 450000 | P65: =IF(A65<>"", (M65+O65) / VLOOKUP(A65, 'Курс валют'!$A:$D, 4, 0), "")+N65 -> 37.037037
A66: 46099 | B66: 4 | C66: Гайка стяжная 100мм | D66: АЗИЯ ФОРМВОРК | E66: Улканбаев Равшан | F66: МЕВА ШАРБАТ ИЛМИЙ ЭКСПЕРИМЕНТАЛ ВИНОЧИЛИК | G66: шт | H66: 370 | I66: 19000 | K66: - | M66: =[1]Строй.Мат!$I66*[1]Строй.Мат!$H66 -> 7030000 | P66: =IF(A66<>"", (M66+O66) / VLOOKUP(A66, 'Курс валют'!$A:$D, 4, 0), "")+N66 -> 578.60082
A67: 18.03.2026 Итог | M67: =SUBTOTAL(9,M63:M66) -> 10480000 | P67: =IF(A67<>"", (M67+O67) / VLOOKUP(A67, 'Курс валют'!$A:$D, 4, 0), "")+N67 -> #N/A
A68: 46100 | B68: 1 | C68: Балка 1,5м | D68: АЛВООД ФОРМВОРК | E68: Улканбаев Равшан | F68: МЕВА ШАРБАТ ИЛМИЙ ЭКСПЕРИМЕНТАЛ ВИНОЧИЛИК | G68: шт | H68: 100 | I68: 142500 | K68: - | M68: =[1]Строй.Мат!$I68*[1]Строй.Мат!$H68 -> 14250000 | O68: 1300000 | P68: =IF(A68<>"", (M68+O68) / VLOOKUP(A68, 'Курс валют'!$A:$D, 4, 0), "")+N68 -> 1279.8354
A69: 46100 | B69: 2 | C69: Балка 3,0м | D69: АЛВООД ФОРМВОРК | E69: Улканбаев Равшан | F69: МЕВА ШАРБАТ ИЛМИЙ ЭКСПЕРИМЕНТАЛ ВИНОЧИЛИК | G69: шт | H69: 175 | I69: 285000 | K69: - | M69: =[1]Строй.Мат!$I69*[1]Строй.Мат!$H69 -> 49875000 | P69: =IF(A69<>"", (M69+O69) / VLOOKUP(A69, 'Курс валют'!$A:$D, 4, 0), "")+N69 -> 4104.9383
A70: 46100 | B70: 3 | C70: Балка двутавровая 3,3м | D70: АЛВООД ФОРМВОРК | E70: Улканбаев Равшан | F70: МЕВА ШАРБАТ ИЛМИЙ ЭКСПЕРИМЕНТАЛ ВИНОЧИЛИК | G70: шт | H70: 275 | I70: 313500 | K70: - | M70: =[1]Строй.Мат!$I70*[1]Строй.Мат!$H70 -> 86212500 | P70: =IF(A70<>"", (M70+O70) / VLOOKUP(A70, 'Курс валют'!$A:$D, 4, 0), "")+N70 -> 7095.679
A71: 46100 | B71: 4 | C71: Балка двутавровая 3,6м | D71: АЛВООД ФОРМВОРК | E71: Улканбаев Равшан | F71: МЕВА ШАРБАТ ИЛМИЙ ЭКСПЕРИМЕНТАЛ ВИНОЧИЛИК | G71: шт | H71: 200 | I71: 342000 | K71: - | M71: =[1]Строй.Мат!$I71*[1]Строй.Мат!$H71 -> 68400000 | P71: =IF(A71<>"", (M71+O71) / VLOOKUP(A71, 'Курс валют'!$A:$D, 4, 0), "")+N71 -> 5629.6296
A72: 46100 | B72: 5 | C72: Балка двутавровая 3,9м | D72: АЛВООД ФОРМВОРК | E72: Улканбаев Равшан | F72: МЕВА ШАРБАТ ИЛМИЙ ЭКСПЕРИМЕНТАЛ ВИНОЧИЛИК | G72: шт | H72: 50 | I72: 370500 | K72: - | M72: =[1]Строй.Мат!$I72*[1]Строй.Мат!$H72 -> 18525000 | P72: =IF(A72<>"", (M72+O72) / VLOOKUP(A72, 'Курс валют'!$A:$D, 4, 0), "")+N72 -> 1524.6914
A73: 46100 | B73: 6 | C73: Фанера | D73: АЛВООД ФОРМВОРК | E73: Улканбаев Равшан | F73: МЕВА ШАРБАТ ИЛМИЙ ЭКСПЕРИМЕНТАЛ ВИНОЧИЛИК | G73: шт | H73: 280 | I73: 475000 | K73: - | M73: =[1]Строй.Мат!$I73*[1]Строй.Мат!$H73 -> 133000000 | P73: =IF(A73<>"", (M73+O73) / VLOOKUP(A73, 'Курс валют'!$A:$D, 4, 0), "")+N73 -> 10946.502
A74: 19.03.2026 Итог | M74: =SUBTOTAL(9,M68:M73) -> 370262500 | P74: =IF(A74<>"", (M74+O74) / VLOOKUP(A74, 'Курс валют'!$A:$D, 4, 0), "")+N74 -> #N/A
A75: 46113 | B75: 1 | C75: Тахта 6х0,05х0,1 | D75: - | E75: Шерзод Ака | F75: МЕВА ШАРБАТ ИЛМИЙ ЭКСПЕРИМЕНТАЛ ВИНОЧИЛИК | G75: м3 | H75: =6*0.05*0.1*278 -> 8.34 | I75: - | J75: 310 | K75: - | L75: =J75*H75 -> 2585.4 | M75: 0 | N75: =L75 -> 2585.4 | P75: =IF(A75<>"", (M75+O75) / VLOOKUP(A75, 'Курс валют'!$A:$D, 4, 0), "")+N75 -> 2585.4
A76: 01.04.2026 Итог | M76: =SUBTOTAL(9,M75:M75) -> 0 | P76: =IF(A76<>"", (M76+O76) / VLOOKUP(A76, 'Курс валют'!$A:$D, 4, 0), "")+N76 -> #N/A
A77: 46114 | B77: 1 | C77: Фанера | D77: АЛВООД ФОРМВОРК | E77: Улканбаев Равшан | F77: МЕВА ШАРБАТ ИЛМИЙ ЭКСПЕРИМЕНТАЛ ВИНОЧИЛИК | G77: шт | H77: 370 | I77: 475000 | M77: =[1]Строй.Мат!$I77*[1]Строй.Мат!$H77 -> 175750000 | O77: 1300000 | P77: =IF(A77<>"", (M77+O77) / VLOOKUP(A77, 'Курс валют'!$A:$D, 4, 0), "")+N77 -> 14632.231
A78: 02.04.2026 Итог | M78: =SUBTOTAL(9,M77:M77) -> 175750000 | P78: =IF(A78<>"", (M78+O78) / VLOOKUP(A78, 'Курс валют'!$A:$D, 4, 0), "")+N78 -> #N/A
A79: 46116 | B79: 1 | C79: Фанера | D79: АЛВООД ФОРМВОРК | E79: Улканбаев Равшан | F79: МЕВА ШАРБАТ ИЛМИЙ ЭКСПЕРИМЕНТАЛ ВИНОЧИЛИК | G79: шт | H79: 505 | I79: 475000 | M79: =[1]Строй.Мат!$I79*[1]Строй.Мат!$H79 -> 239875000 | O79: 1500000 | P79: =IF(A79<>"", (M79+O79) / VLOOKUP(A79, 'Курс валют'!$A:$D, 4, 0), "")+N79 -> 20114.583
A80: 46116 | B80: 2 | C80: Стойка Д-500 | D80: ПЕРИ-ФС | E80: Улканбаев Равшан | F80: МЕВА ШАРБАТ ИЛМИЙ ЭКСПЕРИМЕНТАЛ ВИНОЧИЛИК | G80: шт | H80: 96 | I80: - | K80: - | M80: 0 | O80: 700000 | P80: =IF(A80<>"", (M80+O80) / VLOOKUP(A80, 'Курс валют'!$A:$D, 4, 0), "")+N80 -> 58.333333
A81: 46116 | B81: 3 | C81: Кассета 80х120 | D81: ПЕРИ-ФС | E81: Улканбаев Равшан | F81: МЕВА ШАРБАТ ИЛМИЙ ЭКСПЕРИМЕНТАЛ ВИНОЧИЛИК | G81: шт | H81: 3 | I81: - | K81: - | M81: 0 | P81: =IF(A81<>"", (M81+O81) / VLOOKUP(A81, 'Курс валют'!$A:$D, 4, 0), "")+N81 -> 0
A82: 04.04.2026 Итог | M82: =SUBTOTAL(9,M79:M81) -> 239875000 | P82: =IF(A82<>"", (M82+O82) / VLOOKUP(A82, 'Курс валют'!$A:$D, 4, 0), "")+N82 -> #N/A
A83: 46122 | B83: 1 | C83: Стойка 20-500 | D83: ПЕРИ-ФС | E83: Улканбаев Равшан | F83: МЕВА ШАРБАТ ИЛМИЙ ЭКСПЕРИМЕНТАЛ ВИНОЧИЛИК | G83: шт | H83: 34 | I83: - | K83: - | M83: 0 | O83: 600000 | P83: =IF(A83<>"", (M83+O83) / VLOOKUP(A83, 'Курс валют'!$A:$D, 4, 0), "")+N83 -> 49.180328
A84: 46122 | B84: 2 | C84: Кассета 80х150 | D84: ПЕРИ-ФС | E84: Улканбаев Равшан | F84: МЕВА ШАРБАТ ИЛМИЙ ЭКСПЕРИМЕНТАЛ ВИНОЧИЛИК | G84: шт | H84: 1 | I84: - | K84: - | M84: 0 | P84: =IF(A84<>"", (M84+O84) / VLOOKUP(A84, 'Курс валют'!$A:$D, 4, 0), "")+N84 -> 0
A85: 10.04.2026 Итог | M85: =SUBTOTAL(9,M83:M84) -> 0 | P85: =IF(A85<>"", (M85+O85) / VLOOKUP(A85, 'Курс валют'!$A:$D, 4, 0), "")+N85 -> #N/A
A86: 10.04.2026 Итог | P86: =IF(A86<>"", (M86+O86) / VLOOKUP(A86, 'Курс валют'!$A:$D, 4, 0), "")+N86 -> #N/A
A87: 10.04.2026 Итог Итог | M87: =SUBTOTAL(9,M86:M86) -> 0 | P87: =IF(A87<>"", (M87+O87) / VLOOKUP(A87, 'Курс валют'!$A:$D, 4, 0), "")+N87 -> #N/A
A88: 46128 | C88: Стойка | D88: Частный | E88: Улканбаев Равшан | G88: шт | H88: 300 | I88: 1500 | K88: 46 | M88: 21400000 | P88: =IF(A88<>"", (M88+O88) / VLOOKUP(A88, 'Курс валют'!$A:$D, 4, 0), "")+N88 -> 1761.3169
A89: 16.04.2026 Итог | M89: =SUBTOTAL(9,M88:M88) -> 21400000 | P89: =IF(A89<>"", (M89+O89) / VLOOKUP(A89, 'Курс валют'!$A:$D, 4, 0), "")+N89 -> #N/A
A90: 46129 | B90: 1 | C90: Щиты стеновой опалубки | D90: ПЕРИ-ФС | E90: Улканбаев Равшан | F90: МЕВА ШАРБАТ ИЛМИЙ ЭКСПЕРИМЕНТАЛ ВИНОЧИЛИК | G90: шт | H90: 32 | I90: 8388000 | M90: =I90*H90 -> 268416000 | O90: 1800000 | P90: =IF(A90<>"", (M90+O90) / VLOOKUP(A90, 'Курс валют'!$A:$D, 4, 0), "")+N90 -> 22148.852
A91: 46129 | B91: 2 | C91: Угловые щиты | D91: ПЕРИ-ФС | E91: Улканбаев Равшан | F91: МЕВА ШАРБАТ ИЛМИЙ ЭКСПЕРИМЕНТАЛ ВИНОЧИЛИК | G91: шт | H91: 10 | I91: 4734000 | K91: - | M91: =I91*H91 -> 47340000 | P91: =IF(A91<>"", (M91+O91) / VLOOKUP(A91, 'Курс валют'!$A:$D, 4, 0), "")+N91 -> 3880.3279
A92: 17.04.2026 Итог | M92: =SUBTOTAL(9,M90:M91) -> 315756000 | P92: =IF(A92<>"", (M92+O92) / VLOOKUP(A92, 'Курс валют'!$A:$D, 4, 0), "")+N92 -> #N/A
A93: 46132 | B93: 1 | C93: Балка | D93: ПЕРИ-ФС | E93: Улканбаев Равшан | F93: МЕВА ШАРБАТ ИЛМИЙ ЭКСПЕРИМЕНТАЛ ВИНОЧИЛИК | G93: шт | H93: 100 | I93: 155150 | M93: =I93*H93 -> 15515000 | O93: 700000 | P93: =IF(A93<>"", (M93+O93) / VLOOKUP(A93, 'Курс валют'!$A:$D, 4, 0), "")+N93 -> 1346.7608
A94: 46132 | B94: 2 | C94: Болт для колон | D94: ПЕРИ-ФС | E94: Улканбаев Равшан | F94: МЕВА ШАРБАТ ИЛМИЙ ЭКСПЕРИМЕНТАЛ ВИНОЧИЛИК | G94: шт | H94: 128 | I94: 180000 | K94: - | M94: =I94*H94 -> 23040000 | P94: =IF(A94<>"", (M94+O94) / VLOOKUP(A94, 'Курс валют'!$A:$D, 4, 0), "")+N94 -> 1913.6213
A95: 20.04.2026 Итог | M95: =SUBTOTAL(9,M93:M94) -> 38555000 | P95: =IF(A95<>"", (M95+O95) / VLOOKUP(A95, 'Курс валют'!$A:$D, 4, 0), "")+N95 -> #N/A
A96: 46135 | B96: 1 | C96: Стойка | D96: ПЕРИ-ФС | E96: Улканбаев Равшан | F96: МЕВА ШАРБАТ ИЛМИЙ ЭКСПЕРИМЕНТАЛ ВИНОЧИЛИК | G96: шт | H96: 1000 | I96: 617100 | K96: - | M96: =I96*H96 -> 617100000 | P96: =IF(A96<>"", (M96+O96) / VLOOKUP(A96, 'Курс валют'!$A:$D, 4, 0), "")+N96 -> 51000
A97: 23.04.2026 Итог | M97: =SUBTOTAL(9,M96:M96) -> 617100000 | P97: =IF(A97<>"", (M97+O97) / VLOOKUP(A97, 'Курс валют'!$A:$D, 4, 0), "")+N97 -> #N/A
A98: 46139 | B98: 1 | C98: Опора универсальный 10-25мм | D98: АЗИЯ ФОРМВОРК | E98: Улканбаев Равшан | F98: МЕВА ШАРБАТ ИЛМИЙ ЭКСПЕРИМЕНТАЛ ВИНОЧИЛИК | G98: шт | H98: 30000 | I98: 270 | M98: =[1]Строй.Мат!$I98*[1]Строй.Мат!$H98 -> 8100000 | P98: =IF(A98<>"", (M98+O98) / VLOOKUP(A98, 'Курс валют'!$A:$D, 4, 0), "")+N98 -> 669.42149
A99: 46139 | B99: 2 | C99: Фиксатор | D99: АЗИЯ ФОРМВОРК | E99: Улканбаев Равшан | F99: МЕВА ШАРБАТ ИЛМИЙ ЭКСПЕРИМЕНТАЛ ВИНОЧИЛИК | G99: шт | H99: 5000 | I99: 580 | M99: =[1]Строй.Мат!$I99*[1]Строй.Мат!$H99 -> 2900000 | P99: =IF(A99<>"", (M99+O99) / VLOOKUP(A99, 'Курс валют'!$A:$D, 4, 0), "")+N99 -> 239.66942
A100: 27.04.2026 Итог | M100: =SUBTOTAL(9,M98:M99) -> 11000000 | P100: =IF(A100<>"", (M100+O100) / VLOOKUP(A100, 'Курс валют'!$A:$D, 4, 0), "")+N100 -> #N/A
A101: Общий итог | M101: =SUBTOTAL(9,M2:M99) -> 2103267600 | P101: =IF(A101<>"", (M101+O101) / VLOOKUP(A101, 'Курс валют'!$A:$D, 4, 0), "")+N101 -> #N/A
A102: 46155 | B102: 1 | C102: Стойка | D102: ПЕРИ-ФС | E102: Шерзод Ака | F102: МЕВА ШАРБАТ ИЛМИЙ ЭКСПЕРИМЕНТАЛ ВИНОЧИЛИК | G102: шт | H102: 70 | J102: 50 | M102: 0 | N102: =J102*H102 -> 3500 | P102: =IF(A102<>"", (M102+O102) / VLOOKUP(A102, 'Курс валют'!$A:$D, 4, 0), "")+N102 -> 3500
A103: 46161 | B103: 1 | C103: Стойка | D103: ПЕРИ-ФС | E103: Улканбаев Равшан | F103: МЕВА ШАРБАТ ИЛМИЙ ЭКСПЕРИМЕНТАЛ ВИНОЧИЛИК | G103: шт | H103: 52 | J103: 50 | M103: =[1]Строй.Мат!$I103*[1]Строй.Мат!$H103 -> 0 | N103: =J103*H103 -> 2600 | P103: =IF(A103<>"", (M103+O103) / VLOOKUP(A103, 'Курс валют'!$A:$D, 4, 0), "")+N103 -> 2600
A104: 46168 | B104: 1 | C104: Опора универсальный 10-25мм | D104: АЗИЯ ФОРМВОРК | E104: Улканбаев Равшан | F104: МЕВА ШАРБАТ ИЛМИЙ ЭКСПЕРИМЕНТАЛ ВИНОЧИЛИК | G104: шт | H104: 20000 | I104: 270 | M104: =I104*H104 -> 5400000 | N104: 0 | O104: 0 | P104: =IF(A104<>"", (M104+O104) / VLOOKUP(A104, 'Курс валют'!$A:$D, 4, 0), "")+N104 -> #DIV/0!
A105: 46168 | B105: 2 | C105: Фиксатор | D105: АЗИЯ ФОРМВОРК | E105: Улканбаев Равшан | F105: МЕВА ШАРБАТ ИЛМИЙ ЭКСПЕРИМЕНТАЛ ВИНОЧИЛИК | G105: шт | H105: 5000 | I105: 580 | M105: =I105*H105 -> 2900000 | N105: 0 | O105: 0 | P105: =IF(A105<>"", (M105+O105) / VLOOKUP(A105, 'Курс валют'!$A:$D, 4, 0), "")+N105 -> #DIV/0!
...

Sheet Учет расходов
A1: Дата | B1: Категория | C1: Ед.изм | D1: К-во | E1: Процесс работы | F1: Деньги | G1: Валюта | H1: Приход | I1: Валюта2 | J1: Расход | K1: Текущий курс | L1: Сумма в сумах | M1: Остатка | N1: По доллару | O1: Возврат | P1: {=SUMPRODUCT(H102:H305*IF(G102:G305="USD",I102:I305,1))} -> 929637215 | Q1: {=SUMPRODUCT(J102:J305*IF(G102:G305="USD",K102:K305,1))} -> 933925354 | R1: =P1-Q1 -> -4288139
A2: 46058 | B2: Бетонамешалка | C2: маш/час | D2: 0 | E2: Подготовка бетона | G2: UZS | N2: =IF(A2<>"", J2 / VLOOKUP(A2, 'Курс валют'!$A:$D, 4, 0), "") -> 0
A3: 46058 | B3: Бетон | C3: куб | D3: 310 | E3: Подготовка бетона | G3: UZS | L3: =IF(G3="USD", H3*K3, H3) -> 0 | M3: =IF(H3="USD", I3*L3, I3) -> 0 | N3: =IF(A3<>"", J3 / VLOOKUP(A3, 'Курс валют'!$A:$D, 4, 0), "") -> 0
A4: 46058 | B4: Экскаватор | C4: маш/час | D4: 8 | E4: Подготовка бетона | G4: UZS | J4: =D4*400000-100000 -> 3100000 | L4: =IF(G4="USD", H4*K4, H4) -> 0 | M4: =IF(H4="USD", I4*L4, I4) -> 0 | N4: =IF(A4<>"", J4 / VLOOKUP(A4, 'Курс валют'!$A:$D, 4, 0), "") -> 254.09836
A5: 46058 | B5: Обед | C5: чел | D5: 20 | E5: Подготовка бетона | G5: UZS | J5: 290000 | L5: =IF(G5="USD", H5*K5, H5) -> 0 | M5: =IF(H5="USD", I5*L5, I5) -> 0 | N5: =IF(A5<>"", J5 / VLOOKUP(A5, 'Курс валют'!$A:$D, 4, 0), "") -> 23.770492
A6: 46058 | B6: Щебень | C6: шт | D6: 1 | E6: Подготовка бетона | G6: UZS | J6: 1000000 | L6: =IF(G6="USD", H6*K6, H6) -> 0 | M6: =IF(H6="USD", I6*L6, I6) -> 0 | N6: =IF(A6<>"", J6 / VLOOKUP(A6, 'Курс валют'!$A:$D, 4, 0), "") -> 81.967213
A7: 46058 | B7: Дождевик | C7: шт | D7: 30 | E7: Подготовка бетона | G7: UZS | J7: =D7*15214.8 -> 456444 | L7: =IF(G7="USD", H7*K7, H7) -> 0 | M7: =IF(H7="USD", I7*L7, I7) -> 0 | N7: =IF(A7<>"", J7 / VLOOKUP(A7, 'Курс валют'!$A:$D, 4, 0), "") -> 37.413443
A8: 46058 | B8: Доставка дождевика | C8: услуга | D8: 1 | E8: Подготовка бетона | G8: UZS | J8: 21000 | L8: =IF(G8="USD", H8*K8, H8) -> 0 | M8: =IF(H8="USD", I8*L8, I8) -> 0 | N8: =IF(A8<>"", J8 / VLOOKUP(A8, 'Курс валют'!$A:$D, 4, 0), "") -> 1.7213115
A9: 46058 | B9: Ужин | C9: чел | D9: 20 | E9: Подготовка бетона | G9: UZS | J9: =20000*D9 -> 400000 | L9: =IF(G9="USD", H9*K9, H9) -> 0 | M9: =IF(H9="USD", I9*L9, I9) -> 0 | N9: =IF(A9<>"", J9 / VLOOKUP(A9, 'Курс валют'!$A:$D, 4, 0), "") -> 32.786885
A10: 46058 | B10: Трос Стропа 6м | C10: шт | D10: 1 | E10: Подготовка бетона | G10: UZS | J10: =D10*5370000 -> 5370000 | L10: =IF(G10="USD", H10*K10, H10) -> 0 | M10: =IF(H10="USD", I10*L10, I10) -> 0 | N10: =IF(A10<>"", J10 / VLOOKUP(A10, 'Курс валют'!$A:$D, 4, 0), "") -> 440.16393
A11: 46060 | B11: Бозорли | C11: шт | D11: 1 | E11: Подготовка бетона | G11: UZS | J11: 2350000 | L11: =IF(G11="USD", H11*K11, H11) -> 0 | M11: =IF(H11="USD", I11*L11, I11) -> 0 | N11: =IF(A11<>"", J11 / VLOOKUP(A11, 'Курс валют'!$A:$D, 4, 0), "") -> 192.62295
A12: 46060 | B12: Доставка | C12: услуга | D12: 1 | E12: Подготовка бетона | G12: UZS | J12: 100000 | L12: =IF(G12="USD", H12*K12, H12) -> 0 | M12: =IF(H12="USD", I12*L12, I12) -> 0 | N12: =IF(A12<>"", J12 / VLOOKUP(A12, 'Курс валют'!$A:$D, 4, 0), "") -> 8.1967213
A13: 46060 | B13: Юсель Кран | C13: услуга | D13: 1 | E13: Подготовка бетона | G13: UZS | J13: 200000 | L13: =IF(G13="USD", H13*K13, H13) -> 0 | M13: =IF(H13="USD", I13*L13, I13) -> 0 | N13: =IF(A13<>"", J13 / VLOOKUP(A13, 'Курс валют'!$A:$D, 4, 0), "") -> 16.393443
A14: 46060 | B14: Пализол | C14: шт | D14: 200 | E14: Изоляция бетона | G14: UZS | J14: - | L14: =IF(G14="USD", H14*K14, H14) -> 0 | M14: =IF(H14="USD", I14*L14, I14) -> 0 | N14: =IF(A14<>"", J14 / VLOOKUP(A14, 'Курс валют'!$A:$D, 4, 0), "") -> #VALUE!
A15: 46060 | B15: Фализол | C15: шт | D15: 35 | E15: Изоляция бетона | G15: UZS | J15: - | L15: =IF(G15="USD", H15*K15, H15) -> 0 | M15: =IF(H15="USD", I15*L15, I15) -> 0 | N15: =IF(A15<>"", J15 / VLOOKUP(A15, 'Курс валют'!$A:$D, 4, 0), "") -> #VALUE!
A16: 46060 | B16: Праймер | C16: шт | D16: 20 | E16: Изоляция бетона | G16: UZS | J16: - | L16: =IF(G16="USD", H16*K16, H16) -> 0 | M16: =IF(H16="USD", I16*L16, I16) -> 0 | N16: =IF(A16<>"", J16 / VLOOKUP(A16, 'Курс валют'!$A:$D, 4, 0), "") -> #VALUE!
A17: 46060 | B17: Бензин | C17: лт | D17: 60 | E17: Изоляция бетона | G17: UZS | J17: - | L17: =IF(G17="USD", H17*K17, H17) -> 0 | M17: =IF(H17="USD", I17*L17, I17) -> 0 | N17: =IF(A17<>"", J17 / VLOOKUP(A17, 'Курс валют'!$A:$D, 4, 0), "") -> #VALUE!
A18: 46060 | B18: Валик | C18: шт | D18: 4 | E18: Изоляция бетона | G18: UZS | J18: - | L18: =IF(G18="USD", H18*K18, H18) -> 0 | M18: =IF(H18="USD", I18*L18, I18) -> 0 | N18: =IF(A18<>"", J18 / VLOOKUP(A18, 'Курс валют'!$A:$D, 4, 0), "") -> #VALUE!
A19: 46060 | B19: Доставка мрамора | C19: услуга | D19: 1 | E19: Изоляция бетона | G19: UZS | J19: - | L19: =IF(G19="USD", H19*K19, H19) -> 0 | M19: =IF(H19="USD", I19*L19, I19) -> 0 | N19: =IF(A19<>"", J19 / VLOOKUP(A19, 'Курс валют'!$A:$D, 4, 0), "") -> #VALUE!
A20: 46060 | B20: Бозорли | C20: шт | D20: 1 | E20: Изоляция бетона | G20: UZS | J20: 3955000 | L20: =IF(G20="USD", H20*K20, H20) -> 0 | M20: =IF(H20="USD", I20*L20, I20) -> 0 | N20: =IF(A20<>"", J20 / VLOOKUP(A20, 'Курс валют'!$A:$D, 4, 0), "") -> 324.18033
A21: 46060 | B21: Доставка | C21: услуга | D21: 1 | E21: Изоляция бетона | G21: UZS | J21: 100000 | L21: =IF(G21="USD", H21*K21, H21) -> 0 | M21: =IF(H21="USD", I21*L21, I21) -> 0 | N21: =IF(A21<>"", J21 / VLOOKUP(A21, 'Курс валют'!$A:$D, 4, 0), "") -> 8.1967213
A22: 46060 | B22: Доставка опалубки | C22: услуга | D22: 1 | E22: Изоляция бетона | G22: UZS | J22: 1500000 | L22: =IF(G22="USD", H22*K22, H22) -> 0 | M22: =IF(H22="USD", I22*L22, I22) -> 0 | N22: =IF(A22<>"", J22 / VLOOKUP(A22, 'Курс валют'!$A:$D, 4, 0), "") -> 122.95082
A23: 46060 | B23: Геодезист | C23: услуга | D23: 1 | E23: Изоляция бетона | G23: UZS | J23: 1500000 | L23: =IF(G23="USD", H23*K23, H23) -> 0 | M23: =IF(H23="USD", I23*L23, I23) -> 0 | N23: =IF(A23<>"", J23 / VLOOKUP(A23, 'Курс валют'!$A:$D, 4, 0), "") -> 122.95082
A24: 46061 | B24: Самосвал | C24: ходка | D24: 14 | E24: Подготовка дорог | G24: UZS | J24: =D24*60000+200000 -> 1040000 | L24: =IF(G24="USD", H24*K24, H24) -> 0 | M24: =IF(H24="USD", I24*L24, I24) -> 0 | N24: =IF(A24<>"", J24 / VLOOKUP(A24, 'Курс валют'!$A:$D, 4, 0), "") -> 85.245902
A25: 46061 | B25: Экскаватор | C25: маш/час | D25: 8 | E25: Подготовка дорог | G25: UZS | J25: =D25*400000 -> 3200000 | L25: =IF(G25="USD", H25*K25, H25) -> 0 | M25: =IF(H25="USD", I25*L25, I25) -> 0 | N25: =IF(A25<>"", J25 / VLOOKUP(A25, 'Курс валют'!$A:$D, 4, 0), "") -> 262.29508
A26: 46061 | B26: Прочее | C26: услуга | D26: 1 | E26: Подготовка дорог | G26: UZS | J26: 60000 | L26: =IF(G26="USD", H26*K26, H26) -> 0 | M26: =IF(H26="USD", I26*L26, I26) -> 0 | N26: =IF(A26<>"", J26 / VLOOKUP(A26, 'Курс валют'!$A:$D, 4, 0), "") -> 4.9180328
A27: 46062 | B27: ХозТовары | C27: шт | D27: 1 | E27: Подготовка дорог | G27: UZS | J27: 200000 | L27: =IF(G27="USD", H27*K27, H27) -> 0 | M27: =IF(H27="USD", I27*L27, I27) -> 0 | N27: =IF(A27<>"", J27 / VLOOKUP(A27, 'Курс валют'!$A:$D, 4, 0), "") -> 16.393443
A28: 46062 | B28: Чистка Канализации | C28: услуга | D28: 1 | E28: Подготовка дорог | G28: UZS | J28: 1620000 | L28: =IF(G28="USD", H28*K28, H28) -> 0 | M28: =IF(H28="USD", I28*L28, I28) -> 0 | N28: =IF(A28<>"", J28 / VLOOKUP(A28, 'Курс валют'!$A:$D, 4, 0), "") -> 132.78689
A29: 46062 | B29: Нон | C29: шт | D29: 20 | E29: Подготовка дорог | G29: UZS | J29: =3000*D29 -> 60000 | L29: =IF(G29="USD", H29*K29, H29) -> 0 | M29: =IF(H29="USD", I29*L29, I29) -> 0 | N29: =IF(A29<>"", J29 / VLOOKUP(A29, 'Курс валют'!$A:$D, 4, 0), "") -> 4.9180328
A30: 46063 | B30: Журнал производства | C30: шт | D30: 1 | E30: Подготовка дорог | G30: UZS | J30: 1000000 | L30: =IF(G30="USD", H30*K30, H30) -> 0 | M30: =IF(H30="USD", I30*L30, I30) -> 0 | N30: =IF(A30<>"", J30 / VLOOKUP(A30, 'Курс валют'!$A:$D, 4, 0), "") -> 81.967213
A31: 46063 | B31: Погрузчик | C31: маш/час | D31: 4.5 | E31: Подготовка дорог | G31: UZS | J31: =380000*D31 -> 1710000 | L31: =IF(G31="USD", H31*K31, H31) -> 0 | M31: =IF(H31="USD", I31*L31, I31) -> 0 | N31: =IF(A31<>"", J31 / VLOOKUP(A31, 'Курс валют'!$A:$D, 4, 0), "") -> 140.16393
A32: 46063 | B32: Самосвал | C32: ходка | D32: 6.5 | E32: Подготовка дорог | G32: UZS | J32: =100000*D32 -> 650000 | L32: =IF(G32="USD", H32*K32, H32) -> 0 | M32: =IF(H32="USD", I32*L32, I32) -> 0 | N32: =IF(A32<>"", J32 / VLOOKUP(A32, 'Курс валют'!$A:$D, 4, 0), "") -> 53.278689
A33: 46063 | B33: Экскаватор | C33: маш/час | D33: 5 | E33: Подготовка дорог | G33: UZS | J33: =650000*D33 -> 3250000 | L33: =IF(G33="USD", H33*K33, H33) -> 0 | M33: =IF(H33="USD", I33*L33, I33) -> 0 | N33: =IF(A33<>"", J33 / VLOOKUP(A33, 'Курс валют'!$A:$D, 4, 0), "") -> 266.39344
A34: 46063 | B34: Бозорлик | C34: шт | D34: 1 | E34: Подготовка дорог | G34: UZS | J34: 4000000 | L34: =IF(G34="USD", H34*K34, H34) -> 0 | M34: =IF(H34="USD", I34*L34, I34) -> 0 | N34: =IF(A34<>"", J34 / VLOOKUP(A34, 'Курс валют'!$A:$D, 4, 0), "") -> 327.86885
A35: 46064 | B35: Щебень | C35: Хово | D35: 1 | E35: Подготовка дорог | G35: UZS | J35: 2100000 | L35: =IF(G35="USD", H35*K35, H35) -> 0 | M35: =IF(H35="USD", I35*L35, I35) -> 0 | N35: =IF(A35<>"", J35 / VLOOKUP(A35, 'Курс валют'!$A:$D, 4, 0), "") -> 170.59301
A36: 46064 | B36: Камаз | C36: ходка | D36: 9 | E36: Подготовка дорог | G36: UZS | J36: =70000*D36 -> 630000 | L36: =IF(G36="USD", H36*K36, H36) -> 0 | M36: =IF(H36="USD", I36*L36, I36) -> 0 | N36: =IF(A36<>"", J36 / VLOOKUP(A36, 'Курс валют'!$A:$D, 4, 0), "") -> 51.177904
A37: 46064 | B37: Самосвал | C37: ходка | D37: 12 | E37: Подготовка дорог | G37: UZS | J37: =D37*130000 -> 1560000 | L37: =IF(G37="USD", H37*K37, H37) -> 0 | M37: =IF(H37="USD", I37*L37, I37) -> 0 | N37: =IF(A37<>"", J37 / VLOOKUP(A37, 'Курс валют'!$A:$D, 4, 0), "") -> 126.72624
A38: 46064 | B38: Экскаватор | C38: маш/час | D38: 4.5 | E38: Подготовка дорог | G38: UZS | J38: =D38*400000 -> 1800000 | L38: =IF(G38="USD", H38*K38, H38) -> 0 | M38: =IF(H38="USD", I38*L38, I38) -> 0 | N38: =IF(A38<>"", J38 / VLOOKUP(A38, 'Курс валют'!$A:$D, 4, 0), "") -> 146.22258
A39: 46064 | B39: Экскаватор | C39: маш/час | D39: 9 | E39: Подготовка дорог | G39: UZS | J39: =D39*650000 -> 5850000 | L39: =IF(G39="USD", H39*K39, H39) -> 0 | M39: =IF(H39="USD", I39*L39, I39) -> 0 | N39: =IF(A39<>"", J39 / VLOOKUP(A39, 'Курс валют'!$A:$D, 4, 0), "") -> 475.2234
A40: 46064 | B40: Каток | C40: день | D40: 1 | E40: Подготовка дорог | G40: UZS | J40: 4000000 | L40: =IF(G40="USD", H40*K40, H40) -> 0 | M40: =IF(H40="USD", I40*L40, I40) -> 0 | N40: =IF(A40<>"", J40 / VLOOKUP(A40, 'Курс валют'!$A:$D, 4, 0), "") -> 324.93907
A41: 46064 | B41: Щебень | C41: Хово | D41: 1 | E41: Подготовка дорог | G41: UZS | J41: 2300000 | L41: =IF(G41="USD", H41*K41, H41) -> 0 | M41: =IF(H41="USD", I41*L41, I41) -> 0 | N41: =IF(A41<>"", J41 / VLOOKUP(A41, 'Курс валют'!$A:$D, 4, 0), "") -> 186.83997
A42: 46064 | B42: Доставка(Метропол) | C42: услуга | D42: 1 | E42: Подготовка дорог | G42: UZS | J42: 30000 | L42: =IF(G42="USD", H42*K42, H42) -> 0 | M42: =IF(H42="USD", I42*L42, I42) -> 0 | N42: =IF(A42<>"", J42 / VLOOKUP(A42, 'Курс валют'!$A:$D, 4, 0), "") -> 2.4370431
A43: 46066 | B43: Доставка(Колокольчик) | C43: услуга | D43: 1 | E43: Подушка | G43: UZS | J43: 400000 | L43: =IF(G43="USD", H43*K43, H43) -> 0 | M43: =IF(H43="USD", I43*L43, I43) -> 0 | N43: =IF(A43<>"", J43 / VLOOKUP(A43, 'Курс валют'!$A:$D, 4, 0), "") -> 32.786885
A44: 46066 | B44: Рация | C44: шт | D44: 8 | E44: Подушка | G44: UZS | J44: =140000*D44 -> 1120000 | L44: =IF(G44="USD", H44*K44, H44) -> 0 | M44: =IF(H44="USD", I44*L44, I44) -> 0 | N44: =IF(A44<>"", J44 / VLOOKUP(A44, 'Курс валют'!$A:$D, 4, 0), "") -> 91.803279
A45: 46066 | B45: Экскаватор | C45: маш/час | D45: 2 | E45: Подушка | G45: UZS | J45: =750000*D45 -> 1500000 | L45: =IF(G45="USD", H45*K45, H45) -> 0 | M45: =IF(H45="USD", I45*L45, I45) -> 0 | N45: =IF(A45<>"", J45 / VLOOKUP(A45, 'Курс валют'!$A:$D, 4, 0), "") -> 122.95082
A46: 46067 | B46: Супурги | C46: шт | D46: 8 | E46: Подушка | G46: UZS | L46: =IF(G46="USD", H46*K46, H46) -> 0 | M46: =IF(H46="USD", I46*L46, I46) -> 0 | N46: =IF(A46<>"", J46 / VLOOKUP(A46, 'Курс валют'!$A:$D, 4, 0), "") -> 0
A47: 46067 | B47: Доставка(Вертолет) | C47: услуга | D47: 1 | E47: Подушка | G47: UZS | J47: 60000 | L47: =IF(G47="USD", H47*K47, H47) -> 0 | M47: =IF(H47="USD", I47*L47, I47) -> 0 | N47: =IF(A47<>"", J47 / VLOOKUP(A47, 'Курс валют'!$A:$D, 4, 0), "") -> 4.9261084
A48: 46067 | B48: Вертолет | C48: шт | D48: 10 | E48: Подушка | G48: UZS | L48: =IF(G48="USD", H48*K48, H48) -> 0 | M48: =IF(H48="USD", I48*L48, I48) -> 0 | N48: =IF(A48<>"", J48 / VLOOKUP(A48, 'Курс валют'!$A:$D, 4, 0), "") -> 0
A49: 46067 | B49: Бозорли(Гуруч) | C49: кг | D49: 160 | E49: Подушка | G49: UZS | L49: =IF(G49="USD", H49*K49, H49) -> 0 | M49: =IF(H49="USD", I49*L49, I49) -> 0 | N49: =IF(A49<>"", J49 / VLOOKUP(A49, 'Курс валют'!$A:$D, 4, 0), "") -> 0
A50: 46069 | B50: Электрод | C50: кг | D50: 50 | E50: Подушка | G50: UZS | L50: =IF(G50="USD", H50*K50, H50) -> 0 | M50: =IF(H50="USD", I50*L50, I50) -> 0 | N50: =IF(A50<>"", J50 / VLOOKUP(A50, 'Курс валют'!$A:$D, 4, 0), "") -> 0
A51: 46070 | B51: Автовышка (Хитой) | C51: маш/час | D51: 5 | E51: Подушка | G51: UZS | J51: =D51*600000 -> 3000000 | L51: =IF(G51="USD", H51*K51, H51) -> 0 | M51: =IF(H51="USD", I51*L51, I51) -> 0 | N51: =IF(A51<>"", J51 / VLOOKUP(A51, 'Курс валют'!$A:$D, 4, 0), "") -> 246.91358
A52: 46070 | B52: Бозорли | C52: услуга | D52: 1 | E52: Подушка | G52: UZS | J52: 1530000 | L52: =IF(G52="USD", H52*K52, H52) -> 0 | M52: =IF(H52="USD", I52*L52, I52) -> 0 | N52: =IF(A52<>"", J52 / VLOOKUP(A52, 'Курс валют'!$A:$D, 4, 0), "") -> 125.92593
A53: 46070 | B53: Опалубка Мой | C53: лт | D53: 400 | E53: Подушка | G53: UZS | L53: =IF(G53="USD", H53*K53, H53) -> 0 | M53: =IF(H53="USD", I53*L53, I53) -> 0 | N53: =IF(A53<>"", J53 / VLOOKUP(A53, 'Курс валют'!$A:$D, 4, 0), "") -> 0
A54: 46070 | B54: Доставка Мой | C54: услуга | D54: 1 | E54: Подушка | G54: UZS | J54: 100000 | L54: =IF(G54="USD", H54*K54, H54) -> 0 | M54: =IF(H54="USD", I54*L54, I54) -> 0 | N54: =IF(A54<>"", J54 / VLOOKUP(A54, 'Курс валют'!$A:$D, 4, 0), "") -> 8.2304527
A55: 46070 | B55: Доставка Бозорли | C55: услуга | D55: 1 | E55: Подушка | G55: UZS | J55: 70000 | L55: =IF(G55="USD", H55*K55, H55) -> 0 | M55: =IF(H55="USD", I55*L55, I55) -> 0 | N55: =IF(A55<>"", J55 / VLOOKUP(A55, 'Курс валют'!$A:$D, 4, 0), "") -> 5.7613169
A56: 46070 | B56: Экскаватор | C56: маш/час | D56: 1 | E56: Подушка | G56: UZS | J56: =D56*400000 -> 400000 | L56: =IF(G56="USD", H56*K56, H56) -> 0 | M56: =IF(H56="USD", I56*L56, I56) -> 0 | N56: =IF(A56<>"", J56 / VLOOKUP(A56, 'Курс валют'!$A:$D, 4, 0), "") -> 32.921811
A57: 46070 | B57: Строй Материал | C57: шт | D57: 1 | E57: Подушка | G57: UZS | J57: 2050000 | L57: =IF(G57="USD", H57*K57, H57) -> 0 | M57: =IF(H57="USD", I57*L57, I57) -> 0 | N57: =IF(A57<>"", J57 / VLOOKUP(A57, 'Курс валют'!$A:$D, 4, 0), "") -> 168.72428
A58: 46070 | B58: Щебень | C58: Зил | D58: 1 | E58: Подушка | G58: UZS | J58: 1000000 | L58: =IF(G58="USD", H58*K58, H58) -> 0 | M58: =IF(H58="USD", I58*L58, I58) -> 0 | N58: =IF(A58<>"", J58 / VLOOKUP(A58, 'Курс валют'!$A:$D, 4, 0), "") -> 82.304527
A59: 46071 | B59: Кран | C59: маш/час | D59: 2 | E59: Подушка | G59: UZS | J59: =1000000*D59 -> 2000000 | L59: =IF(G59="USD", H59*K59, H59) -> 0 | M59: =IF(H59="USD", I59*L59, I59) -> 0 | N59: =IF(A59<>"", J59 / VLOOKUP(A59, 'Курс валют'!$A:$D, 4, 0), "") -> 165.56291
A60: 46071 | B60: Эскаватор | C60: маш/час | D60: 4 | E60: Подушка | G60: UZS | J60: =450000*D60 -> 1800000 | L60: =IF(G60="USD", H60*K60, H60) -> 0 | M60: =IF(H60="USD", I60*L60, I60) -> 0 | N60: =IF(A60<>"", J60 / VLOOKUP(A60, 'Курс валют'!$A:$D, 4, 0), "") -> 149.00662
A61: 46071 | B61: Щебень | C61: Камаз | D61: 1 | E61: Подушка | G61: UZS | J61: 1000000 | L61: =IF(G61="USD", H61*K61, H61) -> 0 | M61: =IF(H61="USD", I61*L61, I61) -> 0 | N61: =IF(A61<>"", J61 / VLOOKUP(A61, 'Курс валют'!$A:$D, 4, 0), "") -> 82.781457
A62: 46071 | B62: Эхсон | C62: шт | D62: 1 | E62: Подушка | G62: UZS | J62: 10000000 | L62: =IF(G62="USD", H62*K62, H62) -> 0 | M62: =IF(H62="USD", I62*L62, I62) -> 0 | N62: =IF(A62<>"", J62 / VLOOKUP(A62, 'Курс валют'!$A:$D, 4, 0), "") -> 827.81457
A63: 46071 | B63: Доставка Бозорли | C63: услуга | D63: 1 | E63: Подушка | G63: UZS | J63: 120000 | L63: =IF(G63="USD", H63*K63, H63) -> 0 | M63: =IF(H63="USD", I63*L63, I63) -> 0 | N63: =IF(A63<>"", J63 / VLOOKUP(A63, 'Курс валют'!$A:$D, 4, 0), "") -> 9.9337748
A64: 46072 | B64: Экскаватор | C64: услуга | D64: 1 | E64: Подготовка дорог | G64: UZS | J64: 300000 | L64: =IF(G64="USD", H64*K64, H64) -> 0 | M64: =IF(H64="USD", I64*L64, I64) -> 0 | N64: =IF(A64<>"", J64 / VLOOKUP(A64, 'Курс валют'!$A:$D, 4, 0), "") -> 25
A65: 46072 | B65: ТБ | C65: услуга | D65: 1 | E65: Подушка | G65: UZS | J65: 1000000 | L65: =IF(G65="USD", H65*K65, H65) -> 0 | M65: =IF(H65="USD", I65*L65, I65) -> 0 | N65: =IF(A65<>"", J65 / VLOOKUP(A65, 'Курс валют'!$A:$D, 4, 0), "") -> 83.333333
A66: 46072 | B66: Гушт | C66: кг | D66: 18 | E66: Подушка | G66: UZS | J66: =D66*100000 -> 1800000 | L66: =IF(G66="USD", H66*K66, H66) -> 0 | M66: =IF(H66="USD", I66*L66, I66) -> 0 | N66: =IF(A66<>"", J66 / VLOOKUP(A66, 'Курс валют'!$A:$D, 4, 0), "") -> 150
A67: 46072 | B67: Холодильник | C67: шт | D67: 1 | E67: Подушка | G67: UZS | J67: =12000*150 -> 1800000 | L67: =IF(G67="USD", H67*K67, H67) -> 0 | M67: =IF(H67="USD", I67*L67, I67) -> 0 | N67: =IF(A67<>"", J67 / VLOOKUP(A67, 'Курс валют'!$A:$D, 4, 0), "") -> 150
A68: 46072 | B68: Сим | C68: кг | D68: 2000 | E68: Подушка | G68: UZS | J68: =10126*D68 -> 20252000 | L68: =IF(G68="USD", H68*K68, H68) -> 0 | M68: =IF(H68="USD", I68*L68, I68) -> 0 | N68: =IF(A68<>"", J68 / VLOOKUP(A68, 'Курс валют'!$A:$D, 4, 0), "") -> 1687.6667
A69: 46073 | B69: Щебень | C69: Howo | D69: 1 | E69: Подготовка дорог | G69: UZS | J69: 2100000 | L69: =IF(G69="USD", H69*K69, H69) -> 0 | M69: =IF(H69="USD", I69*L69, I69) -> 0 | N69: =IF(A69<>"", J69 / VLOOKUP(A69, 'Курс валют'!$A:$D, 4, 0), "") -> 175
A70: 46073 | B70: Экскаватор | C70: маш/час | D70: 4 | E70: Подготовка дорог | G70: UZS | J70: =400000*D70 -> 1600000 | L70: =IF(G70="USD", H70*K70, H70) -> 0 | M70: =IF(H70="USD", I70*L70, I70) -> 0 | N70: =IF(A70<>"", J70 / VLOOKUP(A70, 'Курс валют'!$A:$D, 4, 0), "") -> 133.33333
A71: 46073 | B71: Геодезия | C71: услуга | D71: 1 | E71: Подушка | G71: UZS | J71: 6839050 | L71: =IF(G71="USD", H71*K71, H71) -> 0 | M71: =IF(H71="USD", I71*L71, I71) -> 0 | N71: =IF(A71<>"", J71 / VLOOKUP(A71, 'Курс валют'!$A:$D, 4, 0), "") -> 569.92083
A72: 46073 | B72: Доставка Сим | C72: услуга | D72: 1 | E72: Подушка | G72: UZS | J72: 150000 | L72: =IF(G72="USD", H72*K72, H72) -> 0 | M72: =IF(H72="USD", I72*L72, I72) -> 0 | N72: =IF(A72<>"", J72 / VLOOKUP(A72, 'Курс валют'!$A:$D, 4, 0), "") -> 12.5
A73: 46073 | B73: Строй Материал+Доставка | C73: шт | D73: 1 | E73: Подушка | G73: UZS | J73: 4689960 | L73: =IF(G73="USD", H73*K73, H73) -> 0 | M73: =IF(H73="USD", I73*L73, I73) -> 0 | N73: =IF(A73<>"", J73 / VLOOKUP(A73, 'Курс валют'!$A:$D, 4, 0), "") -> 390.83
A74: 46073 | B74: Миржалол Аванс | C74: зарплата | D74: 1 | E74: Подушка | G74: UZS | J74: 400000 | L74: =IF(G74="USD", H74*K74, H74) -> 0 | M74: =IF(H74="USD", I74*L74, I74) -> 0 | N74: =IF(A74<>"", J74 / VLOOKUP(A74, 'Курс валют'!$A:$D, 4, 0), "") -> 33.333333
A75: 46073 | B75: Пенопласт | C75: почка | D75: 3 | E75: Подушка | G75: UZS | J75: =603684*D75 -> 1811052 | L75: =IF(G75="USD", H75*K75, H75) -> 0 | M75: =IF(H75="USD", I75*L75, I75) -> 0 | N75: =IF(A75<>"", J75 / VLOOKUP(A75, 'Курс валют'!$A:$D, 4, 0), "") -> 150.921
A76: 46073 | B76: Доставка пенопласта | C76: услуга | D76: 1 | E76: Подушка | G76: UZS | J76: 240000 | L76: =IF(G76="USD", H76*K76, H76) -> 0 | M76: =IF(H76="USD", I76*L76, I76) -> 0 | N76: =IF(A76<>"", J76 / VLOOKUP(A76, 'Курс валют'!$A:$D, 4, 0), "") -> 20
A77: 46074 | B77: Автовышка (Ивановец) | C77: маш/час | D77: 4 | E77: Подготовка дорог | G77: UZS | J77: 1500000 | L77: =IF(G77="USD", H77*K77, H77) -> 0 | M77: =IF(H77="USD", I77*L77, I77) -> 0 | N77: =IF(A77<>"", J77 / VLOOKUP(A77, 'Курс валют'!$A:$D, 4, 0), "") -> 123.96694
A78: 46074 | B78: Бетон плита | C78: шт | D78: 16 | E78: Подготовка дорог | G78: UZS | J78: =D78*2800000 -> 44800000 | L78: =IF(G78="USD", H78*K78, H78) -> 0 | M78: =IF(H78="USD", I78*L78, I78) -> 0 | N78: =IF(A78<>"", J78 / VLOOKUP(A78, 'Курс валют'!$A:$D, 4, 0), "") -> 3702.4793
A79: 46074 | B79: Аренда болгарки | C79: шт | D79: 2 | E79: Подушка | G79: UZS | J79: =50000*D79 -> 100000 | L79: =IF(G79="USD", H79*K79, H79) -> 0 | M79: =IF(H79="USD", I79*L79, I79) -> 0 | N79: =IF(A79<>"", J79 / VLOOKUP(A79, 'Курс валют'!$A:$D, 4, 0), "") -> 8.2644628
A80: 46074 | B80: Нон | C80: день | D80: 3 | E80: Подушка | G80: UZS | J80: 150000 | L80: =IF(G80="USD", H80*K80, H80) -> 0 | M80: =IF(H80="USD", I80*L80, I80) -> 0 | N80: =IF(A80<>"", J80 / VLOOKUP(A80, 'Курс валют'!$A:$D, 4, 0), "") -> 12.396694
A81: 46075 | B81: Бозорлик | C81: шт | D81: 1 | E81: Подготовка дорог | G81: UZS | J81: 1835000 | L81: =IF(G81="USD", H81*K81, H81) -> 0 | M81: =IF(H81="USD", I81*L81, I81) -> 0 | N81: =IF(A81<>"", J81 / VLOOKUP(A81, 'Курс валют'!$A:$D, 4, 0), "") -> 152.91667
A82: 46075 | B82: Доставка(Бозорли) | C82: услуга | D82: 1 | E82: Подготовка дорог | G82: UZS | J82: 80000 | L82: =IF(G82="USD", H82*K82, H82) -> 0 | M82: =IF(H82="USD", I82*L82, I82) -> 0 | N82: =IF(A82<>"", J82 / VLOOKUP(A82, 'Курс валют'!$A:$D, 4, 0), "") -> 6.6666667
A83: 46075 | B83: Кран замена | C83: шт | D83: 1 | E83: Подушка | G83: UZS | J83: 6075000 | L83: =IF(G83="USD", H83*K83, H83) -> 0 | M83: =IF(H83="USD", I83*L83, I83) -> 0 | N83: =IF(A83<>"", J83 / VLOOKUP(A83, 'Курс валют'!$A:$D, 4, 0), "") -> 506.25
A84: 46077 | B84: ППР(ПТО) | C84: услуга | D84: 1 | E84: Подушка | G84: UZS | J84: 2000000 | L84: =IF(G84="USD", H84*K84, H84) -> 0 | M84: =IF(H84="USD", I84*L84, I84) -> 0 | N84: =IF(A84<>"", J84 / VLOOKUP(A84, 'Курс валют'!$A:$D, 4, 0), "") -> 165.28926
A85: 46077 | B85: Ремонт Электроинструментов | C85: шт | D85: 2 | E85: Подушка | G85: UZS | J85: =D85*100000 -> 200000 | L85: =IF(G85="USD", H85*K85, H85) -> 0 | M85: =IF(H85="USD", I85*L85, I85) -> 0 | N85: =IF(A85<>"", J85 / VLOOKUP(A85, 'Курс валют'!$A:$D, 4, 0), "") -> 16.528926
A86: 46079 | B86: Обвал убрать | C86: услуга | D86: 1 | E86: Подушка | G86: UZS | J86: 1500000 | L86: =IF(G86="USD", H86*K86, H86) -> 0 | M86: =IF(H86="USD", I86*L86, I86) -> 0 | N86: =IF(A86<>"", J86 / VLOOKUP(A86, 'Курс валют'!$A:$D, 4, 0), "") -> 123.96694
A87: 46080 | B87: Бозорли | C87: шт | D87: 1 | E87: Подушка | G87: UZS | J87: 915000 | L87: =IF(G87="USD", H87*K87, H87) -> 0 | M87: =IF(H87="USD", I87*L87, I87) -> 0 | N87: =IF(A87<>"", J87 / VLOOKUP(A87, 'Курс валют'!$A:$D, 4, 0), "") -> 75.745033
A88: 46080 | B88: Гушт | C88: кг | D88: 25 | E88: Подушка | G88: UZS | J88: =D88*105000 -> 2625000 | L88: =IF(G88="USD", H88*K88, H88) -> 0 | M88: =IF(H88="USD", I88*L88, I88) -> 0 | N88: =IF(A88<>"", J88 / VLOOKUP(A88, 'Курс валют'!$A:$D, 4, 0), "") -> 217.30132
A89: 46080 | B89: Счетчик | C89: услуга | D89: 1 | E89: Подушка | G89: UZS | J89: 1000000 | L89: =IF(G89="USD", H89*K89, H89) -> 0 | M89: =IF(H89="USD", I89*L89, I89) -> 0 | N89: =IF(A89<>"", J89 / VLOOKUP(A89, 'Курс валют'!$A:$D, 4, 0), "") -> 82.781457
A90: 46081 | B90: Нон | C90: шт | D90: - | E90: Подвал | G90: UZS | J90: 42000 | L90: =IF(G90="USD", H90*K90, H90) -> 0 | M90: =IF(H90="USD", I90*L90, I90) -> 0 | N90: =IF(A90<>"", J90 / VLOOKUP(A90, 'Курс валют'!$A:$D, 4, 0), "") -> 3.4768212
A91: 46082 | B91: Оплата за подушку | C91: услуга | D91: 1 | E91: Подушка | G91: UZS | J91: 195000000 | L91: =IF(G91="USD", H91*K91, H91) -> 0 | M91: =IF(H91="USD", I91*L91, I91) -> 0 | N91: =IF(A91<>"", J91 / VLOOKUP(A91, 'Курс валют'!$A:$D, 4, 0), "") -> 16182.573
A92: 46083 | B92: Строй Материал | C92: шт | D92: 1 | E92: Подвал | G92: UZS | J92: 8620000 | L92: =IF(G92="USD", H92*K92, H92) -> 0 | M92: =IF(H92="USD", I92*L92, I92) -> 0 | N92: =IF(A92<>"", J92 / VLOOKUP(A92, 'Курс валют'!$A:$D, 4, 0), "") -> 713.57616
A93: 46084 | B93: Оплата за подушку | C93: услуга | D93: 1 | E93: Подушка | G93: UZS | J93: 30000000 | L93: =IF(G93="USD", H93*K93, H93) -> 0 | M93: =IF(H93="USD", I93*L93, I93) -> 0 | N93: =IF(A93<>"", J93 / VLOOKUP(A93, 'Курс валют'!$A:$D, 4, 0), "") -> 2483.4437
A94: 46084 | B94: Крановщик | C94: зарплата | D94: 1 | E94: Подушка | G94: UZS | J94: 6600000 | L94: =IF(G94="USD", H94*K94, H94) -> 0 | M94: =IF(H94="USD", I94*L94, I94) -> 0 | N94: =IF(A94<>"", J94 / VLOOKUP(A94, 'Курс валют'!$A:$D, 4, 0), "") -> 546.35762
A95: 46084 | B95: Строй Материал | C95: шт | D95: 1 | E95: Подвал | G95: UZS | J95: 2025000 | L95: =IF(G95="USD", H95*K95, H95) -> 0 | M95: =IF(H95="USD", I95*L95, I95) -> 0 | N95: =IF(A95<>"", J95 / VLOOKUP(A95, 'Курс валют'!$A:$D, 4, 0), "") -> 167.63245
A96: 46085 | B96: Оплата за подушку | C96: услуга | D96: 1 | E96: Подушка | G96: UZS | J96: 130000000 | L96: =IF(G96="USD", H96*K96, H96) -> 0 | M96: =IF(H96="USD", I96*L96, I96) -> 0 | N96: =IF(A96<>"", J96 / VLOOKUP(A96, 'Курс валют'!$A:$D, 4, 0), "") -> 10761.589
A97: 46085 | B97: Миржалол | C97: зарплата | D97: 1 | E97: Подвал | G97: UZS | J97: 2400000 | L97: =IF(G97="USD", H97*K97, H97) -> 0 | M97: =IF(H97="USD", I97*L97, I97) -> 0 | N97: =IF(A97<>"", J97 / VLOOKUP(A97, 'Курс валют'!$A:$D, 4, 0), "") -> 198.6755
A98: 46085 | B98: Охрана | C98: зарплата | D98: 2 | E98: Подвал | G98: UZS | J98: =3500000*D98 -> 7000000 | L98: =IF(G98="USD", H98*K98, H98) -> 0 | M98: =IF(H98="USD", I98*L98, I98) -> 0 | N98: =IF(A98<>"", J98 / VLOOKUP(A98, 'Курс валют'!$A:$D, 4, 0), "") -> 579.4702
A99: 46085 | B99: Нурсаид | C99: зарплата | D99: 1 | E99: Подвал | G99: UZS | J99: 5500000 | L99: =IF(G99="USD", H99*K99, H99) -> 0 | M99: =IF(H99="USD", I99*L99, I99) -> 0 | N99: =IF(A99<>"", J99 / VLOOKUP(A99, 'Курс валют'!$A:$D, 4, 0), "") -> 455.29801
A100: 46085 | B100: Повар | C100: зарплата | D100: 1 | E100: Подвал | G100: UZS | J100: 5000000 | L100: =IF(G100="USD", H100*K100, H100) -> 0 | M100: =IF(H100="USD", I100*L100, I100) -> 0 | N100: =IF(A100<>"", J100 / VLOOKUP(A100, 'Курс валют'!$A:$D, 4, 0), "") -> 413.90728
...

Sheet Зарплата
A1: Дата | B1: Наименование | C1: Ед.изм | D1: Сумма за ед.изм | E1: В долларе | F1: В долларе
A2: Столбец1 | B2: Столбец2 | C2: Столбец3 | D2: Столбец4 | E2: Столбец5 | F2: Столбец6
A3: 45920 | B3: Санжар | C3: зарплата | D3: 1400000 | F3: =IF(A3<>"", D3 / VLOOKUP(A3, 'Курс валют'!$A:$D, 4, 0), "")+Таблица4[[#This Row],[Столбец5]] -> #N/A
A4: 45924 | B4: Санжар | C4: зарплата | D4: 3700000 | F4: =IF(A4<>"", D4 / VLOOKUP(A4, 'Курс валют'!$A:$D, 4, 0), "")+Таблица4[[#This Row],[Столбец5]] -> #N/A
A5: 45960 | B5: Миржалол | C5: Аванс | D5: 1000000 | F5: =IF(A5<>"", D5 / VLOOKUP(A5, 'Курс валют'!$A:$D, 4, 0), "")+Таблица4[[#This Row],[Столбец5]] -> #N/A
A6: 45964 | B6: Миржалол | C6: зарплата | D6: 3000000 | F6: =IF(A6<>"", D6 / VLOOKUP(A6, 'Курс валют'!$A:$D, 4, 0), "")+Таблица4[[#This Row],[Столбец5]] -> 250.62657
A7: 45964 | B7: Санжар | C7: зарплата | D7: 3500000 | F7: =IF(A7<>"", D7 / VLOOKUP(A7, 'Курс валют'!$A:$D, 4, 0), "")+Таблица4[[#This Row],[Столбец5]] -> 292.39766
A8: 45964 | B8: Миролим | C8: зарплата | D8: 3500000 | F8: =IF(A8<>"", D8 / VLOOKUP(A8, 'Курс валют'!$A:$D, 4, 0), "")+Таблица4[[#This Row],[Столбец5]] -> 292.39766
A9: 45964 | B9: Нурсаид | C9: зарплата | D9: 2500000 | F9: =IF(A9<>"", D9 / VLOOKUP(A9, 'Курс валют'!$A:$D, 4, 0), "")+Таблица4[[#This Row],[Столбец5]] -> 208.85547
A10: 45982 | B10: Нурсаид | C10: зарплата | D10: 4000000 | F10: =IF(A10<>"", D10 / VLOOKUP(A10, 'Курс валют'!$A:$D, 4, 0), "")+Таблица4[[#This Row],[Столбец5]] -> #N/A
A11: 45993 | B11: Миржалол | C11: зарплата | D11: 5000000 | F11: =IF(A11<>"", D11 / VLOOKUP(A11, 'Курс валют'!$A:$D, 4, 0), "")+Таблица4[[#This Row],[Столбец5]] -> #N/A
A12: 45993 | B12: Нурсаид | C12: зарплата | D12: 1250000 | F12: =IF(A12<>"", D12 / VLOOKUP(A12, 'Курс валют'!$A:$D, 4, 0), "")+Таблица4[[#This Row],[Столбец5]] -> #N/A
A13: 45993 | B13: Санжар | C13: зарплата | D13: 3500000 | F13: =IF(A13<>"", D13 / VLOOKUP(A13, 'Курс валют'!$A:$D, 4, 0), "")+Таблица4[[#This Row],[Столбец5]] -> #N/A
A14: 45993 | B14: Миролим | C14: зарплата | D14: 3960000 | F14: =IF(A14<>"", D14 / VLOOKUP(A14, 'Курс валют'!$A:$D, 4, 0), "")+Таблица4[[#This Row],[Столбец5]] -> #N/A
... A21: 46046 | B21: Миржалол | C21: Аванс | D21: 1000000 | F21: =IF(A21<>"", D21 / VLOOKUP(A21, 'Курс валют'!$A:$D, 4, 0), "")+Таблица4[[#This Row],[Столбец5]] -> #N/A
A22: 46053 | B22: Миржалол | C22: зарплата | D22: 50000 | E22: 200 | F22: =IF(A22<>"", D22 / VLOOKUP(A22, 'Курс валют'!$A:$D, 4, 0), "")+Таблица4[[#This Row],[Столбец5]] -> #N/A
A23: 46053 | B23: Миржалол | C23: Питание | D23: 1265000 | E23: 100 | F23: =IF(A23<>"", D23 / VLOOKUP(A23, 'Курс валют'!$A:$D, 4, 0), "")+Таблица4[[#This Row],[Столбец5]] -> #N/A
A24: 46053 | B24: Нурсаид | C24: зарплата | D24: 5500000 | F24: =IF(A24<>"", D24 / VLOOKUP(A24, 'Курс валют'!$A:$D, 4, 0), "")+Таблица4[[#This Row],[Столбец5]] -> #N/A
A25: 46054 | B25: Санжар | C25: зарплата | D25: 3500000 | F25: =IF(A25<>"", D25 / VLOOKUP(A25, 'Курс валют'!$A:$D, 4, 0), "")+Таблица4[[#This Row],[Столбец5]] -> 286.88525
A26: 46054 | B26: Миролим | C26: зарплата | D26: 3500000 | F26: =IF(A26<>"", D26 / VLOOKUP(A26, 'Курс валют'!$A:$D, 4, 0), "")+Таблица4[[#This Row],[Столбец5]] -> 286.88525
A27: 46073 | B27: Миржалол | C27: Аванс | D27: 400000 | F27: =IF(A27<>"", D27 / VLOOKUP(A27, 'Курс валют'!$A:$D, 4, 0), "")+Таблица4[[#This Row],[Столбец5]] -> 33.333333
A28: 46080 | B28: Миржалол | C28: Аванс | E28: 100 | F28: =IF(A28<>"", D28 / VLOOKUP(A28, 'Курс валют'!$A:$D, 4, 0), "")+Таблица4[[#This Row],[Столбец5]] -> 100
A29: 46085 | B29: Миржалол | C29: зарплата | D29: 2400000 | F29: =IF(A29<>"", D29 / VLOOKUP(A29, 'Курс валют'!$A:$D, 4, 0), "")+Таблица4[[#This Row],[Столбец5]] -> 198.6755
A30: 46085 | B30: Охрана | C30: зарплата | D30: 7000000 | F30: =IF(A30<>"", D30 / VLOOKUP(A30, 'Курс валют'!$A:$D, 4, 0), "")+Таблица4[[#This Row],[Столбец5]] -> 579.4702
A31: 46085 | B31: Нурсаид | C31: зарплата | D31: 5500000 | F31: =IF(A31<>"", D31 / VLOOKUP(A31, 'Курс валют'!$A:$D, 4, 0), "")+Таблица4[[#This Row],[Столбец5]] -> 455.29801
A32: 46085 | B32: Повар | C32: зарплата | D32: 5000000 | F32: =IF(A32<>"", D32 / VLOOKUP(A32, 'Курс валют'!$A:$D, 4, 0), "")+Таблица4[[#This Row],[Столбец5]] -> 413.90728
A33: 46085 | B33: Нурсаид | C33: зарплата | D33: 5500000 | F33: =IF(A33<>"", D33 / VLOOKUP(A33, 'Курс валют'!$A:$D, 4, 0), "")+Таблица4[[#This Row],[Столбец5]] -> 455.29801
A34: 46085 | B34: Санжар | C34: зарплата | D34: 3500000 | F34: =IF(A34<>"", D34 / VLOOKUP(A34, 'Курс валют'!$A:$D, 4, 0), "")+Таблица4[[#This Row],[Столбец5]] -> 289.7351
A35: 46097 | B35: Миржалол | C35: Аванс | D35: 300000 | F35: =IF(A35<>"", D35 / VLOOKUP(A35, 'Курс валют'!$A:$D, 4, 0), "")+Таблица4[[#This Row],[Столбец5]] -> 25
A36: 46104 | B36: Миржалол | C36: Аванс | D36: 400000 | F36: =IF(A36<>"", D36 / VLOOKUP(A36, 'Курс валют'!$A:$D, 4, 0), "")+Таблица4[[#This Row],[Столбец5]] -> 33.112583
A37: 46112 | B37: Миржалол | C37: Аванс | E37: 100 | F37: =IF(A37<>"", D37 / VLOOKUP(A37, 'Курс валют'!$A:$D, 4, 0), "")+Таблица4[[#This Row],[Столбец5]] -> 100
A38: 46113 | B38: Миржалол | C38: Аванс | D38: 200000 | F38: =IF(A38<>"", D38 / VLOOKUP(A38, 'Курс валют'!$A:$D, 4, 0), "")+Таблица4[[#This Row],[Столбец5]] -> 16.528926
A39: 46119 | B39: Миржалол | C39: зарплата | D39: 1900000 | F39: =IF(A39<>"", D39 / VLOOKUP(A39, 'Курс валют'!$A:$D, 4, 0), "")+Таблица4[[#This Row],[Столбец5]] -> 157.02479
A40: 46119 | B40: Нурсаид | C40: зарплата | D40: 5500000 | F40: =IF(A40<>"", D40 / VLOOKUP(A40, 'Курс валют'!$A:$D, 4, 0), "")+Таблица4[[#This Row],[Столбец5]] -> 454.54545
A41: 46119 | B41: Санжар | C41: зарплата | D41: 3500000 | F41: =IF(A41<>"", D41 / VLOOKUP(A41, 'Курс валют'!$A:$D, 4, 0), "")+Таблица4[[#This Row],[Столбец5]] -> 289.2562
A42: 46127 | B42: Миржалол | C42: Аванс | D42: 500000 | F42: =IF(A42<>"", D42 / VLOOKUP(A42, 'Курс валют'!$A:$D, 4, 0), "")+Таблица4[[#This Row],[Столбец5]] -> 41.666667
A43: 46147 | B43: Миржалол | C43: зарплата | D43: 3500000 | F43: =IF(A43<>"", D43 / VLOOKUP(A43, 'Курс валют'!$A:$D, 4, 0), "")+Таблица4[[#This Row],[Столбец5]] -> 291.66667
A44: 46147 | B44: Нурсаид | C44: зарплата | D44: 5500000 | F44: =IF(A44<>"", D44 / VLOOKUP(A44, 'Курс валют'!$A:$D, 4, 0), "")+Таблица4[[#This Row],[Столбец5]] -> 458.33333
A45: 46147 | B45: Санжар | C45: зарплата | D45: 3500000 | F45: =IF(A45<>"", D45 / VLOOKUP(A45, 'Курс валют'!$A:$D, 4, 0), "")+Таблица4[[#This Row],[Столбец5]] -> 291.66667
A46: 46147 | B46: Миролим | C46: зарплата | D46: 3500000 | F46: =IF(A46<>"", D46 / VLOOKUP(A46, 'Курс валют'!$A:$D, 4, 0), "")+Таблица4[[#This Row],[Столбец5]] -> 291.66667
A47: 46158 | B47: Миржалол | C47: Аванс | D47: 500000 | F47: =IF(A47<>"", D47 / VLOOKUP(A47, 'Курс валют'!$A:$D, 4, 0), "")+Таблица4[[#This Row],[Столбец5]] -> 41.322314
A48: 46161 | B48: Миржалол | C48: зарплата | E48: 400 | F48: =IF(A48<>"", D48 / VLOOKUP(A48, 'Курс валют'!$A:$D, 4, 0), "")+Таблица4[[#This Row],[Столбец5]] -> 400
F49: =IF(A49<>"", D49 / VLOOKUP(A49, 'Курс валют'!$A:$D, 4, 0), "")+Таблица4[[#This Row],[Столбец5]] -> #VALUE!
F50: =IF(A50<>"", D50 / VLOOKUP(A50, 'Курс валют'!$A:$D, 4, 0), "")+Таблица4[[#This Row],[Столбец5]] -> #VALUE!
F51: =IF(A51<>"", D51 / VLOOKUP(A51, 'Курс валют'!$A:$D, 4, 0), "")+Таблица4[[#This Row],[Столбец5]] -> #VALUE!
F52: =IF(A52<>"", D52 / VLOOKUP(A52, 'Курс валют'!$A:$D, 4, 0), "")+Таблица4[[#This Row],[Столбец5]] -> #VALUE!
F53: =IF(A53<>"", D53 / VLOOKUP(A53, 'Курс валют'!$A:$D, 4, 0), "")+Таблица4[[#This Row],[Столбец5]] -> #VALUE!
F54: =IF(A54<>"", D54 / VLOOKUP(A54, 'Курс валют'!$A:$D, 4, 0), "")+Таблица4[[#This Row],[Столбец5]] -> #VALUE!
F55: =IF(A55<>"", D55 / VLOOKUP(A55, 'Курс валют'!$A:$D, 4, 0), "")+Таблица4[[#This Row],[Столбец5]] -> #VALUE!
F56: =IF(A56<>"", D56 / VLOOKUP(A56, 'Курс валют'!$A:$D, 4, 0), "")+Таблица4[[#This Row],[Столбец5]] -> #VALUE!

Sheet Расходы
